Workbook

Sheet UBER 2025
M1: -10
A2: SEM | B2: CONDUCTOR | C2: AUTO | D2: TAG | E2: SOCIO | F2: PLATAFORMA | G2: APP | H2: GANANCIA | I2: IMPUESTOS | J2: P. AJUSANT | K2: SEGURO | L2: EFECTIVO | M2: PAGO A TERCEROS | N2: TAG | O2: UBER tot | P2: RENTA | Q2: SEM PASADA | R2: FIANZA | S2: MULTA | T2: HOJALATERO | U2: DESCUENTOS | V2: FA | W2: TOTAL | X2: PAGOS | Y2: DEVOLUCIONES | Z2: PAGADO | AA2: ADEUDO | AB2: GANANCIAS TOTALES | AC2: COMENTARIOS
A3: 1 | B3: ADOLFO LOPEZ MARTINEZ | C3: AVEO|2021|OCRE|NEB156A | D3: OHLM023012552 | E3: ASHC | F3: IVETH | G3: UBER | H3: 1943.26 | I3: -16 | J3: 0 | K3: 0 | L3: -758.4 | M3: =-38.8652+32 -> -6.8652 | N3: 0 | O3: =SUM(H3:N3) -> 1161.9948 | P3: -2142.85 | Q3: 0 | R3: 0 | S3: 0 | T3: 0 | U3: 0 | V3: 0 | W3: =+O3+SUM(P3:V3) -> -980.8552 | X3: =IF(W3>=0,W3,0) -> 0 | Y3: =IF(W3<=0,W3,0) -> -980.8552 | Z3: 981 | AA3: =+Y3+Z3 -> 0.1448 | AB3: =+O3-X3+Z3+AA3 -> 2143.1396 | AD3: NEB156A | AE3: =AD3&A3 -> NEB156A1
A4: 1 | B4: ARACELI CASTILLO GUERRERO | C4: AVEO|2018|GRIS|X59AWG | D4: - | E4: ASHC | F4: ASHC | G4: UBER | H4: 6825.48 | I4: -448 | J4: 0 | K4: 0 | L4: -1537.44 | M4: -136.5096 | N4: 0 | O4: =SUM(H4:N4) -> 4703.5304 | P4: -2142.85 | Q4: 0 | R4: 0 | S4: 0 | T4: 0 | U4: 0 | V4: 0 | W4: =+O4+SUM(P4:V4) -> 2560.6804 | X4: =IF(W4>=0,W4,0) -> 2560.6804 | Y4: =IF(W4<=0,W4,0) -> 0 | Z4: 0 | AA4: =+Y4+Z4 -> 0 | AB4: =+O4-X4+Z4+AA4 -> 2142.85 | AD4: =VLOOKUP($C4,'[1]CTRL AUTOS'!$E:$AH,2,0) -> X59AWG | AE4: =AD4&A4 -> X59AWG1
A5: 1 | B5: CESAR PIÑA BARONA | C5: HYUNDAI|2022|PLATA|D40BKD | D5: OHLM023658024 | E5: ASHC | F5: IVETH | G5: UBER | H5: 0 | I5: 0 | J5: 0 | K5: 0 | L5: 0 | M5: 0 | N5: 0 | O5: =SUM(H5:N5) -> 0 | P5: -2142.85 | Q5: -67 | R5: 0 | S5: 0 | T5: 0 | U5: 0 | V5: 0 | W5: =+O5+SUM(P5:V5) -> -2209.85 | X5: =IF(W5>=0,W5,0) -> 0 | Y5: =IF(W5<=0,W5,0) -> -2209.85 | Z5: 2210 | AA5: =+Y5+Z5 -> 0.15 | AB5: =+O5-X5+Z5+AA5 -> 2210.15 | AD5: =VLOOKUP($C5,'[1]CTRL AUTOS'!$E:$AH,2,0) -> D40BKD | AE5: =AD5&A5 -> D40BKD1
A6: 1 | B6: CLAUDIA LEAÑOS | C6: KIA RIO|2017|ROJO|MYE912A | D6: - | E6: U64 | F6: ASHC | G6: UBER | H6: 3855.54 | I6: -30.4 | J6: 0 | K6: 0 | L6: -2145.89 | M6: -77.1108 | N6: 0 | O6: =SUM(H6:N6) -> 1602.1392 | P6: -2142.85 | Q6: -510.28 | R6: 0 | S6: 0 | T6: 0 | U6: 0 | V6: 0 | W6: =+O6+SUM(P6:V6) -> -1050.9908 | X6: =IF(W6>=0,W6,0) -> 0 | Y6: =IF(W6<=0,W6,0) -> -1050.9908 | Z6: 1051 | AA6: =+Y6+Z6 -> 0.0092 | AB6: =+O6-X6+Z6+AA6 -> 2653.1484 | AD6: =VLOOKUP($C6,'[1]CTRL AUTOS'!$E:$AH,2,0) -> MYE912A | AE6: =AD6&A6 -> MYE912A1
A7: 1 | B7: IVAN MOGUEL PULIDO | C7: VERSA|2023|PLATA|NCT814A | D7: OHLM023012487 | E7: ASHC | F7: ASHC | G7: UBER | H7: 3884.89 | I7: 0 | J7: 0 | K7: 0 | L7: -2355.1 | M7: -90.2478 | N7: -70.97 | O7: =SUM(H7:N7) -> 1368.5722 | P7: -714.28 | Q7: 0 | R7: 0 | S7: 0 | T7: -500 | U7: 0 | V7: 0 | W7: =+O7+SUM(P7:V7) -> 154.2922 | X7: =IF(W7>=0,W7,0) -> 154.2922 | Y7: =IF(W7<=0,W7,0) -> 0 | Z7: 0 | AA7: =+Y7+Z7 -> 0 | AB7: =+O7-X7+Z7+AA7 -> 1214.28 | AD7: =VLOOKUP($C7,'[1]CTRL AUTOS'!$E:$AH,2,0) -> NCT814A | AE7: =AD7&A7 -> NCT814A1
A8: 1 | B8: JESUS AURELIO NUNGARAY CASTILLO | C8: VENTO|2020|GRIS|R66BER | D8: - | E8: ASHC | F8: ASHC | G8: UBER | H8: 4885.68 | I8: 0 | J8: 0 | K8: 0 | L8: -2620.14 | M8: -97.7136 | N8: 0 | O8: =SUM(H8:N8) -> 2167.8264 | P8: -2142.85 | Q8: -683.71 | R8: 0 | S8: 0 | T8: 0 | U8: 0 | V8: 0 | W8: =+O8+SUM(P8:V8) -> -658.7336 | X8: =IF(W8>=0,W8,0) -> 0 | Y8: =IF(W8<=0,W8,0) -> -658.7336 | Z8: 659 | AA8: =+Y8+Z8 -> 0.2664 | AB8: =+O8-X8+Z8+AA8 -> 2827.0928 | AD8: =VLOOKUP($C8,'[1]CTRL AUTOS'!$E:$AH,2,0) -> R66BER | AE8: =AD8&A8 -> R66BER1
A9: 1 | B9: JORGE VAZQUEZ HERNANDEZ | C9: AVEO|2018|GRIS|X59AWG | D9: - | E9: ASHC | F9: ASHC | G9: UBER | H9: 9781.33 | I9: 0 | J9: 0 | K9: 0 | L9: -4655.05 | M9: -195.6266 | N9: 0 | O9: =SUM(H9:N9) -> 4930.6534 | P9: -2142.85 | Q9: 0 | R9: 0 | S9: 0 | T9: 0 | U9: 0 | V9: 0 | W9: =+O9+SUM(P9:V9) -> 2787.8034 | X9: =IF(W9>=0,W9,0) -> 2787.8034 | Y9: =IF(W9<=0,W9,0) -> 0 | Z9: 0 | AA9: =+Y9+Z9 -> 0 | AB9: =+O9-X9+Z9+AA9 -> 2142.85 | AD9: =VLOOKUP($C9,'[1]CTRL AUTOS'!$E:$AH,2,0) -> X59AWG | AE9: =AD9&A9 -> X59AWG1
A10: 1 | B10: JOSE GUADALUPE GARCIA MORALES | C10: MARCH|2020|TURQ|N15BKD | D10: OHLM031409071 | E10: ASHC | F10: ASHC | G10: UBER | H10: 5089.85 | I10: -24 | J10: 0 | K10: 0 | L10: -3520.73 | M10: =-101.797+48 -> -53.797 | N10: 0 | O10: =SUM(H10:N10) -> 1491.323 | P10: -2142.85 | Q10: 0 | R10: -500 | S10: 0 | T10: 0 | U10: 0 | V10: 0 | W10: =+O10+SUM(P10:V10) -> -1151.527 | X10: =IF(W10>=0,W10,0) -> 0 | Y10: =IF(W10<=0,W10,0) -> -1151.527 | Z10: 1152 | AA10: =+Y10+Z10 -> 0.473 | AB10: =+O10-X10+Z10+AA10 -> 2643.796 | AD10: =VLOOKUP($C10,'[1]CTRL AUTOS'!$E:$AH,2,0) -> N15BKD | AE10: =AD10&A10 -> N15BKD1
A11: 1 | B11: JOSE JUAN HERNANDEZ MEJIA | C11: VERSA|2017|ACERO|X24APU | D11: OHLM023720345 | E11: ASHC | F11: ASHC | G11: UBER | H11: 4940.33 | I11: -38.4 | J11: 0 | K11: 0 | L11: -2048.73 | M11: =-98.8066+77 -> -21.8066 | N11: 0 | O11: =SUM(H11:N11) -> 2831.3934 | P11: -2142.85 | Q11: -375.31 | R11: -500 | S11: 0 | T11: 0 | U11: 0 | V11: 0 | W11: =+O11+SUM(P11:V11) -> -186.7666 | X11: =IF(W11>=0,W11,0) -> 0 | Y11: =IF(W11<=0,W11,0) -> -186.7666 | Z11: 187 | AA11: =+Y11+Z11 -> 0.2334 | AB11: =+O11-X11+Z11+AA11 -> 3018.6268 | AD11: X24APU | AE11: =AD11&A11 -> X24APU1
A12: 1 | B12: OSCAR BLANCAS NORIEGA | C12: VENTO|2017|GRIS|NZV7888 | D12: OHLM023720279 | E12: ASHC | F12: ASHC | G12: UBER | H12: 4068.3 | I12: -38.4 | J12: 0 | K12: 0 | L12: -935.09 | M12: =-81.366+77 -> -4.366 | N12: 0 | O12: =SUM(H12:N12) -> 3090.444 | P12: -1971.42 | Q12: -1063 | R12: -500 | S12: 0 | T12: 0 | U12: 0 | V12: 0 | W12: =+O12+SUM(P12:V12) -> -443.976 | X12: =IF(W12>=0,W12,0) -> 0 | Y12: =IF(W12<=0,W12,0) -> -443.976 | Z12: 444 | AA12: =+Y12+Z12 -> 0.024 | AB12: =+O12-X12+Z12+AA12 -> 3534.468 | AD12: BAJA DE PLACAS | AE12: =AD12&A12 -> BAJA DE PLACAS1
A13: 1 | B13: ULISES ITIEL CASTILLO AVILA | C13: KIA RIO|2020|GRIS|NCK475B | D13: OHLM031397326 | E13: ASHC | F13: IVETH | G13: UBER | H13: 5393.23 | I13: -68.8 | J13: 0 | K13: 0 | L13: -2447.29 | M13: -107.8646 | N13: 0 | O13: =SUM(H13:N13) -> 2769.2754 | P13: -2142.85 | Q13: 0 | R13: 0 | S13: 0 | T13: 0 | U13: 0 | V13: 0 | W13: =+O13+SUM(P13:V13) -> 626.4254 | X13: =IF(W13>=0,W13,0) -> 626.4254 | Y13: =IF(W13<=0,W13,0) -> 0 | Z13: 0 | AA13: =+Y13+Z13 -> 0 | AB13: =+O13-X13+Z13+AA13 -> 2142.85 | AD13: =VLOOKUP($C13,'[1]CTRL AUTOS'!$E:$AH,2,0) -> NCK475B | AE13: =AD13&A13 -> NCK475B1
A14: 2 | B14: ABRAHAM ESCOBEDO ESCALANTE | C14: BEAT|2020|GRIS|NFN014B | D14: - | E14: U64 | F14: ASHC | G14: UBER | H14: 1382.8 | I14: -22.4 | J14: 0 | K14: 0 | L14: -723.89 | M14: -27.656 | N14: 0 | O14: =SUM(H14:N14) -> 608.854 | P14: -1428.56 | Q14: 0 | R14: 0 | S14: 0 | T14: 0 | U14: 0 | V14: 0 | W14: =+O14+SUM(P14:V14) -> -819.706 | X14: =IF(W14>=0,W14,0) -> 0 | Y14: =IF(W14<=0,W14,0) -> -819.706 | Z14: 0 | AA14: =+Y14+Z14 -> -819.706 | AB14: =+O14-X14+Z14+AA14 -> -210.852 | AC14: PÉRDIDA | AD14: =VLOOKUP($C14,'[1]CTRL AUTOS'!$E:$AH,2,0) -> NFN014B | AE14: =AD14&A14 -> NFN014B2
A15: 2 | B15: ADOLFO LOPEZ MARTINEZ | C15: AVEO|2021|OCRE|NEB156A | D15: OHLM023012552 | E15: ASHC | F15: IVETH | G15: UBER | H15: 0 | I15: 0 | J15: 0 | K15: 0 | L15: 0 | M15: 0 | N15: 0 | O15: =SUM(H15:N15) -> 0 | P15: -2500 | Q15: 0 | R15: 0 | S15: 0 | T15: 0 | U15: 0 | V15: 0 | W15: =+O15+SUM(P15:V15) -> -2500 | X15: =IF(W15>=0,W15,0) -> 0 | Y15: =IF(W15<=0,W15,0) -> -2500 | Z15: 2500 | AA15: =+Y15+Z15 -> 0 | AB15: =+O15-X15+Z15+AA15 -> 2500 | AD15: NEB156A | AE15: =AD15&A15 -> NEB156A2
A16: 2 | B16: ARACELI CASTILLO GUERRERO | C16: AVEO|2018|GRIS|X59AWG | D16: - | E16: ASHC | F16: ASHC | G16: UBER | H16: 3130.3 | I16: 0 | J16: 0 | K16: 0 | L16: -1220.45 | M16: -62.606 | N16: 0 | O16: =SUM(H16:N16) -> 1847.244 | P16: -2500 | Q16: 0 | R16: 0 | S16: 0 | T16: 0 | U16: 0 | V16: 0 | W16: =+O16+SUM(P16:V16) -> -652.756 | X16: =IF(W16>=0,W16,0) -> 0 | Y16: =IF(W16<=0,W16,0) -> -652.756 | Z16: 653 | AA16: =+Y16+Z16 -> 0.244 | AB16: =+O16-X16+Z16+AA16 -> 2500.488 | AD16: =VLOOKUP($C16,'[1]CTRL AUTOS'!$E:$AH,2,0) -> X59AWG | AE16: =AD16&A16 -> X59AWG2
A17: 2 | B17: CESAR PIÑA BARONA | C17: HYUNDAI|2022|PLATA|D40BKD | D17: OHLM023658024 | E17: ASHC | F17: IVETH | G17: UBER | H17: 0 | I17: 0 | J17: 0 | K17: 0 | L17: 0 | M17: 0 | N17: 0 | O17: =SUM(H17:N17) -> 0 | P17: -2500 | Q17: 0 | R17: 0 | S17: 0 | T17: 0 | U17: 0 | V17: 0 | W17: =+O17+SUM(P17:V17) -> -2500 | X17: =IF(W17>=0,W17,0) -> 0 | Y17: =IF(W17<=0,W17,0) -> -2500 | Z17: 2500 | AA17: =+Y17+Z17 -> 0 | AB17: =+O17-X17+Z17+AA17 -> 2500 | AD17: =VLOOKUP($C17,'[1]CTRL AUTOS'!$E:$AH,2,0) -> D40BKD | AE17: =AD17&A17 -> D40BKD2
A18: 2 | B18: CLAUDIA LEAÑOS | C18: KIA RIO|2017|ROJO|MYE912A | D18: - | E18: U64 | F18: ASHC | G18: UBER | H18: 3759.89 | I18: -60.8 | J18: 0 | K18: 0 | L18: -1578.07 | M18: -75.1978 | N18: 0 | O18: =SUM(H18:N18) -> 2045.8222 | P18: -2500 | Q18: 0 | R18: 0 | S18: 0 | T18: 0 | U18: 0 | V18: 0 | W18: =+O18+SUM(P18:V18) -> -454.1778 | X18: =IF(W18>=0,W18,0) -> 0 | Y18: =IF(W18<=0,W18,0) -> -454.1778 | Z18: 0 | AA18: =+Y18+Z18 -> -454.1778 | AB18: =+O18-X18+Z18+AA18 -> 1591.6444 | AC18: PÉRDIDA | AD18: =VLOOKUP($C18,'[1]CTRL AUTOS'!$E:$AH,2,0) -> MYE912A | AE18: =AD18&A18 -> MYE912A2
A19: 2 | B19: DIEGO SANCHEZ | C19: VENTO|2020|GRIS|R66BER | D19: OHLM023720329 | E19: ASHC | F19: ASHC | G19: UBER | H19: 2574.35 | I19: 0 | J19: 0 | K19: 0 | L19: -1659.48 | M19: -51.487 | N19: 0 | O19: =SUM(H19:N19) -> 863.383 | P19: -1428.56 | Q19: 0 | R19: -500 | S19: 0 | T19: 0 | U19: 0 | V19: 0 | W19: =+O19+SUM(P19:V19) -> -1065.177 | X19: =IF(W19>=0,W19,0) -> 0 | Y19: =IF(W19<=0,W19,0) -> -1065.177 | Z19: 1065 | AA19: =+Y19+Z19 -> -0.177 | AB19: =+O19-X19+Z19+AA19 -> 1928.206 | AD19: =VLOOKUP($C19,'[1]CTRL AUTOS'!$E:$AH,2,0) -> R66BER | AE19: =AD19&A19 -> R66BER2
A20: 2 | B20: EDGAR GEOVANY URIBE | C20: AVEO|2019|PLATA|NEL860A | D20: OHLM023720337 | E20: ASHC | F20: ASHC | G20: UBER | H20: 4536.98 | I20: -119.2 | J20: 0 | K20: 0 | L20: -898.58 | M20: -113.3596 | N20: 0 | O20: =SUM(H20:N20) -> 3405.8404 | P20: -2500 | Q20: 0 | R20: 0 | S20: -500 | T20: 0 | U20: 0 | V20: 0 | W20: =+O20+SUM(P20:V20) -> 405.8404 | X20: =IF(W20>=0,W20,0) -> 405.8404 | Y20: =IF(W20<=0,W20,0) -> 0 | Z20: 0 | AA20: =+Y20+Z20 -> 0 | AB20: =+O20-X20+Z20+AA20 -> 3000 | AD20: =VLOOKUP($C20,'[1]CTRL AUTOS'!$E:$AH,2,0) -> NEL860A | AE20: =AD20&A20 -> NEL860A2
A21: 2 | B21: IRAM HERNANDEZ | C21: AVEO|2022|AZUL|MUF515A | D21: OHLM023720311 | E21: ASHC | F21: ASHC | G21: UBER | H21: 6165.24 | I21: 0 | J21: 0 | K21: 0 | L21: -2465.51 | M21: -123.3048 | N21: 0 | O21: =SUM(H21:N21) -> 3576.4252 | P21: -2500 | Q21: 0 | R21: 0 | S21: -500 | T21: 0 | U21: 0 | V21: 0 | W21: =+O21+SUM(P21:V21) -> 576.4252 | X21: =IF(W21>=0,W21,0) -> 576.4252 | Y21: =IF(W21<=0,W21,0) -> 0 | Z21: 0 | AA21: =+Y21+Z21 -> 0 | AB21: =+O21-X21+Z21+AA21 -> 3000 | AD21: =VLOOKUP($C21,'[1]CTRL AUTOS'!$E:$AH,2,0) -> MUF515A | AE21: =AD21&A21 -> MUF515A2
A22: 2 | B22: IVAN MOGUEL PULIDO | C22: VERSA|2023|PLATA|NCT814A | D22: OHLM023012487 | E22: ASHC | F22: ASHC | G22: UBER | H22: 11072.8 | I22: -262.4 | J22: 0 | K22: 0 | L22: -4296.05 | M22: -221.456 | N22: -46 | O22: =SUM(H22:N22) -> 6246.894 | P22: -2500 | Q22: 0 | R22: 0 | S22: 0 | T22: -500 | U22: 0 | V22: 0 | W22: =+O22+SUM(P22:V22) -> 3246.894 | X22: =IF(W22>=0,W22,0) -> 3246.894 | Y22: =IF(W22<=0,W22,0) -> 0 | Z22: 0 | AA22: =+Y22+Z22 -> 0 | AB22: =+O22-X22+Z22+AA22 -> 3000 | AD22: =VLOOKUP($C22,'[1]CTRL AUTOS'!$E:$AH,2,0) -> NCT814A | AE22: =AD22&A22 -> NCT814A2
A23: 2 | B23: JESUS AURELIO NUNGARAY CASTILLO | C23: VENTO|2020|GRIS|R66BER | D23: - | E23: ASHC | F23: ASHC | G23: UBER | H23: 2251.02 | I23: 0 | J23: 0 | K23: 0 | L23: -1814.27 | M23: -45.0204 | N23: -127.82 | O23: =SUM(H23:N23) -> 263.9096 | P23: -714.28 | Q23: 0 | R23: 0 | S23: 0 | T23: 0 | U23: 0 | V23: 0 | W23: =+O23+SUM(P23:V23) -> -450.3704 | X23: =IF(W23>=0,W23,0) -> 0 | Y23: =IF(W23<=0,W23,0) -> -450.3704 | Z23: 450 | AA23: =+Y23+Z23 -> -0.3704 | AB23: =+O23-X23+Z23+AA23 -> 713.5392 | AD23: =VLOOKUP($C23,'[1]CTRL AUTOS'!$E:$AH,2,0) -> R66BER | AE23: =AD23&A23 -> R66BER2
A24: 2 | B24: JORGE VAZQUEZ HERNANDEZ | C24: AVEO|2018|GRIS|X59AWG | D24: - | E24: ASHC | F24: ASHC | G24: UBER | H24: 3233.43 | I24: 0 | J24: 0 | K24: 0 | L24: -628.14 | M24: -64.6686 | N24: 0 | O24: =SUM(H24:N24) -> 2540.6214 | P24: -2500 | Q24: 0 | R24: 0 | S24: 0 | T24: 0 | U24: 0 | V24: 0 | W24: =+O24+SUM(P24:V24) -> 40.6214 | X24: =IF(W24>=0,W24,0) -> 40.6214 | Y24: =IF(W24<=0,W24,0) -> 0 | Z24: 0 | AA24: =+Y24+Z24 -> 0 | AB24: =+O24-X24+Z24+AA24 -> 2500 | AD24: =VLOOKUP($C24,'[1]CTRL AUTOS'!$E:$AH,2,0) -> X59AWG | AE24: =AD24&A24 -> X59AWG2
A25: 2 | B25: JOSE GUADALUPE GARCIA MORALES | C25: MARCH|2020|TURQ|N15BKD | D25: OHLM031409071 | E25: ASHC | F25: ASHC | G25: UBER | H25: 5208.21 | I25: 0 | J25: 0 | K25: 0 | L25: -3087.32 | M25: -104.1642 | N25: 0 | O25: =SUM(H25:N25) -> 2016.7258 | P25: -2500 | Q25: -1151.53 | R25: -500 | S25: 0 | T25: 0 | U25: 0 | V25: 0 | W25: =+O25+SUM(P25:V25) -> -2134.8042 | X25: =IF(W25>=0,W25,0) -> 0 | Y25: =IF(W25<=0,W25,0) -> -2134.8042 | Z25: 2135 | AA25: =+Y25+Z25 -> 0.1958 | AB25: =+O25-X25+Z25+AA25 -> 4151.9216 | AD25: =VLOOKUP($C25,'[1]CTRL AUTOS'!$E:$AH,2,0) -> N15BKD | AE25: =AD25&A25 -> N15BKD2
A26: 2 | B26: JOSE GUILLERMO HERNANDEZ RAMIREZ | C26: AVEO|2018|ROJO|R51BKD | D26: OHLM017365206 | E26: U64 | F26: ASHC | G26: UBER | H26: 6685.99 | I26: -164.8 | J26: 0 | K26: 0 | L26: -3647.5 | M26: -133.7198 | N26: 0 | O26: =SUM(H26:N26) -> 2739.9702 | P26: -2500 | Q26: 0 | R26: 0 | S26: 0 | T26: 0 | U26: 0 | V26: 0 | W26: =+O26+SUM(P26:V26) -> 239.9702 | X26: =IF(W26>=0,W26,0) -> 239.9702 | Y26: =IF(W26<=0,W26,0) -> 0 | Z26: 0 | AA26: =+Y26+Z26 -> 0 | AB26: =+O26-X26+Z26+AA26 -> 2500 | AD26: =VLOOKUP($C26,'[1]CTRL AUTOS'!$E:$AH,2,0) -> R51BKD | AE26: =AD26&A26 -> R51BKD2
A27: 2 | B27: JOSE JUAN HERNANDEZ MEJIA | C27: VERSA|2017|ACERO|X24APU | D27: OHLM023720345 | E27: ASHC | F27: ASHC | G27: UBER | H27: 3188.12 | I27: -48 | J27: 0 | K27: 0 | L27: -1867.2 | M27: -63.7624 | N27: 0 | O27: =SUM(H27:N27) -> 1209.1576 | P27: -2500 | Q27: -186.97 | R27: -500 | S27: 0 | T27: 0 | U27: 0 | V27: 0 | W27: =+O27+SUM(P27:V27) -> -1977.8124 | X27: =IF(W27>=0,W27,0) -> 0 | Y27: =IF(W27<=0,W27,0) -> -1977.8124 | Z27: 1882 | AA27: =+Y27+Z27 -> -95.8124 | AB27: =+O27-X27+Z27+AA27 -> 2995.3452 | AD27: X24APU | AE27: =AD27&A27 -> X24APU2
A28: 2 | B28: OSCAR BLANCAS NORIEGA | C28: VENTO|2017|GRIS|NZV7888 | D28: OHLM023720279 | E28: ASHC | F28: ASHC | G28: UBER | H28: 4151.87 | I28: -81.6 | J28: 0 | K28: 0 | L28: -1247.87 | M28: -83.0374 | N28: 0 | O28: =SUM(H28:N28) -> 2739.3626 | P28: -2300 | Q28: 0 | R28: -339 | S28: -257 | T28: 0 | U28: 0 | V28: 0 | W28: =+O28+SUM(P28:V28) -> -156.6374 | X28: =IF(W28>=0,W28,0) -> 0 | Y28: =IF(W28<=0,W28,0) -> -156.6374 | Z28: 157 | AA28: =+Y28+Z28 -> 0.3626 | AB28: =+O28-X28+Z28+AA28 -> 2896.7252 | AD28: BAJA DE PLACAS | AE28: =AD28&A28 -> BAJA DE PLACAS2
A29: 2 | B29: ULISES ITIEL CASTILLO AVILA | C29: KIA RIO|2020|GRIS|NCK475B | D29: OHLM031397326 | E29: ASHC | F29: IVETH | G29: UBER | H29: 7618.92 | I29: -139.2 | J29: 0 | K29: 0 | L29: -4430.72 | M29: -152.3784 | N29: 0 | O29: =SUM(H29:N29) -> 2896.6216 | P29: -2500 | Q29: 0 | R29: 0 | S29: 0 | T29: 0 | U29: 0 | V29: 0 | W29: =+O29+SUM(P29:V29) -> 396.6216 | X29: =IF(W29>=0,W29,0) -> 396.6216 | Y29: =IF(W29<=0,W29,0) -> 0 | Z29: 0 | AA29: =+Y29+Z29 -> 0 | AB29: =+O29-X29+Z29+AA29 -> 2500 | AD29: =VLOOKUP($C29,'[1]CTRL AUTOS'!$E:$AH,2,0) -> NCK475B | AE29: =AD29&A29 -> NCK475B2
A30: 3 | B30: ABRAHAM ESCOBEDO ESCALANTE | C30: BEAT|2020|GRIS|NFN014B | D30: - | E30: U64 | F30: ASHC | G30: UBER | H30: 2639.76 | I30: 0 | J30: 0 | K30: 0 | L30: -2186.24 | M30: -52.7952 | N30: 0 | O30: =SUM(H30:N30) -> 400.7248 | P30: -2500 | Q30: -35 | R30: 0 | S30: 0 | T30: 0 | U30: 0 | V30: 0 | W30: =+O30+SUM(P30:V30) -> -2134.2752 | X30: =IF(W30>=0,W30,0) -> 0 | Y30: =IF(W30<=0,W30,0) -> -2134.2752 | Z30: 0 | AA30: =+Y30+Z30 -> -2134.2752 | AB30: =+O30-X30+Z30+AA30 -> -1733.5504 | AC30: PÉRDIDA | AD30: =VLOOKUP($C30,'[1]CTRL AUTOS'!$E:$AH,2,0) -> NFN014B | AE30: =AD30&A30 -> NFN014B3
A31: 3 | B31: ADOLFO LOPEZ MARTINEZ | C31: AVEO|2021|OCRE|NEB156A | D31: OHLM023012552 | E31: ASHC | F31: ASHC | G31: UBER | H31: 50.31 | I31: 0 | J31: 0 | K31: 0 | L31: 0 | M31: 0 | N31: 0 | O31: =SUM(H31:N31) -> 50.31 | P31: -1071 | Q31: 0 | R31: 0 | S31: 0 | T31: 0 | U31: 0 | V31: 0 | W31: =+O31+SUM(P31:V31) -> -1020.69 | X31: =IF(W31>=0,W31,0) -> 0 | Y31: =IF(W31<=0,W31,0) -> -1020.69 | Z31: 1021 | AA31: =+Y31+Z31 -> 0.31 | AB31: =+O31-X31+Z31+AA31 -> 1071.62 | AD31: NEB156A | AE31: =AD31&A31 -> NEB156A3
A32: 3 | B32: ADOLFO LOPEZ MARTINEZ | C32: AVEO|2021|OCRE|NEB156A | D32: OHLM023012552 | E32: ASHC | F32: IVETH | G32: UBER | H32: 1787.03 | I32: 0 | J32: 0 | K32: 0 | L32: -586.14 | M32: -35.7406 | N32: 0 | O32: =SUM(H32:N32) -> 1165.1494 | P32: -1429 | Q32: 0 | R32: 0 | S32: 0 | T32: 0 | U32: 0 | V32: 0 | W32: =+O32+SUM(P32:V32) -> -263.8506 | X32: =IF(W32>=0,W32,0) -> 0 | Y32: =IF(W32<=0,W32,0) -> -263.8506 | Z32: 264 | AA32: =+Y32+Z32 -> 0.1494 | AB32: =+O32-X32+Z32+AA32 -> 1429.2988 | AD32: NEB156A | AE32: =AD32&A32 -> NEB156A3
A33: 3 | B33: ARACELI CASTILLO GUERRERO | C33: AVEO|2018|GRIS|X59AWG | D33: - | E33: ASHC | F33: ASHC | G33: UBER | H33: 3737.75 | I33: 0 | J33: 0 | K33: 0 | L33: -1707.4 | M33: -74.755 | N33: 0 | O33: =SUM(H33:N33) -> 1955.595 | P33: -2500 | Q33: 0 | R33: 0 | S33: 0 | T33: 0 | U33: 0 | V33: 0 | W33: =+O33+SUM(P33:V33) -> -544.405 | X33: =IF(W33>=0,W33,0) -> 0 | Y33: =IF(W33<=0,W33,0) -> -544.405 | Z33: 544 | AA33: =+Y33+Z33 -> -0.405 | AB33: =+O33-X33+Z33+AA33 -> 2499.19 | AD33: =VLOOKUP($C33,'[1]CTRL AUTOS'!$E:$AH,2,0) -> X59AWG | AE33: =AD33&A33 -> X59AWG3
A34: 3 | B34: CESAR PIÑA BARONA | C34: HYUNDAI|2022|PLATA|D40BKD | D34: OHLM023658024 | E34: ASHC | F34: ASHC | G34: UBER | H34: 0 | I34: 0 | J34: 0 | K34: 0 | L34: 0 | M34: 0 | N34: 0 | O34: =SUM(H34:N34) -> 0 | P34: -1071 | Q34: -1300 | R34: 0 | S34: 0 | T34: 0 | U34: 0 | V34: 0 | W34: =+O34+SUM(P34:V34) -> -2371 | X34: =IF(W34>=0,W34,0) -> 0 | Y34: =IF(W34<=0,W34,0) -> -2371 | Z34: 2371 | AA34: =+Y34+Z34 -> 0 | AB34: =+O34-X34+Z34+AA34 -> 2371 | AC34: PAGADO | AD34: =VLOOKUP($C34,'[1]CTRL AUTOS'!$E:$AH,2,0) -> D40BKD | AE34: =AD34&A34 -> D40BKD3
A35: 3 | B35: CESAR PIÑA BARONA | C35: HYUNDAI|2022|PLATA|D40BKD | D35: OHLM023658024 | E35: ASHC | F35: IVETH | G35: UBER | H35: 0 | I35: 0 | J35: 0 | K35: 0 | L35: 0 | M35: 0 | N35: 0 | O35: =SUM(H35:N35) -> 0 | P35: -1429 | Q35: 0 | R35: 0 | S35: 0 | T35: 0 | U35: 0 | V35: 0 | W35: =+O35+SUM(P35:V35) -> -1429 | X35: =IF(W35>=0,W35,0) -> 0 | Y35: =IF(W35<=0,W35,0) -> -1429 | Z35: 1429 | AA35: =+Y35+Z35 -> 0 | AB35: =+O35-X35+Z35+AA35 -> 1429 | AC35: PAGADO | AD35: =VLOOKUP($C35,'[1]CTRL AUTOS'!$E:$AH,2,0) -> D40BKD | AE35: =AD35&A35 -> D40BKD3
A36: 3 | B36: CLAUDIA LEAÑOS | C36: KIA RIO|2017|ROJO|MYE912A | D36: - | E36: U64 | F36: ASHC | G36: UBER | H36: 449.82 | I36: 0 | J36: 0 | K36: 0 | L36: -93.56 | M36: 0 | N36: 0 | O36: =SUM(H36:N36) -> 356.26 | P36: 0 | Q36: 0 | R36: 0 | S36: 0 | T36: 0 | U36: 0 | V36: 0 | W36: =+O36+SUM(P36:V36) -> 356.26 | X36: =IF(W36>=0,W36,0) -> 356.26 | Y36: =IF(W36<=0,W36,0) -> 0 | Z36: 0 | AA36: =+Y36+Z36 -> 0 | AB36: =+O36-X36+Z36+AA36 -> 0 | AD36: =VLOOKUP($C36,'[1]CTRL AUTOS'!$E:$AH,2,0) -> MYE912A | AE36: =AD36&A36 -> MYE912A3
A37: 3 | B37: DIEGO SANCHEZ | C37: VENTO|2020|GRIS|R66BER | D37: OHLM023720329 | E37: ASHC | F37: ASHC | G37: UBER | H37: 4532.44 | I37: 0 | J37: 0 | K37: 0 | L37: -2041.45 | M37: -101.0688 | N37: 0 | O37: =SUM(H37:N37) -> 2389.9212 | P37: -2500 | Q37: 0 | R37: -500 | S37: 0 | T37: 0 | U37: 0 | V37: 0 | W37: =+O37+SUM(P37:V37) -> -610.0788 | X37: =IF(W37>=0,W37,0) -> 0 | Y37: =IF(W37<=0,W37,0) -> -610.0788 | Z37: 620 | AA37: =+Y37+Z37 -> 9.9212 | AB37: =+O37-X37+Z37+AA37 -> 3019.8424 | AC37: PAGADO | 21 ENE | AD37: =VLOOKUP($C37,'[1]CTRL AUTOS'!$E:$AH,2,0) -> R66BER | AE37: =AD37&A37 -> R66BER3
A38: 3 | B38: EDGAR GEOVANY URIBE | C38: AVEO|2019|PLATA|NEL860A | D38: OHLM023720337 | E38: ASHC | F38: ASHC | G38: UBER | H38: 5544.83 | I38: -101.6 | J38: 0 | K38: 0 | L38: -1756.2 | M38: -137.71245 | N38: 0 | O38: =SUM(H38:N38) -> 3549.3175 | P38: -2500 | Q38: 0 | R38: 0 | S38: -500 | T38: 0 | U38: 0 | V38: 0 | W38: =+O38+SUM(P38:V38) -> 549.31755 | X38: =IF(W38>=0,W38,0) -> 549.31755 | Y38: =IF(W38<=0,W38,0) -> 0 | Z38: 0 | AA38: =+Y38+Z38 -> 0 | AB38: =+O38-X38+Z38+AA38 -> 3000 | AD38: =VLOOKUP($C38,'[1]CTRL AUTOS'!$E:$AH,2,0) -> NEL860A | AE38: =AD38&A38 -> NEL860A3
A39: 3 | B39: FERNANDO ESQUIVEL SOSA | C39: VENTO|2018|AMARILLO|PED1652 | D39: OHLM031409055 | E39: ASHC | F39: ASHC | G39: UBER | H39: 7403.76 | I39: -138.4 | J39: 0 | K39: 0 | L39: -1056.42 | M39: -148.0752 | N39: 0 | O39: =SUM(H39:N39) -> 6060.8648 | P39: -1968 | Q39: 0 | R39: -500 | S39: 0 | T39: 0 | U39: 0 | V39: 0 | W39: =+O39+SUM(P39:V39) -> 3592.8648 | X39: =IF(W39>=0,W39,0) -> 3592.8648 | Y39: =IF(W39<=0,W39,0) -> 0 | Z39: 0 | AA39: =+Y39+Z39 -> 0 | AB39: =+O39-X39+Z39+AA39 -> 2468 | AD39: =VLOOKUP($C39,'[1]CTRL AUTOS'!$E:$AH,2,0) -> #N/A | AE39: =AD39&A39 -> #N/A
A40: 3 | B40: IRAM HERNANDEZ | C40: AVEO|2022|AZUL|MUF515A | D40: OHLM023720311 | E40: ASHC | F40: ASHC | G40: UBER | H40: 5136.53 | I40: -54.31 | J40: 0 | K40: 0 | L40: -1437.61 | M40: -77.04795 | N40: -55 | O40: =SUM(H40:N40) -> 3512.562 | P40: -2500 | Q40: 0 | R40: 0 | S40: -300 | T40: 0 | U40: 0 | V40: 0 | W40: =+O40+SUM(P40:V40) -> 712.56205 | X40: =IF(W40>=0,W40,0) -> 712.56205 | Y40: =IF(W40<=0,W40,0) -> 0 | Z40: 0 | AA40: =+Y40+Z40 -> 0 | AB40: =+O40-X40+Z40+AA40 -> 2800 | AD40: =VLOOKUP($C40,'[1]CTRL AUTOS'!$E:$AH,2,0) -> MUF515A | AE40: =AD40&A40 -> MUF515A3
A41: 3 | B41: IVAN MOGUEL PULIDO | C41: VERSA|2023|PLATA|NCT814A | D41: OHLM023012487 | E41: ASHC | F41: ASHC | G41: UBER | H41: 9859.83 | I41: -121.6 | J41: 0 | K41: 0 | L41: -4486.28 | M41: -197.1966 | N41: -217.97 | O41: =SUM(H41:N41) -> 4836.7834 | P41: -2500 | Q41: -1500 | R41: 0 | S41: 0 | T41: -500 | U41: 0 | V41: 0 | W41: =+O41+SUM(P41:V41) -> 336.7834 | X41: =IF(W41>=0,W41,0) -> 336.7834 | Y41: =IF(W41<=0,W41,0) -> 0 | Z41: 0 | AA41: =+Y41+Z41 -> 0 | AB41: =+O41-X41+Z41+AA41 -> 4500 | AD41: =VLOOKUP($C41,'[1]CTRL AUTOS'!$E:$AH,2,0) -> NCT814A | AE41: =AD41&A41 -> NCT814A3
A42: 3 | B42: JORGE VAZQUEZ HERNANDEZ | C42: AVEO|2018|GRIS|X59AWG | D42: - | E42: ASHC | F42: ASHC | G42: UBER | H42: 861.11 | I42: 0 | J42: 0 | K42: 0 | L42: -251.63 | M42: -17.2222 | N42: 0 | O42: =SUM(H42:N42) -> 592.2578 | P42: -357.15 | Q42: 0 | R42: 0 | S42: 0 | T42: 0 | U42: 0 | V42: 0 | W42: =+O42+SUM(P42:V42) -> 235.1078 | X42: =IF(W42>=0,W42,0) -> 235.1078 | Y42: =IF(W42<=0,W42,0) -> 0 | Z42: 0 | AA42: =+Y42+Z42 -> 0 | AB42: =+O42-X42+Z42+AA42 -> 357.15 | AD42: =VLOOKUP($C42,'[1]CTRL AUTOS'!$E:$AH,2,0) -> X59AWG | AE42: =AD42&A42 -> X59AWG3
A43: 3 | B43: JOSE GUADALUPE GARCIA MORALES | C43: MARCH|2020|TURQ|N15BKD | D43: OHLM031409071 | E43: ASHC | F43: ASHC | G43: UBER | H43: 5945.25 | I43: 0 | J43: 0 | K43: 0 | L43: -2654.06 | M43: -90.41875 | N43: 0 | O43: =SUM(H43:N43) -> 3200.7713 | P43: -2500 | Q43: -1153 | R43: 0 | S43: 0 | T43: 0 | U43: 0 | V43: 0 | W43: =+O43+SUM(P43:V43) -> -452.22875 | X43: =IF(W43>=0,W43,0) -> 0 | Y43: =IF(W43<=0,W43,0) -> -452.22875 | Z43: 453 | AA43: =+Y43+Z43 -> 0.77125 | AB43: =+O43-X43+Z43+AA43 -> 3654.5425 | AD43: =VLOOKUP($C43,'[1]CTRL AUTOS'!$E:$AH,2,0) -> N15BKD | AE43: =AD43&A43 -> N15BKD3
A44: 3 | B44: JOSE GUILLERMO HERNANDEZ RAMIREZ | C44: AVEO|2018|ROJO|R51BKD | D44: OHLM017365206 | E44: U64 | F44: ASHC | G44: UBER | H44: 7475.53 | I44: -199.2 | J44: 0 | K44: 0 | L44: -3393.99 | M44: -149.5106 | N44: 0 | O44: =SUM(H44:N44) -> 3732.8294 | P44: -2500 | Q44: 0 | R44: 0 | S44: 0 | T44: -500 | U44: 0 | V44: 0 | W44: =+O44+SUM(P44:V44) -> 732.8294 | X44: =IF(W44>=0,W44,0) -> 732.8294 | Y44: =IF(W44<=0,W44,0) -> 0 | Z44: 0 | AA44: =+Y44+Z44 -> 0 | AB44: =+O44-X44+Z44+AA44 -> 3000 | AD44: =VLOOKUP($C44,'[1]CTRL AUTOS'!$E:$AH,2,0) -> R51BKD | AE44: =AD44&A44 -> R51BKD3
A45: 3 | B45: JOSE JUAN HERNANDEZ MEJIA | C45: VERSA|2017|ACERO|X24APU | D45: OHLM023720345 | E45: ASHC | F45: ASHC | G45: UBER | H45: 4692.05 | I45: 0 | J45: 0 | K45: 0 | L45: -2385.04 | M45: -70.38075 | N45: 0 | O45: =SUM(H45:N45) -> 2236.6293 | P45: -2500 | Q45: -559 | R45: -500 | S45: 0 | T45: 0 | U45: 0 | V45: 0 | W45: =+O45+SUM(P45:V45) -> -1322.3707 | X45: =IF(W45>=0,W45,0) -> 0 | Y45: =IF(W45<=0,W45,0) -> -1322.3707 | Z45: 1322 | AA45: =+Y45+Z45 -> -0.37075 | AB45: =+O45-X45+Z45+AA45 -> 3558.2585 | AD45: X24APU | AE45: =AD45&A45 -> X24APU3
A46: 3 | B46: JUAN CARLOS MUÑOZ | C46: AVEO|2019|BLANCO|NBS225A | D46: OHLM023720287 | E46: ASHC | F46: IVETH | G46: UBER | H46: 3798.92 | I46: 0 | J46: 0 | K46: 0 | L46: -2545.8 | M46: -71.8792 | N46: 0 | O46: =SUM(H46:N46) -> 1181.2408 | P46: -1252 | Q46: 0 | R46: 0 | S46: 0 | T46: 0 | U46: 0 | V46: 0 | W46: =+O46+SUM(P46:V46) -> -70.7592 | X46: =IF(W46>=0,W46,0) -> 0 | Y46: =IF(W46<=0,W46,0) -> -70.7592 | Z46: 105 | AA46: =+Y46+Z46 -> 34.2408 | AB46: =+O46-X46+Z46+AA46 -> 1320.4816 | AD46: =VLOOKUP($C46,'[1]CTRL AUTOS'!$E:$AH,2,0) -> NBS225A | AE46: =AD46&A46 -> NBS225A3
A47: 3 | B47: OSCAR BLANCAS NORIEGA | C47: VENTO|2017|GRIS|NZV7888 | D47: OHLM023720279 | E47: ASHC | F47: ASHC | G47: UBER | H47: 4987.69 | I47: -61.6 | J47: 0 | K47: 0 | L47: -2062.35 | M47: -74.81535 | N47: -97 | O47: =SUM(H47:N47) -> 2691.9246 | P47: -2300 | Q47: 0 | R47: 0 | S47: -500 | T47: 0 | U47: 0 | V47: 0 | W47: =+O47+SUM(P47:V47) -> -108.07535 | X47: =IF(W47>=0,W47,0) -> 0 | Y47: =IF(W47<=0,W47,0) -> -108.07535 | Z47: 108 | AA47: =+Y47+Z47 -> -0.07535 | AB47: =+O47-X47+Z47+AA47 -> 2799.8493 | AD47: BAJA DE PLACAS | AE47: =AD47&A47 -> BAJA DE PLACAS3
A48: 3 | B48: ULISES ITIEL CASTILLO AVILA | C48: KIA RIO|2020|GRIS|NCK475B | D48: OHLM031397326 | E48: ASHC | F48: ASHC | G48: UBER | H48: 4374.64 | I48: -53.6 | J48: 0 | K48: 0 | L48: -2304.06 | M48: -87.4928 | N48: 0 | O48: =SUM(H48:N48) -> 1929.4872 | P48: -1071 | Q48: 0 | R48: 0 | S48: 0 | T48: 0 | U48: 0 | V48: 0 | W48: =+O48+SUM(P48:V48) -> 858.4872 | X48: =IF(W48>=0,W48,0) -> 858.4872 | Y48: =IF(W48<=0,W48,0) -> 0 | Z48: 0 | AA48: =+Y48+Z48 -> 0 | AB48: =+O48-X48+Z48+AA48 -> 1071 | AD48: =VLOOKUP($C48,'[1]CTRL AUTOS'!$E:$AH,2,0) -> NCK475B | AE48: =AD48&A48 -> NCK475B3
A49: 3 | B49: ULISES ITIEL CASTILLO AVILA | C49: KIA RIO|2020|GRIS|NCK475B | D49: OHLM031397326 | E49: ASHC | F49: IVETH | G49: UBER | H49: 3116.48 | I49: -72.8 | J49: 0 | K49: 0 | L49: -1226.18 | M49: -62.3296 | N49: -10.78 | O49: =SUM(H49:N49) -> 1744.3904 | P49: -1429 | Q49: 0 | R49: 0 | S49: 0 | T49: 0 | U49: 0 | V49: 0 | W49: =+O49+SUM(P49:V49) -> 315.3904 | X49: =IF(W49>=0,W49,0) -> 315.3904 | Y49: =IF(W49<=0,W49,0) -> 0 | Z49: 0 | AA49: =+Y49+Z49 -> 0 | AB49: =+O49-X49+Z49+AA49 -> 1429 | AD49: =VLOOKUP($C49,'[1]CTRL AUTOS'!$E:$AH,2,0) -> NCK475B | AE49: =AD49&A49 -> NCK475B3
A50: 4 | B50: ADOLFO LOPEZ MARTINEZ | C50: AVEO|2021|OCRE|NEB156A | D50: OHLM023012552 | E50: ASHC | F50: IVETH | G50: UBER | H50: 0 | I50: 0 | J50: 0 | K50: 0 | L50: 0 | M50: -30 | N50: 0 | O50: =SUM(H50:N50) -> -30 | P50: -2500 | Q50: 0 | R50: 0 | S50: 0 | T50: 0 | U50: 0 | V50: 0 | W50: =+O50+SUM(P50:V50) -> -2530 | X50: =IF(W50>=0,W50,0) -> 0 | Y50: =IF(W50<=0,W50,0) -> -2530 | Z50: 2530 | AA50: =+Y50+Z50 -> 0 | AB50: =+O50-X50+Z50+AA50 -> 2500 | AD50: NEB156A | AE50: =AD50&A50 -> NEB156A4
A51: 4 | B51: ARACELI CASTILLO GUERRERO | C51: AVEO|2018|GRIS|X59AWG | D51: - | E51: ASHC | F51: ASHC | G51: UBER | H51: 0 | I51: -200 | J51: 0 | K51: 0 | L51: 0 | M51: 0 | N51: 0 | O51: =SUM(H51:N51) -> -200 | P51: 0 | Q51: 0 | R51: 0 | S51: 0 | T51: 0 | U51: 0 | V51: 0 | W51: =+O51+SUM(P51:V51) -> -200 | X51: =IF(W51>=0,W51,0) -> 0 | Y51: =IF(W51<=0,W51,0) -> -200 | Z51: 0 | AA51: =+Y51+Z51 -> -200 | AB51: =+O51-X51+Z51+AA51 -> -400 | AD51: =VLOOKUP($C51,'[1]CTRL AUTOS'!$E:$AH,2,0) -> X59AWG | AE51: =AD51&A51 -> X59AWG4
A52: 4 | B52: CESAR PIÑA BARONA | C52: HYUNDAI|2022|PLATA|D40BKD | D52: OHLM023658024 | E52: ASHC | F52: IVETH | G52: UBER | H52: 0 | I52: 0 | J52: 0 | K52: 0 | L52: 0 | M52: 0 | N52: 0 | O52: =SUM(H52:N52) -> 0 | P52: -2500 | Q52: 0 | R52: 0 | S52: 0 | T52: 0 | U52: 0 | V52: 0 | W52: =+O52+SUM(P52:V52) -> -2500 | X52: =IF(W52>=0,W52,0) -> 0 | Y52: =IF(W52<=0,W52,0) -> -2500 | Z52: 0 | AA52: =+Y52+Z52 -> -2500 | AB52: =+O52-X52+Z52+AA52 -> -2500 | AD52: =VLOOKUP($C52,'[1]CTRL AUTOS'!$E:$AH,2,0) -> D40BKD | AE52: =AD52&A52 -> D40BKD4
A53: 4 | B53: DIEGO SANCHEZ | C53: VENTO|2020|GRIS|R66BER | D53: OHLM023720329 | E53: ASHC | F53: ASHC | G53: UBER | H53: 3186.86 | I53: 0 | J53: 0 | K53: 0 | L53: -1760.81 | M53: -25 | N53: 0 | O53: =SUM(H53:N53) -> 1401.05 | P53: -2500 | Q53: 0 | R53: -500 | S53: 0 | T53: 0 | U53: 0 | V53: 0 | W53: =+O53+SUM(P53:V53) -> -1598.95 | X53: =IF(W53>=0,W53,0) -> 0 | Y53: =IF(W53<=0,W53,0) -> -1598.95 | Z53: 1599 | AA53: =+Y53+Z53 -> 0.05 | AB53: =+O53-X53+Z53+AA53 -> 3000.1 | AC53: PAGADO | 30 ENE | AD53: =VLOOKUP($C53,'[1]CTRL AUTOS'!$E:$AH,2,0) -> R66BER | AE53: =AD53&A53 -> R66BER4
A54: 4 | B54: EDGAR GEOVANY URIBE | C54: AVEO|2019|PLATA|NEL860A | D54: OHLM023720337 | E54: ASHC | F54: ASHC | G54: UBER | H54: 7979.51 | I54: -94.4 | J54: 0 | K54: 0 | L54: -1948.64 | M54: -60.83 | N54: 0 | O54: =SUM(H54:N54) -> 5875.64 | P54: -2500 | Q54: 0 | R54: 0 | S54: -500 | T54: 0 | U54: 0 | V54: 0 | W54: =+O54+SUM(P54:V54) -> 2875.64 | X54: =IF(W54>=0,W54,0) -> 2875.64 | Y54: =IF(W54<=0,W54,0) -> 0 | Z54: 0 | AA54: =+Y54+Z54 -> 0 | AB54: =+O54-X54+Z54+AA54 -> 3000 | AD54: =VLOOKUP($C54,'[1]CTRL AUTOS'!$E:$AH,2,0) -> NEL860A | AE54: =AD54&A54 -> NEL860A4
A55: 4 | B55: FERNANDO ESQUIVEL SOSA | C55: VENTO|2018|AMARILLO|PED1652 | D55: OHLM031409055 | E55: ASHC | F55: ASHC | G55: UBER | H55: 6015.72 | I55: -96 | J55: 0 | K55: 0 | L55: -2519.47 | M55: -40 | N55: -68 | O55: =SUM(H55:N55) -> 3292.25 | P55: -2500 | Q55: 0 | R55: -500 | S55: 0 | T55: 0 | U55: 0 | V55: 0 | W55: =+O55+SUM(P55:V55) -> 292.25 | X55: =IF(W55>=0,W55,0) -> 292.25 | Y55: =IF(W55<=0,W55,0) -> 0 | Z55: 0 | AA55: =+Y55+Z55 -> 0 | AB55: =+O55-X55+Z55+AA55 -> 3000 | AD55: =VLOOKUP($C55,'[1]CTRL AUTOS'!$E:$AH,2,0) -> #N/A | AE55: =AD55&A55 -> #N/A
A56: 4 | B56: IRAM HERNANDEZ | C56: AVEO|2022|AZUL|MUF515A | D56: OHLM023720311 | E56: ASHC | F56: ASHC | G56: UBER | H56: 5446.08 | I56: 0 | J56: 0 | K56: 0 | L56: -1740.95 | M56: -45 | N56: -111 | O56: =SUM(H56:N56) -> 3549.13 | P56: -2500 | Q56: 0 | R56: 0 | S56: -500 | T56: 0 | U56: 0 | V56: 0 | W56: =+O56+SUM(P56:V56) -> 549.13 | X56: =IF(W56>=0,W56,0) -> 549.13 | Y56: =IF(W56<=0,W56,0) -> 0 | Z56: 0 | AA56: =+Y56+Z56 -> 0 | AB56: =+O56-X56+Z56+AA56 -> 3000 | AD56: =VLOOKUP($C56,'[1]CTRL AUTOS'!$E:$AH,2,0) -> MUF515A | AE56: =AD56&A56 -> MUF515A4
A57: 4 | B57: IVAN MOGUEL PULIDO | C57: VERSA|2023|PLATA|NCT814A | D57: OHLM023012487 | E57: ASHC | F57: ASHC | G57: UBER | H57: 10172.05 | I57: -184 | J57: 0 | K57: 0 | L57: -4557.47 | M57: -97.57 | N57: -503.08 | O57: =SUM(H57:N57) -> 4829.93 | P57: -2500 | Q57: 0 | R57: 0 | S57: 0 | T57: -500 | U57: 0 | V57: 0 | W57: =+O57+SUM(P57:V57) -> 1829.93 | X57: =IF(W57>=0,W57,0) -> 1829.93 | Y57: =IF(W57<=0,W57,0) -> 0 | Z57: 0 | AA57: =+Y57+Z57 -> 0 | AB57: =+O57-X57+Z57+AA57 -> 3000 | AD57: =VLOOKUP($C57,'[1]CTRL AUTOS'!$E:$AH,2,0) -> NCT814A | AE57: =AD57&A57 -> NCT814A4
A58: 4 | B58: JOSE GUADALUPE GARCIA MORALES | C58: MARCH|2020|TURQ|N15BKD | D58: OHLM031409071 | E58: ASHC | F58: ASHC | G58: UBER | H58: 4194.92 | I58: 0 | J58: 0 | K58: 0 | L58: -2079.62 | M58: -35 | N58: 0 | O58: =SUM(H58:N58) -> 2080.3 | P58: -2500 | Q58: 0 | R58: 0 | S58: 0 | T58: 0 | U58: 0 | V58: 0 | W58: =+O58+SUM(P58:V58) -> -419.7 | X58: =IF(W58>=0,W58,0) -> 0 | Y58: =IF(W58<=0,W58,0) -> -419.7 | Z58: 0 | AA58: =+Y58+Z58 -> -419.7 | AB58: =+O58-X58+Z58+AA58 -> 1660.6 | AC58: PAGADO | 4 FEB | AD58: =VLOOKUP($C58,'[1]CTRL AUTOS'!$E:$AH,2,0) -> N15BKD | AE58: =AD58&A58 -> N15BKD4
A59: 4 | B59: JOSE GUILLERMO HERNANDEZ RAMIREZ | C59: AVEO|2018|ROJO|R51BKD | D59: OHLM017365206 | E59: U64 | F59: ASHC | G59: UBER | H59: 7059.17 | I59: -155.2 | J59: 0 | K59: 0 | L59: -3771.6 | M59: -50 | N59: 0 | O59: =SUM(H59:N59) -> 3082.37 | P59: -2500 | Q59: 0 | R59: 0 | S59: 0 | T59: 0 | U59: 0 | V59: 0 | W59: =+O59+SUM(P59:V59) -> 582.37 | X59: =IF(W59>=0,W59,0) -> 582.37 | Y59: =IF(W59<=0,W59,0) -> 0 | Z59: 0 | AA59: =+Y59+Z59 -> 0 | AB59: =+O59-X59+Z59+AA59 -> 2500 | AD59: =VLOOKUP($C59,'[1]CTRL AUTOS'!$E:$AH,2,0) -> R51BKD | AE59: =AD59&A59 -> R51BKD4
A60: 4 | B60: JOSE JUAN HERNANDEZ MEJIA | C60: VERSA|2017|ACERO|X24APU | D60: OHLM023720345 | E60: ASHC | F60: ASHC | G60: UBER | H60: 4787.08 | I60: -29.31 | J60: 0 | K60: 0 | L60: -1967.22 | M60: -30 | N60: 0 | O60: =SUM(H60:N60) -> 2760.55 | P60: -2500 | Q60: 0 | R60: -500 | S60: 0 | T60: 0 | U60: 0 | V60: 0 | W60: =+O60+SUM(P60:V60) -> -239.45 | X60: =IF(W60>=0,W60,0) -> 0 | Y60: =IF(W60<=0,W60,0) -> -239.45 | Z60: 181 | AA60: =+Y60+Z60 -> -58.45 | AB60: =+O60-X60+Z60+AA60 -> 2883.1 | AC60: PAGADO | 4 FEB | AD60: X24APU | AE60: =AD60&A60 -> X24APU4
A61: 4 | B61: JUAN CARLOS MUÑOZ | C61: AVEO|2019|BLANCO|NBS225A | D61: OHLM023720287 | E61: ASHC | F61: IVETH | G61: UBER | H61: 5743.67 | I61: 0 | J61: 0 | K61: 0 | L61: -2576.79 | M61: -45 | N61: -58 | O61: =SUM(H61:N61) -> 3063.88 | P61: -2500 | Q61: 0 | R61: 0 | S61: 0 | T61: 0 | U61: 0 | V61: 0 | W61: =+O61+SUM(P61:V61) -> 563.88 | X61: =IF(W61>=0,W61,0) -> 563.88 | Y61: =IF(W61<=0,W61,0) -> 0 | Z61: 0 | AA61: =+Y61+Z61 -> 0 | AB61: =+O61-X61+Z61+AA61 -> 2500 | AD61: =VLOOKUP($C61,'[1]CTRL AUTOS'!$E:$AH,2,0) -> NBS225A | AE61: =AD61&A61 -> NBS225A4
A62: 4 | B62: OSCAR BLANCAS NORIEGA | C62: VENTO|2017|GRIS|NZV7888 | D62: OHLM023720279 | E62: ASHC | F62: ASHC | G62: UBER | H62: 3430.61 | I62: -16 | J62: 0 | K62: 0 | L62: -2162.82 | M62: -25 | N62: 0 | O62: =SUM(H62:N62) -> 1226.79 | P62: -2300 | Q62: 120 | R62: 0 | S62: -500 | T62: 0 | U62: 0 | V62: 0 | W62: =+O62+SUM(P62:V62) -> -1453.21 | X62: =IF(W62>=0,W62,0) -> 0 | Y62: =IF(W62<=0,W62,0) -> -1453.21 | Z62: 1421 | AA62: =+Y62+Z62 -> -32.21 | AB62: =+O62-X62+Z62+AA62 -> 2615.58 | AC62: PAGADO | 29 ENE |4 FEB | AD62: BAJA DE PLACAS | AE62: =AD62&A62 -> BAJA DE PLACAS4
A63: 4 | B63: SIN CONDUCTOR | C63: BEAT|2020|GRIS|NFN014B | D63: - | E63: U64 | F63: ASHC | G63: UBER | H63: 0 | I63: 0 | J63: 0 | K63: 0 | L63: 0 | M63: 0 | N63: 0 | O63: =SUM(H63:N63) -> 0 | P63: 0 | Q63: 0 | R63: 0 | S63: 0 | T63: 0 | U63: 0 | V63: 0 | W63: =+O63+SUM(P63:V63) -> 0 | X63: =IF(W63>=0,W63,0) -> 0 | Y63: =IF(W63<=0,W63,0) -> 0 | Z63: 0 | AA63: =+Y63+Z63 -> 0 | AB63: =+O63-X63+Z63+AA63 -> 0 | AD63: =VLOOKUP($C63,'[1]CTRL AUTOS'!$E:$AH,2,0) -> NFN014B | AE63: =AD63&A63 -> NFN014B4
A64: 4 | B64: ULISES ITIEL CASTILLO AVILA | C64: KIA RIO|2020|GRIS|NCK475B | D64: OHLM031397326 | E64: ASHC | F64: IVETH | G64: UBER | H64: 5452.14 | I64: -67.2 | J64: 0 | K64: 0 | L64: -1513.04 | M64: -78 | N64: -75.21 | O64: =SUM(H64:N64) -> 3718.69 | P64: -2500 | Q64: 0 | R64: 0 | S64: 0 | T64: 0 | U64: 0 | V64: 0 | W64: =+O64+SUM(P64:V64) -> 1218.69 | X64: =IF(W64>=0,W64,0) -> 1218.69 | Y64: =IF(W64<=0,W64,0) -> 0 | Z64: 0 | AA64: =+Y64+Z64 -> 0 | AB64: =+O64-X64+Z64+AA64 -> 2500 | AD64: =VLOOKUP($C64,'[1]CTRL AUTOS'!$E:$AH,2,0) -> NCK475B | AE64: =AD64&A64 -> NCK475B4
A65: 5 | B65: ADOLFO LOPEZ MARTINEZ | C65: AVEO|2021|OCRE|NEB156A | D65: OHLM023012552 | E65: ASHC | F65: IVETH | G65: UBER | H65: 675.51 | I65: 9.15 | J65: 0 | K65: 0 | L65: 0 | M65: -19 | N65: 0 | O65: =SUM(H65:N65) -> 665.66 | P65: -2500 | Q65: 0 | R65: 0 | S65: 0 | T65: 0 | U65: 0 | V65: 0 | W65: =+O65+SUM(P65:V65) -> -1834.34 | X65: =IF(W65>=0,W65,0) -> 0 | Y65: =IF(W65<=0,W65,0) -> -1834.34 | Z65: 1834 | AA65: =+Y65+Z65 -> -0.34 | AB65: =+O65-X65+Z65+AA65 -> 2499.32 | AD65: NEB156A | AE65: =AD65&A65 -> NEB156A5
A66: 5 | B66: ARACELI CASTILLO GUERRERO | C66: AVEO|2018|GRIS|X59AWG | D66: - | E66: ASHC | F66: ASHC | G66: UBER | H66: 0 | I66: 0 | J66: 0 | K66: 0 | L66: 0 | M66: 0 | N66: 0 | O66: =SUM(H66:N66) -> 0 | P66: 0 | Q66: 0 | R66: 0 | S66: 0 | T66: 0 | U66: 0 | V66: 0 | W66: =+O66+SUM(P66:V66) -> 0 | X66: =IF(W66>=0,W66,0) -> 0 | Y66: =IF(W66<=0,W66,0) -> 0 | Z66: 0 | AA66: =+Y66+Z66 -> 0 | AB66: =+O66-X66+Z66+AA66 -> 0 | AD66: =VLOOKUP($C66,'[1]CTRL AUTOS'!$E:$AH,2,0) -> X59AWG | AE66: =AD66&A66 -> X59AWG5
A67: 5 | B67: CESAR PIÑA BARONA | C67: HYUNDAI|2022|PLATA|D40BKD | D67: OHLM023658024 | E67: ASHC | F67: IVETH | G67: UBER | H67: 0 | I67: 0 | J67: 0 | K67: 0 | L67: 0 | M67: 0 | N67: 0 | O67: =SUM(H67:N67) -> 0 | P67: -2500 | Q67: 0 | R67: 0 | S67: 0 | T67: 0 | U67: 0 | V67: 0 | W67: =+O67+SUM(P67:V67) -> -2500 | X67: =IF(W67>=0,W67,0) -> 0 | Y67: =IF(W67<=0,W67,0) -> -2500 | Z67: 5000 | AA67: =+Y67+Z67 -> 2500 | AB67: =+O67-X67+Z67+AA67 -> 7500 | AD67: =VLOOKUP($C67,'[1]CTRL AUTOS'!$E:$AH,2,0) -> D40BKD | AE67: =AD67&A67 -> D40BKD5
A68: 5 | B68: DIEGO SANCHEZ | C68: VENTO|2020|GRIS|R66BER | D68: OHLM023720329 | E68: ASHC | F68: ASHC | G68: UBER | H68: 4292.37 | I68: 0 | J68: 0 | K68: 0 | L68: -1767.76 | M68: -35 | N68: -55 | O68: =SUM(H68:N68) -> 2434.61 | P68: -2500 | Q68: 0 | R68: -25 | S68: 0 | T68: 0 | U68: 0 | V68: 0 | W68: =+O68+SUM(P68:V68) -> -90.39 | X68: =IF(W68>=0,W68,0) -> 0 | Y68: =IF(W68<=0,W68,0) -> -90.39 | Z68: 0 | AA68: =+Y68+Z68 -> -90.39 | AB68: =+O68-X68+Z68+AA68 -> 2344.22 | AC68: PAGADO 8 FEB | AD68: =VLOOKUP($C68,'[1]CTRL AUTOS'!$E:$AH,2,0) -> R66BER | AE68: =AD68&A68 -> R66BER5
A69: 5 | B69: EDGAR GEOVANY URIBE | C69: AVEO|2019|PLATA|NEL860A | D69: OHLM023720337 | E69: ASHC | F69: ASHC | G69: UBER | H69: 8172.09 | I69: 206.4 | J69: 0 | K69: 0 | L69: -1598.72 | M69: -95 | N69: -15.1 | O69: =SUM(H69:N69) -> 6669.67 | P69: -2500 | Q69: 0 | R69: 0 | S69: -500 | T69: 0 | U69: 0 | V69: 0 | W69: =+O69+SUM(P69:V69) -> 3669.67 | X69: =IF(W69>=0,W69,0) -> 3669.67 | Y69: =IF(W69<=0,W69,0) -> 0 | Z69: 0 | AA69: =+Y69+Z69 -> 0 | AB69: =+O69-X69+Z69+AA69 -> 3000 | AD69: =VLOOKUP($C69,'[1]CTRL AUTOS'!$E:$AH,2,0) -> NEL860A | AE69: =AD69&A69 -> NEL860A5
A70: 5 | B70: FERNANDO ESQUIVEL SOSA | C70: VENTO|2018|AMARILLO|PED1652 | D70: OHLM031409055 | E70: ASHC | F70: ASHC | G70: UBER | H70: 5850.36 | I70: 120 | J70: 0 | K70: 0 | L70: -2290.38 | M70: -49 | N70: -68 | O70: =SUM(H70:N70) -> 3562.98 | P70: -2500 | Q70: 465 | R70: -500 | S70: 0 | T70: 0 | U70: 0 | V70: 0 | W70: =+O70+SUM(P70:V70) -> 1027.98 | X70: =IF(W70>=0,W70,0) -> 1027.98 | Y70: =IF(W70<=0,W70,0) -> 0 | Z70: 0 | AA70: =+Y70+Z70 -> 0 | AB70: =+O70-X70+Z70+AA70 -> 2535 | AC70: PAGADO | AD70: =VLOOKUP($C70,'[1]CTRL AUTOS'!$E:$AH,2,0) -> #N/A | AE70: =AD70&A70 -> #N/A
A71: 5 | B71: IRAM HERNANDEZ | C71: AVEO|2022|AZUL|MUF515A | D71: OHLM031491772 | E71: ASHC | F71: ASHC | G71: UBER | H71: 4096.64 | I71: 0 | J71: 0 | K71: 0 | L71: -1452.54 | M71: -45 | N71: -91 | O71: =SUM(H71:N71) -> 2508.1 | P71: -1964.2857 | Q71: 0 | R71: 0 | S71: -300 | T71: 0 | U71: 0 | V71: 0 | W71: =+O71+SUM(P71:V71) -> 243.81429 | X71: =IF(W71>=0,W71,0) -> 243.81429 | Y71: =IF(W71<=0,W71,0) -> 0 | Z71: 0 | AA71: =+Y71+Z71 -> 0 | AB71: =+O71-X71+Z71+AA71 -> 2264.2857 | AD71: =VLOOKUP($C71,'[1]CTRL AUTOS'!$E:$AH,2,0) -> MUF515A | AE71: =AD71&A71 -> MUF515A5
A72: 5 | B72: IVAN MOGUEL PULIDO | C72: VERSA|2023|PLATA|NCT814A | D72: OHLM031491780 | E72: ASHC | F72: ASHC | G72: UBER | H72: 10628.31 | I72: 223.2 | J72: 0 | K72: 0 | L72: -4537.27 | M72: -90 | N72: -328.97 | O72: =SUM(H72:N72) -> 5895.27 | P72: -2500 | Q72: 0 | R72: 0 | S72: 0 | T72: -500 | U72: 0 | V72: 0 | W72: =+O72+SUM(P72:V72) -> 2895.27 | X72: =IF(W72>=0,W72,0) -> 2895.27 | Y72: =IF(W72<=0,W72,0) -> 0 | Z72: 0 | AA72: =+Y72+Z72 -> 0 | AB72: =+O72-X72+Z72+AA72 -> 3000 | AD72: =VLOOKUP($C72,'[1]CTRL AUTOS'!$E:$AH,2,0) -> NCT814A | AE72: =AD72&A72 -> NCT814A5
A73: 5 | B73: JOSE GUADALUPE GARCIA MORALES | C73: MARCH|2020|TURQ|N15BKD | D73: OHLM031409071 | E73: ASHC | F73: ASHC | G73: UBER | H73: 5033.08 | I73: 0 | J73: 0 | K73: 0 | L73: -1722.51 | M73: -58.83 | N73: 0 | O73: =SUM(H73:N73) -> 3251.74 | P73: -2500 | Q73: -420 | R73: 0 | S73: 0 | T73: 0 | U73: 0 | V73: 0 | W73: =+O73+SUM(P73:V73) -> 331.74 | X73: =IF(W73>=0,W73,0) -> 331.74 | Y73: =IF(W73<=0,W73,0) -> 0 | Z73: 0 | AA73: =+Y73+Z73 -> 0 | AB73: =+O73-X73+Z73+AA73 -> 2920 | AC73: PAGADO | AD73: =VLOOKUP($C73,'[1]CTRL AUTOS'!$E:$AH,2,0) -> N15BKD | AE73: =AD73&A73 -> N15BKD5
A74: 5 | B74: JOSE GUILLERMO HERNANDEZ RAMIREZ | C74: AVEO|2018|ROJO|R51BKD | D74: OHLM017365206 | E74: U64 | F74: ASHC | G74: UBER | H74: 6762.66 | I74: 100 | J74: 0 | K74: 0 | L74: -4033.67 | M74: -48 | N74: 0 | O74: =SUM(H74:N74) -> 2780.99 | P74: -2500 | Q74: 28 | R74: 0 | S74: 0 | T74: 0 | U74: 0 | V74: 0 | W74: =+O74+SUM(P74:V74) -> 308.99 | X74: =IF(W74>=0,W74,0) -> 308.99 | Y74: =IF(W74<=0,W74,0) -> 0 | Z74: 0 | AA74: =+Y74+Z74 -> 0 | AB74: =+O74-X74+Z74+AA74 -> 2472 | AC74: RETIRO CAJERO | AD74: =VLOOKUP($C74,'[1]CTRL AUTOS'!$E:$AH,2,0) -> R51BKD | AE74: =AD74&A74 -> R51BKD5
A75: 5 | B75: JOSE JUAN HERNANDEZ MEJIA | C75: VERSA|2017|ACERO|X24APU | D75: OHLM023720345 | E75: ASHC | F75: ASHC | G75: UBER | H75: 4727.71 | I75: 0 | J75: 0 | K75: 0 | L75: -1513.29 | M75: -55 | N75: 0 | O75: =SUM(H75:N75) -> 3159.42 | P75: -2500 | Q75: 0 | R75: -500 | S75: 0 | T75: 0 | U75: 0 | V75: 0 | W75: =+O75+SUM(P75:V75) -> 159.42 | X75: =IF(W75>=0,W75,0) -> 159.42 | Y75: =IF(W75<=0,W75,0) -> 0 | Z75: 0 | AA75: =+Y75+Z75 -> 0 | AB75: =+O75-X75+Z75+AA75 -> 3000 | AC75: COMPENSACIÓN DE SALDOS | AD75: X24APU | AE75: =AD75&A75 -> X24APU5
A76: 5 | B76: JUAN CARLOS MUÑOZ | C76: AVEO|2019|BLANCO|NBS225A | D76: OHLM023720287 | E76: ASHC | F76: IVETH | G76: UBER | H76: 6000.31 | I76: 0 | J76: 0 | K76: 0 | L76: -3123.9 | M76: 0 | N76: -43 | O76: =SUM(H76:N76) -> 2833.41 | P76: -2500 | Q76: 0 | R76: -500 | S76: 0 | T76: 0 | U76: 0 | V76: 0 | W76: =+O76+SUM(P76:V76) -> -166.59 | X76: =IF(W76>=0,W76,0) -> 0 | Y76: =IF(W76<=0,W76,0) -> -166.59 | Z76: 0 | AA76: =+Y76+Z76 -> -166.59 | AB76: =+O76-X76+Z76+AA76 -> 2666.82 | AD76: =VLOOKUP($C76,'[1]CTRL AUTOS'!$E:$AH,2,0) -> NBS225A | AE76: =AD76&A76 -> NBS225A5
A77: 5 | B77: OSCAR BLANCAS NORIEGA | C77: VENTO|2017|GRIS|NZV7888 | D77: OHLM023720279 | E77: ASHC | F77: ASHC | G77: UBER | H77: 3945.89 | I77: 24 | J77: 0 | K77: 0 | L77: -1941.72 | M77: -30 | N77: -4.97 | O77: =SUM(H77:N77) -> 1993.2 | P77: -2300 | Q77: 0 | R77: 0 | S77: -500 | T77: 0 | U77: 0 | V77: 0 | W77: =+O77+SUM(P77:V77) -> -806.8 | X77: =IF(W77>=0,W77,0) -> 0 | Y77: =IF(W77<=0,W77,0) -> -806.8 | Z77: 0 | AA77: =+Y77+Z77 -> -806.8 | AB77: =+O77-X77+Z77+AA77 -> 1186.4 | AC77: PAGADO 5 FEB | AD77: BAJA DE PLACAS | AE77: =AD77&A77 -> BAJA DE PLACAS5
A78: 5 | B78: SIN CONDUCTOR | C78: BEAT|2020|GRIS|NFN014B | D78: - | E78: U64 | F78: ASHC | G78: UBER | H78: 0 | I78: 0 | J78: 0 | K78: 0 | L78: 0 | M78: 0 | N78: 0 | O78: =SUM(H78:N78) -> 0 | P78: 0 | Q78: 0 | R78: 0 | S78: 0 | T78: 0 | U78: 0 | V78: 0 | W78: =+O78+SUM(P78:V78) -> 0 | X78: =IF(W78>=0,W78,0) -> 0 | Y78: =IF(W78<=0,W78,0) -> 0 | Z78: 0 | AA78: =+Y78+Z78 -> 0 | AB78: =+O78-X78+Z78+AA78 -> 0 | AD78: =VLOOKUP($C78,'[1]CTRL AUTOS'!$E:$AH,2,0) -> NFN014B | AE78: =AD78&A78 -> NFN014B5
A79: 5 | B79: ULISES ITIEL CASTILLO AVILA | C79: KIA RIO|2020|GRIS|NCK475B | D79: OHLM031397326 | E79: ASHC | F79: IVETH | G79: UBER | H79: 6031.51 | I79: 63.2 | J79: 0 | K79: 0 | L79: -2551.25 | M79: 0 | N79: -381.72 | O79: =SUM(H79:N79) -> 3161.74 | P79: -2500 | Q79: 0 | R79: 0 | S79: 0 | T79: 0 | U79: 0 | V79: 0 | W79: =+O79+SUM(P79:V79) -> 661.74 | X79: =IF(W79>=0,W79,0) -> 661.74 | Y79: =IF(W79<=0,W79,0) -> 0 | Z79: 0 | AA79: =+Y79+Z79 -> 0 | AB79: =+O79-X79+Z79+AA79 -> 2500 | AD79: =VLOOKUP($C79,'[1]CTRL AUTOS'!$E:$AH,2,0) -> NCK475B | AE79: =AD79&A79 -> NCK475B5
A80: 6 | B80: ADOLFO LOPEZ MARTINEZ | C80: AVEO|2021|OCRE|NEB156A | D80: OHLM023012552 | E80: ASHC | F80: IVETH | G80: UBER | H80: 0 | I80: 0 | J80: 0 | K80: 0 | L80: 0 | M80: 0 | N80: 0 | O80: =SUM(H80:N80) -> 0 | P80: -2500 | Q80: 0 | R80: 0 | S80: 0 | T80: 0 | U80: 0 | V80: 0 | W80: =+O80+SUM(P80:V80) -> -2500 | X80: =IF(W80>=0,W80,0) -> 0 | Y80: =IF(W80<=0,W80,0) -> -2500 | Z80: 2500 | AA80: =+Y80+Z80 -> 0 | AB80: =+O80-X80+Z80+AA80 -> 2500 | AC80: Pendiente | AD80: NEB156A | AE80: =AD80&A80 -> NEB156A6
A81: 6 | B81: CESAR PIÑA BARONA | C81: HYUNDAI|2022|PLATA|D40BKD | D81: OHLM023658024 | E81: ASHC | F81: IVETH | G81: UBER | H81: 0 | I81: 0 | J81: 0 | K81: 0 | L81: 0 | M81: 0 | N81: 0 | O81: =SUM(H81:N81) -> 0 | P81: -2500 | Q81: 0 | R81: 0 | S81: 0 | T81: 0 | U81: 0 | V81: 0 | W81: =+O81+SUM(P81:V81) -> -2500 | X81: =IF(W81>=0,W81,0) -> 0 | Y81: =IF(W81<=0,W81,0) -> -2500 | Z81: 2500 | AA81: =+Y81+Z81 -> 0 | AB81: =+O81-X81+Z81+AA81 -> 2500 | AC81: PENDIENTE | AD81: =VLOOKUP($C81,'[1]CTRL AUTOS'!$E:$AH,2,0) -> D40BKD | AE81: =AD81&A81 -> D40BKD6
A82: 6 | B82: DIEGO SANCHEZ | C82: VENTO|2020|GRIS|R66BER | D82: OHLM023720329 | E82: ASHC | F82: ASHC | G82: UBER | H82: 4542.31 | I82: 0 | J82: 0 | K82: 0 | L82: -2505.74 | M82: 0 | N82: 0 | O82: =SUM(H82:N82) -> 2036.57 | P82: -2500 | Q82: 0 | R82: 0 | S82: 0 | T82: 0 | U82: 0 | V82: 0 | W82: =+O82+SUM(P82:V82) -> -463.43 | X82: =IF(W82>=0,W82,0) -> 0 | Y82: =IF(W82<=0,W82,0) -> -463.43 | Z82: 0 | AA82: =+Y82+Z82 -> -463.43 | AB82: =+O82-X82+Z82+AA82 -> 1573.14 | AD82: =VLOOKUP($C82,'[1]CTRL AUTOS'!$E:$AH,2,0) -> R66BER | AE82: =AD82&A82 -> R66BER6
A83: 6 | B83: EDGAR GEOVANY URIBE | C83: AVEO|2019|PLATA|NEL860A | D83: OHLM023720337 | E83: ASHC | F83: ASHC | G83: UBER | H83: 7372.52 | I83: 139.2 | J83: 0 | K83: 0 | L83: -1389.35 | M83: -96 | N83: 0 | O83: =SUM(H83:N83) -> 6026.37 | P83: -2500 | Q83: 0 | R83: 0 | S83: -343 | T83: 0 | U83: 0 | V83: 0 | W83: =+O83+SUM(P83:V83) -> 3183.37 | X83: =IF(W83>=0,W83,0) -> 3183.37 | Y83: =IF(W83<=0,W83,0) -> 0 | Z83: 0 | AA83: =+Y83+Z83 -> 0 | AB83: =+O83-X83+Z83+AA83 -> 2843 | AD83: =VLOOKUP($C83,'[1]CTRL AUTOS'!$E:$AH,2,0) -> NEL860A | AE83: =AD83&A83 -> NEL860A6
A84: 6 | B84: FERNANDO ESQUIVEL SOSA | C84: VENTO|2018|AMARILLO|PED1652 | D84: OHLM031409055 | E84: ASHC | F84: ASHC | G84: UBER | H84: 3023.97 | I84: 0 | J84: 0 | K84: 0 | L84: -588.19 | M84: 0 | N84: 0 | O84: =SUM(H84:N84) -> 2435.78 | P84: -2500 | Q84: 0 | R84: -500 | S84: 0 | T84: 0 | U84: 0 | V84: 0 | W84: =+O84+SUM(P84:V84) -> -564.22 | X84: =IF(W84>=0,W84,0) -> 0 | Y84: =IF(W84<=0,W84,0) -> -564.22 | Z84: 545 | AA84: =+Y84+Z84 -> -19.22 | AB84: =+O84-X84+Z84+AA84 -> 2961.56 | AD84: =VLOOKUP($C84,'[1]CTRL AUTOS'!$E:$AH,2,0) -> #N/A | AE84: =AD84&A84 -> #N/A
A85: 6 | B85: IRAM HERNANDEZ | C85: AVEO|2022|AZUL|MUF515A | D85: OHLM031491772 | E85: ASHC | F85: ASHC | G85: UBER | H85: 4975.22 | I85: 0 | J85: 0 | K85: 0 | L85: -1753.47 | M85: -56 | N85: 0 | O85: =SUM(H85:N85) -> 3165.75 | P85: -2500 | Q85: 0 | R85: 0 | S85: -500 | T85: 0 | U85: 0 | V85: 0 | W85: =+O85+SUM(P85:V85) -> 165.75 | X85: =IF(W85>=0,W85,0) -> 165.75 | Y85: =IF(W85<=0,W85,0) -> 0 | Z85: 0 | AA85: =+Y85+Z85 -> 0 | AB85: =+O85-X85+Z85+AA85 -> 3000 | AD85: =VLOOKUP($C85,'[1]CTRL AUTOS'!$E:$AH,2,0) -> MUF515A | AE85: =AD85&A85 -> MUF515A6
A86: 6 | B86: IVAN MOGUEL PULIDO | C86: VERSA|2023|PLATA|NCT814A | D86: OHLM031491780 | E86: ASHC | F86: ASHC | G86: UBER | H86: 8889.43 | I86: 89.6 | J86: -54 | K86: 0 | L86: -4457.29 | M86: -85 | N86: -172.05 | O86: =SUM(H86:N86) -> 4210.69 | P86: -2500 | Q86: 0 | R86: 0 | S86: -500 | T86: -65 | U86: 0 | V86: 0 | W86: =+O86+SUM(P86:V86) -> 1145.69 | X86: =IF(W86>=0,W86,0) -> 1145.69 | Y86: =IF(W86<=0,W86,0) -> 0 | Z86: 0 | AA86: =+Y86+Z86 -> 0 | AB86: =+O86-X86+Z86+AA86 -> 3065 | AD86: =VLOOKUP($C86,'[1]CTRL AUTOS'!$E:$AH,2,0) -> NCT814A | AE86: =AD86&A86 -> NCT814A6
A87: 6 | B87: JOSE GUADALUPE GARCIA MORALES | C87: MARCH|2020|TURQ|N15BKD | D87: OHLM031409071 | E87: ASHC | F87: ASHC | G87: UBER | H87: 4661.12 | I87: 0 | J87: 0 | K87: 0 | L87: -2350.13 | M87: -45 | N87: 0 | O87: =SUM(H87:N87) -> 2265.99 | P87: -2500 | Q87: 0 | R87: 0 | S87: 0 | T87: 0 | U87: 0 | V87: 0 | W87: =+O87+SUM(P87:V87) -> -234.01 | X87: =IF(W87>=0,W87,0) -> 0 | Y87: =IF(W87<=0,W87,0) -> -234.01 | Z87: 234 | AA87: =+Y87+Z87 -> -0.01 | AB87: =+O87-X87+Z87+AA87 -> 2499.98 | AD87: =VLOOKUP($C87,'[1]CTRL AUTOS'!$E:$AH,2,0) -> N15BKD | AE87: =AD87&A87 -> N15BKD6
A88: 6 | B88: JOSE GUILLERMO HERNANDEZ RAMIREZ | C88: AVEO|2018|ROJO|R51BKD | D88: OHLM017365206 | E88: U64 | F88: ASHC | G88: UBER | H88: 6463.43 | I88: 117.6 | J88: 0 | K88: 0 | L88: -3597.86 | M88: -78 | N88: 0 | O88: =SUM(H88:N88) -> 2905.17 | P88: -2500 | Q88: 9 | R88: 0 | S88: 0 | T88: 0 | U88: 0 | V88: 0 | W88: =+O88+SUM(P88:V88) -> 414.17 | X88: =IF(W88>=0,W88,0) -> 414.17 | Y88: =IF(W88<=0,W88,0) -> 0 | Z88: 0 | AA88: =+Y88+Z88 -> 0 | AB88: =+O88-X88+Z88+AA88 -> 2491 | AD88: =VLOOKUP($C88,'[1]CTRL AUTOS'!$E:$AH,2,0) -> R51BKD | AE88: =AD88&A88 -> R51BKD6
A89: 6 | B89: JOSE JUAN HERNANDEZ MEJIA | C89: VERSA|2017|ACERO|X24APU | D89: OHLM023720345 | E89: ASHC | F89: ASHC | G89: UBER | H89: 3144.49 | I89: 0 | J89: 0 | K89: 0 | L89: -831.67 | M89: 0 | N89: -75 | O89: =SUM(H89:N89) -> 2237.82 | P89: -2321.4286 | Q89: 0 | R89: -500 | S89: 0 | T89: 0 | U89: 0 | V89: 0 | W89: =+O89+SUM(P89:V89) -> -583.60857 | X89: =IF(W89>=0,W89,0) -> 0 | Y89: =IF(W89<=0,W89,0) -> -583.60857 | Z89: 584 | AA89: =+Y89+Z89 -> 0.39142857 | AB89: =+O89-X89+Z89+AA89 -> 2822.2114 | AD89: X24APU | AE89: =AD89&A89 -> X24APU6
A90: 6 | B90: JUAN CARLOS MUÑOZ | C90: AVEO|2019|BLANCO|NBS225A | D90: OHLM023720287 | E90: ASHC | F90: IVETH | G90: UBER | H90: 659.52 | I90: 0 | J90: 0 | K90: 0 | L90: -220 | M90: 0 | N90: -114 | O90: =SUM(H90:N90) -> 325.52 | P90: -1786 | Q90: 0 | R90: 0 | S90: 0 | T90: 0 | U90: 0 | V90: 0 | W90: =+O90+SUM(P90:V90) -> -1460.48 | X90: =IF(W90>=0,W90,0) -> 0 | Y90: =IF(W90<=0,W90,0) -> -1460.48 | Z90: 3167 | AA90: =+Y90+Z90 -> 1706.52 | AB90: =+O90-X90+Z90+AA90 -> 5199.04 | AC90: Devolución Fianza | AD90: =VLOOKUP($C90,'[1]CTRL AUTOS'!$E:$AH,2,0) -> NBS225A | AE90: =AD90&A90 -> NBS225A6
A91: 6 | B91: MARIO ALBERTO ROJAS | C91: AVEO|2018|GRIS|X59AWG | D91: - | E91: ASHC | F91: ASHC | G91: UBER | H91: 3054.64 | I91: 0.31 | J91: 0 | K91: 0 | L91: -1378.41 | M91: -0.83 | N91: 0 | O91: =SUM(H91:N91) -> 1675.71 | P91: -1785.7143 | Q91: 0 | R91: -500 | S91: 0 | T91: 0 | U91: 0 | V91: 0 | W91: =+O91+SUM(P91:V91) -> -610.00429 | X91: =IF(W91>=0,W91,0) -> 0 | Y91: =IF(W91<=0,W91,0) -> -610.00429 | Z91: 0 | AA91: =+Y91+Z91 -> -610.00429 | AB91: =+O91-X91+Z91+AA91 -> 1065.7057 | AD91: =VLOOKUP($C91,'[1]CTRL AUTOS'!$E:$AH,2,0) -> X59AWG | AE91: =AD91&A91 -> X59AWG6
A92: 6 | B92: OSCAR BLANCAS NORIEGA | C92: VENTO|2017|GRIS|NZV7888 | D92: OHLM023720279 | E92: ASHC | F92: ASHC | G92: UBER | H92: 5375.28 | I92: 28.8 | J92: 0 | K92: 0 | L92: -1997.86 | M92: -67 | N92: 0 | O92: =SUM(H92:N92) -> 3339.22 | P92: -2300 | Q92: 0 | R92: 0 | S92: -500 | T92: 0 | U92: 0 | V92: 0 | W92: =+O92+SUM(P92:V92) -> 539.22 | X92: =IF(W92>=0,W92,0) -> 539.22 | Y92: =IF(W92<=0,W92,0) -> 0 | Z92: 0 | AA92: =+Y92+Z92 -> 0 | AB92: =+O92-X92+Z92+AA92 -> 2800 | AD92: BAJA DE PLACAS | AE92: =AD92&A92 -> BAJA DE PLACAS6
A93: 6 | B93: RODOLFO AVANTES | C93: BEAT|2020|GRIS|NFN014B | D93: SIN TAG | E93: U64 | F93: ASHC | G93: UBER | H93: 2278.65 | I93: 0 | J93: 0 | K93: 0 | L93: -1184.24 | M93: 0 | N93: 0 | O93: =SUM(H93:N93) -> 1094.41 | P93: -1785.7143 | Q93: 0 | R93: -500 | S93: 0 | T93: 0 | U93: 0 | V93: 0 | W93: =+O93+SUM(P93:V93) -> -1191.3043 | X93: =IF(W93>=0,W93,0) -> 0 | Y93: =IF(W93<=0,W93,0) -> -1191.3043 | Z93: 0 | AA93: =+Y93+Z93 -> -1191.3043 | AB93: =+O93-X93+Z93+AA93 -> -96.894286 | AD93: =VLOOKUP($C93,'[1]CTRL AUTOS'!$E:$AH,2,0) -> NFN014B | AE93: =AD93&A93 -> NFN014B6
A94: 6 | B94: ULISES ITIEL CASTILLO AVILA | C94: KIA RIO|2020|GRIS|NCK475B | D94: OHLM031397326 | E94: ASHC | F94: IVETH | G94: UBER | H94: 4559.7 | I94: 8 | J94: 0 | K94: 0 | L94: -1681.88 | M94: 0 | N94: 0 | O94: =SUM(H94:N94) -> 2885.82 | P94: -2500 | Q94: 0 | R94: 0 | S94: 0 | T94: 0 | U94: 0 | V94: 0 | W94: =+O94+SUM(P94:V94) -> 385.82 | X94: =IF(W94>=0,W94,0) -> 385.82 | Y94: =IF(W94<=0,W94,0) -> 0 | Z94: 0 | AA94: =+Y94+Z94 -> 0 | AB94: =+O94-X94+Z94+AA94 -> 2500 | AD94: =VLOOKUP($C94,'[1]CTRL AUTOS'!$E:$AH,2,0) -> NCK475B | AE94: =AD94&A94 -> NCK475B6
A95: 7 | B95: ADOLFO LOPEZ MARTINEZ | C95: AVEO|2021|OCRE|NEB156A | D95: OHLM023012552 | E95: ASHC | F95: IVETH | G95: UBER | H95: 0 | I95: 0 | J95: 0 | K95: 0 | L95: 0 | M95: 0 | N95: 0 | O95: =SUM(H95:N95) -> 0 | P95: 0 | Q95: 0 | R95: 0 | S95: 0 | T95: 0 | U95: 0 | V95: 0 | W95: =+O95+SUM(P95:V95) -> 0 | X95: =IF(W95>=0,W95,0) -> 0 | Y95: =IF(W95<=0,W95,0) -> 0 | Z95: 0 | AA95: =+Y95+Z95 -> 0 | AB95: =+O95-X95+Z95+AA95 -> 0 | AD95: NEB156A | AE95: =AD95&A95 -> NEB156A7
A96: 7 | B96: CESAR PIÑA BARONA | C96: HYUNDAI|2022|PLATA|D40BKD | D96: OHLM023658024 | E96: ASHC | F96: IVETH | G96: UBER | H96: 0 | I96: 0 | J96: 0 | K96: 0 | L96: 0 | M96: 0 | N96: 0 | O96: =SUM(H96:N96) -> 0 | P96: -2500 | Q96: 0 | R96: 0 | S96: 0 | T96: 0 | U96: 0 | V96: 0 | W96: =+O96+SUM(P96:V96) -> -2500 | X96: =IF(W96>=0,W96,0) -> 0 | Y96: =IF(W96<=0,W96,0) -> -2500 | Z96: 2500 | AA96: =+Y96+Z96 -> 0 | AB96: =+O96-X96+Z96+AA96 -> 2500 | AD96: =VLOOKUP($C96,'[1]CTRL AUTOS'!$E:$AH,2,0) -> D40BKD | AE96: =AD96&A96 -> D40BKD7
A97: 7 | B97: DIEGO SANCHEZ | C97: VENTO|2020|GRIS|R66BER | D97: OHLM023720329 | E97: ASHC | F97: ASHC | G97: UBER | H97: 3240.77 | I97: 0 | J97: 0 | K97: 0 | L97: -1738.57 | M97: -26 | N97: -295.29 | O97: =SUM(H97:N97) -> 1180.91 | P97: -2500 | Q97: 0 | R97: 0 | S97: 0 | T97: 0 | U97: 0 | V97: 0 | W97: =+O97+SUM(P97:V97) -> -1319.09 | X97: =IF(W97>=0,W97,0) -> 0 | Y97: =IF(W97<=0,W97,0) -> -1319.09 | Z97: 0 | AA97: =+Y97+Z97 -> -1319.09 | AB97: =+O97-X97+Z97+AA97 -> -138.18 | AD97: =VLOOKUP($C97,'[1]CTRL AUTOS'!$E:$AH,2,0) -> R66BER | AE97: =AD97&A97 -> R66BER7
A98: 7 | B98: EDGAR GEOVANY URIBE | C98: AVEO|2019|PLATA|NEL860A | D98: OHLM023720337 | E98: ASHC | F98: ASHC | G98: UBER | H98: 5003.53 | I98: 0 | J98: 0 | K98: 0 | L98: -731.26 | M98: -45 | N98: -8.73 | O98: =SUM(H98:N98) -> 4218.54 | P98: -96 | Q98: 0 | R98: 0 | S98: 0 | T98: 0 | U98: 0 | V98: 0 | W98: =+O98+SUM(P98:V98) -> 4122.54 | X98: =IF(W98>=0,W98,0) -> 4122.54 | Y98: =IF(W98<=0,W98,0) -> 0 | Z98: 0 | AA98: =+Y98+Z98 -> 0 | AB98: =+O98-X98+Z98+AA98 -> 96 | AD98: =VLOOKUP($C98,'[1]CTRL AUTOS'!$E:$AH,2,0) -> NEL860A | AE98: =AD98&A98 -> NEL860A7
A99: 7 | B99: FERNANDO ESQUIVEL SOSA | C99: VENTO|2018|AMARILLO|PED1652 | D99: OHLM031409055 | E99: ASHC | F99: ASHC | G99: UBER | H99: 79.68 | I99: 0 | J99: 0 | K99: 0 | L99: 0 | M99: 0 | N99: -71 | O99: =SUM(H99:N99) -> 8.68 | P99: 0 | Q99: 0 | R99: 0 | S99: 0 | T99: 0 | U99: 0 | V99: 0 | W99: =+O99+SUM(P99:V99) -> 8.68 | X99: =IF(W99>=0,W99,0) -> 8.68 | Y99: =IF(W99<=0,W99,0) -> 0 | Z99: 0 | AA99: =+Y99+Z99 -> 0 | AB99: =+O99-X99+Z99+AA99 -> 0 | AD99: =VLOOKUP($C99,'[1]CTRL AUTOS'!$E:$AH,2,0) -> #N/A | AE99: =AD99&A99 -> #N/A
A100: 7 | B100: IRAM HERNANDEZ | C100: AVEO|2022|AZUL|MUF515A | D100: OHLM031491772 | E100: ASHC | F100: ASHC | G100: UBER | H100: 4390.43 | I100: 0 | J100: 0 | K100: 0 | L100: -1581.18 | M100: 0 | N100: 0 | O100: =SUM(H100:N100) -> 2809.25 | P100: -56 | Q100: 0 | R100: 0 | S100: -300 | T100: 0 | U100: 0 | V100: 0 | W100: =+O100+SUM(P100:V100) -> 2453.25 | X100: =IF(W100>=0,W100,0) -> 2453.25 | Y100: =IF(W100<=0,W100,0) -> 0 | Z100: 0 | AA100: =+Y100+Z100 -> 0 | AB100: =+O100-X100+Z100+AA100 -> 356 | AD100: =VLOOKUP($C100,'[1]CTRL AUTOS'!$E:$AH,2,0) -> MUF515A | AE100: =AD100&A100 -> MUF515A7
...

Sheet UBER 2026
A1: SEM | B1: CONDUCTOR | C1: LLAVE | D1: TAG | E1: SOCIO | F1: PLATAFORMA | G1: APP | H1: GANANCIA | I1: EFECTIVO | J1: IMPUESTOS | K1: P. A ANT | L1: SEGURO | M1: P T | N1: TAG | O1: UBER GANANCIA | P1: RENTA | Q1: SEM PASADA | R1: FIANZA | S1: MULTA | T1: HOJALATERO | U1: DESCUENTOS | V1: PRÉSTAMOS | W1: TOTAL | X1: A PAGAR | Y1: DEV | Z1: PAGADO | AA1: ADEUDO | AB1: GANANCIAS TOTALES | AC1: Anticipo F | AD1: COMENTARIOS
A2: 1 | B2: ALEJANDRO PAZ CAMACHO | C2: MARCH|2020|TURQ|N15BKD | D2: OHLM038285789 | E2: =VLOOKUP(C2,'[2]CTRL AUTOS'!$E$2:$L$58,8,FALSE) -> ASHC | F2: =VLOOKUP(C2,'[2]CTRL AUTOS'!$E$2:$K$58,7,FALSE) -> ASHC | G2: DIDI | H2: 4784.74 | I2: -6209.03 | J2: -620 | K2: 0 | L2: 0 | M2: -95 | N2: 0 | O2: =IF(H2+I2<0,SUM(J2:N2),SUM(H2:N2)) -> -715 | P2: -2600 | Q2: -2771.97 | R2: 0 | S2: 0 | T2: 0 | U2: 0 | V2: 0 | W2: =SUM(O2:V2) -> -6086.97 | X2: =IF(W2>=0,W2,0) -> 0 | Y2: =IF(W2<=0,W2,0) -> -6086.97 | Z2: =800+2357 -> 3157 | AA2: =+Y2+Z2 -> -2929.97 | AB2: =+O2-X2+Z2+AA2 -> -487.97 | AD2: SE CONDONA ADEUDO Y SE AJUSTA DEUDO 2025
A3: 1 | B3: RAUL FRANCISCO VAZQUEZ CORTE | C3: V DRIVE|2023|GRIS|MXW453C | D3: OHLM038626776 | E3: =VLOOKUP(C3,'[2]CTRL AUTOS'!$E$2:$L$58,8,FALSE) -> ASHC | F3: =VLOOKUP(C3,'[2]CTRL AUTOS'!$E$2:$K$58,7,FALSE) -> ASHC | G3: DIDI | H3: 176.49 | I3: -130.25 | J3: -13 | K3: 0 | L3: 0 | M3: -65 | N3: 0 | O3: =IF(H3+I3<0,SUM(J3:N3),SUM(H3:N3)) -> -31.76 | P3: -2500 | Q3: -94 | R3: 0 | S3: 0 | T3: -500 | U3: 0 | V3: 0 | W3: =SUM(O3:V3) -> -3125.76 | X3: =IF(W3>=0,W3,0) -> 0 | Y3: =IF(W3<=0,W3,0) -> -3125.76 | Z3: 2800 | AA3: =+Y3+Z3 -> -325.76 | AB3: =+O3-X3+Z3+AA3 -> 2442.48 | AD3: DA RENTA POR FUERA HOJALATERIA 11/18, PAGA 2,800 11 ENE
A4: 1 | B4: FRANCISCO RODOLFO GOMEZ URQUIZA ESCALANTE | C4: KIA RIO|2020|AZUL|LUE960C | D4: OHLM035935635 | E4: ASHC | F4: ASHC | G4: DIDI | H4: 2721.77 | I4: -2373.6 | J4: -237 | K4: 0 | L4: 0 | M4: -95 | N4: 0 | O4: =IF(H4+I4<0,SUM(J4:N4),SUM(H4:N4)) -> 16.17 | P4: -2600 | Q4: 0 | R4: 0 | S4: 0 | T4: 0 | U4: 0 | V4: 0 | W4: =SUM(O4:V4) -> -2583.83 | X4: =IF(W4>=0,W4,0) -> 0 | Y4: =IF(W4<=0,W4,0) -> -2583.83 | Z4: 2857 | AA4: =+Y4+Z4 -> 273.17 | AB4: =+O4-X4+Z4+AA4 -> 3146.34 | AD4: TRABAJA DIDI-ASHC, PAGO 2,857 10 ENE (273 DE DIDI ATRASOS)
A5: 1 | B5: FRANCISCO ISLAS CHAVEZ | C5: AVEO|2024|GRIS|LRL009C | D5: OHLM032762171 | E5: =VLOOKUP(C5,'[2]CTRL AUTOS'!$E$2:$L$58,8,FALSE) -> ASHC | F5: =VLOOKUP(C5,'[2]CTRL AUTOS'!$E$2:$K$58,7,FALSE) -> ASHC | G5: DIDI | H5: 5249.01 | I5: -6142.27 | J5: -614 | K5: 0 | L5: 0 | M5: -95 | N5: 0 | O5: =IF(H5+I5<0,SUM(J5:N5),SUM(H5:N5)) -> -709 | P5: -2600 | Q5: 0 | R5: 0 | S5: 0 | T5: 0 | U5: 0 | V5: 0 | W5: =SUM(O5:V5) -> -3309 | X5: =IF(W5>=0,W5,0) -> 0 | Y5: =IF(W5<=0,W5,0) -> -3309 | Z5: =1200+1000 -> 2200 | AA5: =+Y5+Z5 -> -1109 | AB5: =+O5-X5+Z5+AA5 -> 382 | AD5: TRABAJA AMBAS APPS | PAGO 7 ENE 1,200 + 1,000 10 ENE GESTIONAR PAGO URGE
A6: 1 | B6: ADALBERTO BELLO NAVARRO | C6: AVEO|2025|PERSUASION|MXM510C | D6: OHLM038285821 | E6: =VLOOKUP(C6,'[2]CTRL AUTOS'!$E$2:$L$58,8,FALSE) -> ASHC | F6: =VLOOKUP(C6,'[2]CTRL AUTOS'!$E$2:$K$58,7,FALSE) -> ASHC | G6: UBER | H6: 8443.13 | I6: -5565.59 | J6: -20.8 | K6: 0 | L6: 0 | M6: -60 | N6: 0 | O6: =IF(H6+I6<0,SUM(J6:N6),SUM(H6:N6)) -> 2796.74 | P6: -2700 | Q6: 0 | R6: 0 | S6: 0 | T6: 0 | U6: 0 | V6: 0 | W6: =SUM(O6:V6) -> 96.74 | X6: =IF(W6>=0,W6,0) -> 96.74 | Y6: =IF(W6<=0,W6,0) -> 0 | Z6: 0 | AA6: =+Y6+Z6 -> 0 | AB6: =+O6-X6+Z6+AA6 -> 2700
A7: 1 | B7: ADRIAN CRUZ CUADROS | C7: AVEO|2025|PERSUASION|MXM503C | D7: OHLM038285813 | E7: =VLOOKUP(C7,'[2]CTRL AUTOS'!$E$2:$L$58,8,FALSE) -> ASHC | F7: =VLOOKUP(C7,'[2]CTRL AUTOS'!$E$2:$K$58,7,FALSE) -> ASHC | G7: UBER | H7: 6903.68 | I7: 0 | J7: -66.72 | K7: 19.58 | L7: 0 | M7: -77 | N7: -89 | O7: =IF(H7+I7<0,SUM(J7:N7),SUM(H7:N7)) -> 6690.54 | P7: -2700 | Q7: 0 | R7: 0 | S7: 0 | T7: 0 | U7: 0 | V7: 0 | W7: =SUM(O7:V7) -> 3990.54 | X7: =IF(W7>=0,W7,0) -> 3990.54 | Y7: =IF(W7<=0,W7,0) -> 0 | Z7: 0 | AA7: =+Y7+Z7 -> 0 | AB7: =+O7-X7+Z7+AA7 -> 2700
A8: 1 | B8: ALBERTO ARRIAGA MEJIA | C8: AVEO|2020|AZUL|D28BET | D8: OHLM032370140 | E8: =VLOOKUP(C8,'[2]CTRL AUTOS'!$E$2:$L$58,8,FALSE) -> ASHC | F8: =VLOOKUP(C8,'[2]CTRL AUTOS'!$E$2:$K$58,7,FALSE) -> ASHC | G8: UBER | H8: 1020.36 | I8: -59.93 | J8: -11.2 | K8: 0 | L8: 0 | M8: -63 | N8: -71 | O8: =IF(H8+I8<0,SUM(J8:N8),SUM(H8:N8)) -> 815.23 | P8: -2500 | Q8: 0 | R8: -500 | S8: 0 | T8: 0 | U8: 0 | V8: 0 | W8: =SUM(O8:V8) -> -2184.77 | X8: =IF(W8>=0,W8,0) -> 0 | Y8: =IF(W8<=0,W8,0) -> -2184.77 | Z8: =1100+1085 -> 2185 | AA8: =+Y8+Z8 -> 0.23 | AB8: =+O8-X8+Z8+AA8 -> 3000.46 | AD8: FIANZA 7/11 PAGO 7 ENE 1,100 + 1,085 8 ENE
A9: 1 | B9: ANGEL ALCANTARA CRUZ | C9: AVEO|2025|PERSUASION|MZN091C | D9: OHLM038626768 | E9: =VLOOKUP(C9,'[2]CTRL AUTOS'!$E$2:$L$58,8,FALSE) -> ASHC | F9: =VLOOKUP(C9,'[2]CTRL AUTOS'!$E$2:$K$58,7,FALSE) -> ASHC | G9: UBER | H9: 668.17 | I9: -29.99 | J9: -4.48 | K9: 0 | L9: 0 | M9: -60 | N9: 0 | O9: =IF(H9+I9<0,SUM(J9:N9),SUM(H9:N9)) -> 573.7 | P9: 0 | Q9: -737 | R9: 0 | S9: 0 | T9: 0 | U9: 0 | V9: 0 | W9: =SUM(O9:V9) -> -163.3 | X9: =IF(W9>=0,W9,0) -> 0 | Y9: =IF(W9<=0,W9,0) -> -163.3 | Z9: 0 | AA9: =+Y9+Z9 -> -163.3 | AB9: =+O9-X9+Z9+AA9 -> 410.4 | AD9: ADEUDO SEM ANT - PROB FAM HIJA LEUSEM PAGA EL LUNES SE CONDONA LA CUENTA
A10: 1 | B10: ARMANDO MARTINEZ VELAZQUEZ | C10: HYUNDAI|2022|PLATA|D40BKD | D10: OHLM023658024 | E10: =VLOOKUP(C10,'[2]CTRL AUTOS'!$E$2:$L$58,8,FALSE) -> ASHC | F10: =VLOOKUP(C10,'[2]CTRL AUTOS'!$E$2:$K$58,7,FALSE) -> ASHC | G10: UBER | H10: 922.84 | I10: 0 | J10: -4.48 | K10: 0 | L10: -8.49 | M10: -60 | N10: 0 | O10: =IF(H10+I10<0,SUM(J10:N10),SUM(H10:N10)) -> 849.87 | P10: -357.14286 | Q10: 0 | R10: 0 | S10: 0 | T10: -600 | U10: 0 | V10: 0 | W10: =SUM(O10:V10) -> -107.27286 | X10: =IF(W10>=0,W10,0) -> 0 | Y10: =IF(W10<=0,W10,0) -> -107.27286 | Z10: 0 | AA10: =+Y10+Z10 -> -107.27286 | AB10: =+O10-X10+Z10+AA10 -> 742.59714 | AD10: HOJALATERIA 2/5 PAGA HASTA LA SEM 3 SIN DESC DE HOJ
A11: 1 | B11: CAMILO IESUA MEJIA DIAZ | C11: KIA RIO|2020|GRIS|NCK475B | D11: OHLM032370124 | E11: =VLOOKUP(C11,'[2]CTRL AUTOS'!$E$2:$L$58,8,FALSE) -> ASHC | F11: =VLOOKUP(C11,'[2]CTRL AUTOS'!$E$2:$K$58,7,FALSE) -> ASHC | G11: UBER | H11: 2560.11 | I11: -491.67 | J11: -16.96 | K11: 106.1 | L11: 0 | M11: -60 | N11: 0 | O11: =IF(H11+I11<0,SUM(J11:N11),SUM(H11:N11)) -> 2097.58 | P11: -2500 | Q11: 0 | R11: -500 | S11: 0 | T11: 0 | U11: 0 | V11: 0 | W11: =SUM(O11:V11) -> -902.42 | X11: =IF(W11>=0,W11,0) -> 0 | Y11: =IF(W11<=0,W11,0) -> -902.42 | Z11: 902 | AA11: =+Y11+Z11 -> -0.42 | AB11: =+O11-X11+Z11+AA11 -> 2999.16 | AD11: FIANZA 5/10 PAGO 7 ENE 902
A12: 1 | B12: DAVID ARTURO GONZALEZ TELLEZ | C12: AVEO|2025|PERSUASION|MXM502C | D12: OHLM038285805 | E12: =VLOOKUP(C12,'[2]CTRL AUTOS'!$E$2:$L$58,8,FALSE) -> ASHC | F12: =VLOOKUP(C12,'[2]CTRL AUTOS'!$E$2:$K$58,7,FALSE) -> ASHC | G12: UBER | H12: 1605.6 | I12: -1702.64 | J12: -9.44 | K12: 0 | L12: 0 | M12: -86 | N12: -125.49 | O12: =IF(H12+I12<0,SUM(J12:N12),SUM(H12:N12)) -> -220.93 | P12: -771.42 | Q12: -4976 | R12: 0 | S12: 0 | T12: -700 | U12: 0 | V12: 0 | W12: =SUM(O12:V12) -> -6668.35 | X12: =IF(W12>=0,W12,0) -> 0 | Y12: =IF(W12<=0,W12,0) -> -6668.35 | Z12: =1000+1300+1000 -> 3300 | AA12: =+Y12+Z12 -> -3368.35 | AB12: =+O12-X12+Z12+AA12 -> -289.28 | AD12: CTA PROP 2 DIAS PQ SALIO CDMX,HOJALATERIA 11/26 - 1,300 9 ENE + 1,000 11 ENE 8ene 1000
A13: 1 | B13: FERNANDO FUENTES OTERO | C13: AVEOH|2024|BLANCO|MWV156C | D13: OHLM038626743 | E13: =VLOOKUP(C13,'[2]CTRL AUTOS'!$E$2:$L$58,8,FALSE) -> ASHC | F13: =VLOOKUP(C13,'[2]CTRL AUTOS'!$E$2:$K$58,7,FALSE) -> ASHC | G13: UBER | H13: 309.82 | I13: 0 | J13: 0 | K13: 0 | L13: 0 | M13: -60 | N13: 0 | O13: =IF(H13+I13<0,SUM(J13:N13),SUM(H13:N13)) -> 249.82 | P13: -2500 | Q13: -250 | R13: 0 | S13: 0 | T13: 0 | U13: 0 | V13: 0 | W13: =SUM(O13:V13) -> -2500.18 | X13: =IF(W13>=0,W13,0) -> 0 | Y13: =IF(W13<=0,W13,0) -> -2500.18 | Z13: =610+473+375+400+500+306 -> 2664 | AA13: =+Y13+Z13 -> 163.82 | AB13: =+O13-X13+Z13+AA13 -> 3077.64 | AD13: PAGO TRANSF ASHC 5 ENE 610, 473 9 ENE, 375 10 ENE, 400 10 ENE, 500 11 ENE, 306 11 ENE
A14: 1 | B14: FRANCISCO GOMEZ URQUIZA SILVA | C14: VERSA|2023|PLATA|NCT814A | D14: OHLM031491780 | E14: =VLOOKUP(C14,'[2]CTRL AUTOS'!$E$2:$L$58,8,FALSE) -> ASHC | F14: =VLOOKUP(C14,'[2]CTRL AUTOS'!$E$2:$K$58,7,FALSE) -> ASHC | G14: UBER | H14: 4543.72 | I14: -2246.92 | J14: -31.84 | K14: 0 | L14: 0 | M14: -65 | N14: 0 | O14: =IF(H14+I14<0,SUM(J14:N14),SUM(H14:N14)) -> 2199.96 | P14: -2500 | Q14: 0 | R14: -500 | S14: 0 | T14: 0 | U14: 0 | V14: 0 | W14: =SUM(O14:V14) -> -800.04 | X14: =IF(W14>=0,W14,0) -> 0 | Y14: =IF(W14<=0,W14,0) -> -800.04 | Z14: 800 | AA14: =+Y14+Z14 -> -0.04 | AB14: =+O14-X14+Z14+AA14 -> 2999.92 | AD14: FIANZA 5/10 - PAGO 800 6 ENE
A15: 1 | B15: FRANCISCO ISLAS CHAVEZ | C15: AVEO|2024|GRIS|LRL009C | D15: OHLM032762171 | E15: =VLOOKUP(C15,'[2]CTRL AUTOS'!$E$2:$L$58,8,FALSE) -> ASHC | F15: =VLOOKUP(C15,'[2]CTRL AUTOS'!$E$2:$K$58,7,FALSE) -> ASHC | G15: UBER | H15: 95.23 | I15: -80.21 | J15: 0 | K15: 0 | L15: 0 | M15: -15 | N15: 0 | O15: =IF(H15+I15<0,SUM(J15:N15),SUM(H15:N15)) -> 0.02 | P15: 0 | Q15: 0 | R15: 0 | S15: 0 | T15: 0 | U15: 0 | V15: 0 | W15: =SUM(O15:V15) -> 0.02 | X15: =IF(W15>=0,W15,0) -> 0.02 | Y15: =IF(W15<=0,W15,0) -> 0 | Z15: 0 | AA15: =+Y15+Z15 -> 0 | AB15: =+O15-X15+Z15+AA15 -> 0 | AD15: SE COBRA CTA COMPL EN DIDI
A16: 1 | B16: GERMAN LUSARRETA ROMERO | C16: AVEO|2021|GRIS|D51BHV | D16: OHLM037480324 | E16: =VLOOKUP(C16,'[2]CTRL AUTOS'!$E$2:$L$58,8,FALSE) -> ASHC | F16: =VLOOKUP(C16,'[2]CTRL AUTOS'!$E$2:$K$58,7,FALSE) -> ASHC | G16: UBER | H16: 5101.6 | I16: -1716.25 | J16: -23.84 | K16: 311.99 | L16: 0 | M16: -66.5 | N16: -25.87 | O16: =IF(H16+I16<0,SUM(J16:N16),SUM(H16:N16)) -> 3581.13 | P16: -2500 | Q16: 0 | R16: -500 | S16: 0 | T16: 0 | U16: 0 | V16: 0 | W16: =SUM(O16:V16) -> 581.13 | X16: =IF(W16>=0,W16,0) -> 581.13 | Y16: =IF(W16<=0,W16,0) -> 0 | Z16: 0 | AA16: =+Y16+Z16 -> 0 | AB16: =+O16-X16+Z16+AA16 -> 3000 | AD16: FIANZA 6/11
A17: 1 | B17: JESUS ROSALES GARCIA | C17: AVEOH|2026|ACERO|NEJ996C | D17: SIN TAG | E17: =VLOOKUP(C17,'[2]CTRL AUTOS'!$E$2:$L$58,8,FALSE) -> ASHC | F17: =VLOOKUP(C17,'[2]CTRL AUTOS'!$E$2:$K$58,7,FALSE) -> ASHC | G17: UBER | H17: 10752.02 | I17: -5054.19 | J17: -36.48 | K17: 0 | L17: 0 | M17: -65 | N17: 0 | O17: =IF(H17+I17<0,SUM(J17:N17),SUM(H17:N17)) -> 5596.35 | P17: =-357.14-2314.28 -> -2671.42 | Q17: 0 | R17: -500 | S17: 0 | T17: 0 | U17: 0 | V17: 0 | W17: =SUM(O17:V17) -> 2424.93 | X17: =IF(W17>=0,W17,0) -> 2424.93 | Y17: =IF(W17<=0,W17,0) -> 0 | Z17: 0 | AA17: =+Y17+Z17 -> 0 | AB17: =+O17-X17+Z17+AA17 -> 3171.42 | AD17: CTA PROPDEL LUNES 2,500, RESTO DE SEM 2700
A18: 1 | B18: JONATHAN BERNAL RODRIGUEZ | C18: AVEO|2018|GRIS|X59AWG | D18: OHLM031409063 | E18: =VLOOKUP(C18,'[2]CTRL AUTOS'!$E$2:$L$58,8,FALSE) -> ASHC | F18: =VLOOKUP(C18,'[2]CTRL AUTOS'!$E$2:$K$58,7,FALSE) -> ASHC | G18: UBER | H18: 2245.26 | I18: -363.75 | J18: 0 | K18: 0 | L18: -24.09 | M18: -140 | N18: -378.18 | O18: =IF(H18+I18<0,SUM(J18:N18),SUM(H18:N18)) -> 1339.24 | P18: -2500 | Q18: -627 | R18: -500 | S18: 0 | T18: 0 | U18: 0 | V18: 0 | W18: =SUM(O18:V18) -> -2287.76 | X18: =IF(W18>=0,W18,0) -> 0 | Y18: =IF(W18<=0,W18,0) -> -2287.76 | Z18: 1800 | AA18: =+Y18+Z18 -> -487.76 | AB18: =+O18-X18+Z18+AA18 -> 2651.48 | AD18: PAGA 1,800 10 ENE
A19: 1 | B19: JOSE GUILLERMO HERNANDEZ RAMIREZ | C19: AVEO|2023|GRIS|MLC126A | D19: OHLM037480332 | E19: =VLOOKUP(C19,'[2]CTRL AUTOS'!$E$2:$L$58,8,FALSE) -> ASHC | F19: =VLOOKUP(C19,'[2]CTRL AUTOS'!$E$2:$K$58,7,FALSE) -> ASHC | G19: UBER | H19: 7594.7 | I19: -3449.65 | J19: -36.48 | K19: 0 | L19: 0 | M19: -65 | N19: 0 | O19: =IF(H19+I19<0,SUM(J19:N19),SUM(H19:N19)) -> 4043.57 | P19: -1250 | Q19: -360 | R19: 0 | S19: 0 | T19: 0 | U19: 0 | V19: 0 | W19: =SUM(O19:V19) -> 2433.57 | X19: =IF(W19>=0,W19,0) -> 2433.57 | Y19: =IF(W19<=0,W19,0) -> 0 | Z19: 0 | AA19: =+Y19+Z19 -> 0 | AB19: =+O19-X19+Z19+AA19 -> 1610 | AD19: REDUCCION DE CTA 1/2
A20: 1 | B20: JOSE JUAN HERNANDEZ MEJIA | C20: VENTO|2020|GRIS|A19BDY | D20: OHLM038626750 | E20: =VLOOKUP(C20,'[2]CTRL AUTOS'!$E$2:$L$58,8,FALSE) -> ASHC | F20: =VLOOKUP(C20,'[2]CTRL AUTOS'!$E$2:$K$58,7,FALSE) -> ASHC | G20: UBER | H20: 7690.57 | I20: -3610.68 | J20: -76.96 | K20: 0 | L20: 0 | M20: -65 | N20: 0 | O20: =IF(H20+I20<0,SUM(J20:N20),SUM(H20:N20)) -> 3937.93 | P20: -2500 | Q20: -210 | R20: 0 | S20: 0 | T20: 0 | U20: 0 | V20: 0 | W20: =SUM(O20:V20) -> 1227.93 | X20: =IF(W20>=0,W20,0) -> 1227.93 | Y20: =IF(W20<=0,W20,0) -> 0 | Z20: 0 | AA20: =+Y20+Z20 -> 0 | AB20: =+O20-X20+Z20+AA20 -> 2710
A21: 1 | B21: JUAN CARLOS ZEA CRUZ | C21: AVEO|2019|PLATA|NEL860A | D21: OHLM032370132 | E21: =VLOOKUP(C21,'[2]CTRL AUTOS'!$E$2:$L$58,8,FALSE) -> ASHC | F21: =VLOOKUP(C21,'[2]CTRL AUTOS'!$E$2:$K$58,7,FALSE) -> ASHC | G21: UBER | H21: 2373.01 | I21: -218.08 | J21: 0 | K21: 0 | L21: 0 | M21: -60 | N21: 0 | O21: =IF(H21+I21<0,SUM(J21:N21),SUM(H21:N21)) -> 2094.93 | P21: -2500 | Q21: 0 | R21: -500 | S21: 0 | T21: 0 | U21: 0 | V21: 0 | W21: =SUM(O21:V21) -> -905.07 | X21: =IF(W21>=0,W21,0) -> 0 | Y21: =IF(W21<=0,W21,0) -> -905.07 | Z21: 605 | AA21: =+Y21+Z21 -> -300.07 | AB21: =+O21-X21+Z21+AA21 -> 2399.86 | AD21: FIANZA 3/11 PAGO 7 ENE 605 NO CONTESTA
A22: 1 | B22: KRISTOPHER ALEXANDER TORREALBA RAMOS | C22: VENTO|2017|GRIS|MMA672C | D22: OHLM023720279 | E22: =VLOOKUP(C22,'[2]CTRL AUTOS'!$E$2:$L$58,8,FALSE) -> ASHC | F22: =VLOOKUP(C22,'[2]CTRL AUTOS'!$E$2:$K$58,7,FALSE) -> ASHC | G22: UBER | H22: 3703.3 | I22: -2282.87 | J22: 0 | K22: 0 | L22: 0 | M22: -60 | N22: 0 | O22: =IF(H22+I22<0,SUM(J22:N22),SUM(H22:N22)) -> 1360.43 | P22: -1360 | Q22: 0 | R22: 0 | S22: 0 | T22: 0 | U22: 0 | V22: 0 | W22: =SUM(O22:V22) -> 0.43 | X22: =IF(W22>=0,W22,0) -> 0.43 | Y22: =IF(W22<=0,W22,0) -> 0 | Z22: 0 | AA22: =+Y22+Z22 -> 0 | AB22: =+O22-X22+Z22+AA22 -> 1360 | AD22: CTA PROPAL JUEVES, ABANDONA AUTO, NO SE LE REGRESA FIANZA NI PAGO.
A23: 1 | B23: MARCO ANTONIO FARIAS AVILES | C23: BEAT|2019|OCRE|MAY730C | D23: OHLM036759058 | E23: =VLOOKUP(C23,'[2]CTRL AUTOS'!$E$2:$L$58,8,FALSE) -> ASHC | F23: =VLOOKUP(C23,'[2]CTRL AUTOS'!$E$2:$K$58,7,FALSE) -> ASHC | G23: UBER | H23: 1577.88 | I23: 0 | J23: -9.28 | K23: 0 | L23: 0 | M23: -65 | N23: 0 | O23: =IF(H23+I23<0,SUM(J23:N23),SUM(H23:N23)) -> 1503.6 | P23: -2500 | Q23: -76 | R23: -500 | S23: 0 | T23: 0 | U23: 0 | V23: 0 | W23: =SUM(O23:V23) -> -1572.4 | X23: =IF(W23>=0,W23,0) -> 0 | Y23: =IF(W23<=0,W23,0) -> -1572.4 | Z23: =1000+500 -> 1500 | AA23: =+Y23+Z23 -> -72.4 | AB23: =+O23-X23+Z23+AA23 -> 2931.2 | AD23: FIANZA 3/10 PAGO 7 ENE 1,000 Y 500 11 ENE
A24: 1 | B24: OSCAR BLANCAS NORIEGA | C24: VENTO|2020|GRIS|R66BER | D24: OHLM023720329 | E24: =VLOOKUP(C24,'[2]CTRL AUTOS'!$E$2:$L$58,8,FALSE) -> ASHC | F24: =VLOOKUP(C24,'[2]CTRL AUTOS'!$E$2:$K$58,7,FALSE) -> ASHC | G24: UBER | H24: 2073.67 | I24: -619.58 | J24: -14.4 | K24: 0 | L24: 0 | M24: -11 | N24: 0 | O24: =IF(H24+I24<0,SUM(J24:N24),SUM(H24:N24)) -> 1428.69 | P24: -1428.57 | Q24: 0 | R24: 0 | S24: 0 | T24: 0 | U24: 0 | V24: 0 | W24: =SUM(O24:V24) -> 0.12 | X24: =IF(W24>=0,W24,0) -> 0.12 | Y24: =IF(W24<=0,W24,0) -> 0 | Z24: 0 | AA24: =+Y24+Z24 -> 0 | AB24: =+O24-X24+Z24+AA24 -> 1428.57 | AD24: CTA PROP 4 DÍAS, SE BAJA VIE, ADEUDA HOJTRIA, LLAVE, Y LAV INTER (SIN DEV DE FIANZA)
A25: 1 | B25: RAYMUNDO CHAVEZ DELGADO | C25: AVEOH|2026|ACERO|NEJ971C | D25: SIN TAG | E25: =VLOOKUP(C25,'[2]CTRL AUTOS'!$E$2:$L$58,8,FALSE) -> ASHC | F25: =VLOOKUP(C25,'[2]CTRL AUTOS'!$E$2:$K$58,7,FALSE) -> ASHC | G25: UBER | H25: 3451.27 | I25: -1775.14 | J25: -16.96 | K25: 127.04 | L25: -42.97 | M25: -65 | N25: 0 | O25: =IF(H25+I25<0,SUM(J25:N25),SUM(H25:N25)) -> 1678.24 | P25: =-357.14-2314.28 -> -2671.42 | Q25: 0 | R25: -500 | S25: 0 | T25: 0 | U25: 0 | V25: 0 | W25: =SUM(O25:V25) -> -1493.18 | X25: =IF(W25>=0,W25,0) -> 0 | Y25: =IF(W25<=0,W25,0) -> -1493.18 | Z25: 0 | AA25: =+Y25+Z25 -> -1493.18 | AB25: =+O25-X25+Z25+AA25 -> 185.06 | AD25: CTA LUNES 2,500, MAR-DOM 2700, FIANZA 10/10 - QUEDA CON ROUS PAGO EN DOS EXHIBISIONES S2 746.5 Y S3 746.5 +12%
A26: 1 | B26: RICARDO HERNANDEZ ARIAS | C26: AVEO|2019|BLANCO|NBS225A | D26: OHLM038285797 | E26: =VLOOKUP(C26,'[2]CTRL AUTOS'!$E$2:$L$58,8,FALSE) -> ASHC | F26: =VLOOKUP(C26,'[2]CTRL AUTOS'!$E$2:$K$58,7,FALSE) -> ASHC | G26: UBER | H26: 7279.62 | I26: -277.08 | J26: -42.02 | K26: -5.32 | L26: 0 | M26: -65 | N26: 0 | O26: =IF(H26+I26<0,SUM(J26:N26),SUM(H26:N26)) -> 6890.2 | P26: -2500 | Q26: 0 | R26: 0 | S26: 0 | T26: -700 | U26: 0 | V26: 0 | W26: =SUM(O26:V26) -> 3690.2 | X26: =IF(W26>=0,W26,0) -> 3690.2 | Y26: =IF(W26<=0,W26,0) -> 0 | Z26: 0 | AA26: =+Y26+Z26 -> 0 | AB26: =+O26-X26+Z26+AA26 -> 3200 | AD26: HOJALATERIA 11/23
A27: 1 | B27: SAUL DOMINGUEZ VAZQUEZ | C27: VERSA|2020|BLANCO|A35BHD | D27: OHLM032370082 | E27: =VLOOKUP(C27,'[2]CTRL AUTOS'!$E$2:$L$58,8,FALSE) -> ASHC | F27: =VLOOKUP(C27,'[2]CTRL AUTOS'!$E$2:$K$58,7,FALSE) -> ASHC | G27: UBER | H27: 2853.66 | I27: -428.05 | J27: -34.56 | K27: 0 | L27: -23.35 | M27: -60 | N27: 0 | O27: =IF(H27+I27<0,SUM(J27:N27),SUM(H27:N27)) -> 2307.7 | P27: -2500 | Q27: 0 | R27: 0 | S27: 0 | T27: 0 | U27: 0 | V27: 0 | W27: =SUM(O27:V27) -> -192.3 | X27: =IF(W27>=0,W27,0) -> 0 | Y27: =IF(W27<=0,W27,0) -> -192.3 | Z27: 192 | AA27: =+Y27+Z27 -> -0.3 | AB27: =+O27-X27+Z27+AA27 -> 2499.4 | AD27: PAGA 192 6 ENE
A28: 1 | B28: SERGIO BALDERAS BAEZ | C28: AVEO|2022|AZUL|NZY685B | D28: OHLM032370116 | E28: =VLOOKUP(C28,'[2]CTRL AUTOS'!$E$2:$L$58,8,FALSE) -> ASHC | F28: =VLOOKUP(C28,'[2]CTRL AUTOS'!$E$2:$K$58,7,FALSE) -> ASHC | G28: UBER | H28: 5549.21 | I28: -1856.39 | J28: -18.88 | K28: 0 | L28: 0 | M28: -65 | N28: 0 | O28: =IF(H28+I28<0,SUM(J28:N28),SUM(H28:N28)) -> 3608.94 | P28: -2500 | Q28: 0 | R28: -500 | S28: 0 | T28: 0 | U28: -1000 | V28: 0 | W28: =SUM(O28:V28) -> -391.06 | X28: =IF(W28>=0,W28,0) -> 0 | Y28: =IF(W28<=0,W28,0) -> -391.06 | Z28: 391 | AA28: =+Y28+Z28 -> -0.06 | AB28: =+O28-X28+Z28+AA28 -> 3999.88 | AD28: FIANZA 7/10, PAGA ADEUDO 2/2 | PAGO 7 ENE 391
A29: 1 | B29: YOSHUA JARETH VALDEZ HERNANDEZ | C29: KIA RIO|2017|ROJO|MYE912A | D29: OHLM032762130 | E29: =VLOOKUP(C29,'[2]CTRL AUTOS'!$E$2:$L$58,8,FALSE) -> U64 | F29: =VLOOKUP(C29,'[2]CTRL AUTOS'!$E$2:$K$58,7,FALSE) -> BYER | G29: UBER | H29: 1169.28 | I29: -370.52 | J29: -4.48 | K29: 0 | L29: 0 | M29: -65 | N29: 0 | O29: =IF(H29+I29<0,SUM(J29:N29),SUM(H29:N29)) -> 729.28 | P29: -2500 | Q29: 871 | R29: 0 | S29: 0 | T29: 0 | U29: 0 | V29: 0 | W29: =SUM(O29:V29) -> -899.72 | X29: =IF(W29>=0,W29,0) -> 0 | Y29: =IF(W29<=0,W29,0) -> -899.72 | Z29: 900 | AA29: =+Y29+Z29 -> 0.28 | AB29: =+O29-X29+Z29+AA29 -> 1629.56 | AD29: SEM 817 A FAVOR, ADEUDO DE GOLPE 2018, $5000 SEMANALES - DEPOSITA 3,000 6 ENE (900 A CUENTA Y 2,100 GLPE PED)
A30: 1 | B30: JOSE AGUILAR SOTO | C30: AVEO|2020|AZUL|D28BET | D30: OHLM032370140 | E30: =VLOOKUP(C30,'[2]CTRL AUTOS'!$E$2:$L$58,8,FALSE) -> ASHC | F30: =VLOOKUP(C30,'[2]CTRL AUTOS'!$E$2:$K$58,7,FALSE) -> ASHC | G30: UBER | H30: 0 | I30: 0 | J30: 0 | K30: 0 | L30: 0 | M30: 0 | N30: 0 | O30: =IF(H30+I30<0,SUM(J30:N30),SUM(H30:N30)) -> 0 | P30: 0 | Q30: 0 | R30: 500 | S30: 0 | T30: 0 | U30: 0 | V30: 0 | W30: =SUM(O30:V30) -> 500 | X30: =IF(W30>=0,W30,0) -> 500 | Y30: =IF(W30<=0,W30,0) -> 0 | Z30: 0 | AA30: =+Y30+Z30 -> 0 | AB30: =+O30-X30+Z30+AA30 -> -500 | AD30: DEV FIANZA 7/10
A31: 1 | B31: RUBEN BERMEJO | C31: AVEO|2022|VINO|P62BHW | D31: OHLM037480340 | E31: =VLOOKUP(C31,'[2]CTRL AUTOS'!$E$2:$L$58,8,FALSE) -> ASHC | F31: BYER | G31: UBER | H31: 0 | I31: 0 | J31: 0 | K31: 0 | L31: 0 | M31: 0 | N31: 0 | O31: =IF(H31+I31<0,SUM(J31:N31),SUM(H31:N31)) -> 0 | P31: 0 | Q31: 0 | R31: 500 | S31: 0 | T31: 0 | U31: 0 | V31: 0 | W31: =SUM(O31:V31) -> 500 | X31: =IF(W31>=0,W31,0) -> 500 | Y31: =IF(W31<=0,W31,0) -> 0 | Z31: 0 | AA31: =+Y31+Z31 -> 0 | AB31: =+O31-X31+Z31+AA31 -> -500 | AD31: ULTIMO PAGO DE FIANZA
A32: 1 | B32: FIDEL ALEJANDRO SANCHEZ VERGARA | C32: VERSA|2023|PLATA|NCT814A | D32: OHLM031491780 | E32: =VLOOKUP(C32,'[2]CTRL AUTOS'!$E$2:$L$58,8,FALSE) -> ASHC | F32: =VLOOKUP(C32,'[2]CTRL AUTOS'!$E$2:$K$58,7,FALSE) -> ASHC | G32: UBER | H32: 0 | I32: 0 | J32: 0 | K32: 0 | L32: 0 | M32: 0 | N32: 0 | O32: =IF(H32+I32<0,SUM(J32:N32),SUM(H32:N32)) -> 0 | P32: 0 | Q32: 0 | R32: 500 | S32: 0 | T32: 0 | U32: 0 | V32: 0 | W32: =SUM(O32:V32) -> 500 | X32: =IF(W32>=0,W32,0) -> 500 | Y32: =IF(W32<=0,W32,0) -> 0 | Z32: 0 | AA32: =+Y32+Z32 -> 0 | AB32: =+O32-X32+Z32+AA32 -> -500 | AD32: DEV DE FIANZA 3/7
A33: 1 | B33: JOSE LUIS HERNANDEZ MEDINA | C33: AVEO|2018|GRIS|X59AWG | D33: OHLM031409063 | E33: =VLOOKUP(C33,'[2]CTRL AUTOS'!$E$2:$L$58,8,FALSE) -> ASHC | F33: =VLOOKUP(C33,'[2]CTRL AUTOS'!$E$2:$K$58,7,FALSE) -> ASHC | G33: UBER | H33: 0 | I33: 0 | J33: 0 | K33: 0 | L33: 0 | M33: 0 | N33: 0 | O33: =IF(H33+I33<0,SUM(J33:N33),SUM(H33:N33)) -> 0 | P33: 0 | Q33: 0 | R33: 0 | S33: 0 | T33: -700 | U33: 0 | V33: 0 | W33: =SUM(O33:V33) -> -700 | X33: =IF(W33>=0,W33,0) -> 0 | Y33: =IF(W33<=0,W33,0) -> -700 | Z33: 700 | AA33: =+Y33+Z33 -> 0 | AB33: =+O33-X33+Z33+AA33 -> 700 | AD33: TRABAJA APP JG UBER, HOJALATERIA 12/15 - PAGA 700 7 ENE
A34: 1 | B34: ALFONSO GONZALEZ MORALES | C34: SWIFT|2017|ROJO|X89ALV | D34: OHLM032370090 | E34: =VLOOKUP(C34,'[2]CTRL AUTOS'!$E$2:$L$58,8,FALSE) -> BYER | F34: =VLOOKUP(C34,'[2]CTRL AUTOS'!$E$2:$K$58,7,FALSE) -> BYER | G34: UBER | H34: 5950.53 | I34: -2088.56 | J34: -14.4 | K34: 14.69 | L34: 0 | M34: -62 | N34: 0 | O34: =IF(H34+I34<0,SUM(J34:N34),SUM(H34:N34)) -> 3800.26 | P34: -2500 | Q34: -600 | R34: 0 | S34: 0 | T34: -700 | U34: 0 | V34: 0 | W34: =SUM(O34:V34) -> 0.26 | X34: =IF(W34>=0,W34,0) -> 0.26 | Y34: =IF(W34<=0,W34,0) -> 0 | Z34: 0 | AA34: =+Y34+Z34 -> 0 | AB34: =+O34-X34+Z34+AA34 -> 3800 | AD34: ADEUDO SEMANA PASADA A 12%,HOJALATERIA 7/8
A35: 1 | B35: CRISTIAN HERNANDEZ MUNGUIA | C35: AVEOH|2026|ACERO|NEJ990C | D35: SIN TAG | E35: =VLOOKUP(C35,'[2]CTRL AUTOS'!$E$2:$L$58,8,FALSE) -> ASHC | F35: =VLOOKUP(C35,'[2]CTRL AUTOS'!$E$2:$K$58,7,FALSE) -> ASHC | G35: UBER | H35: 5116.35 | I35: -556.69 | J35: -11.68 | K35: 0 | L35: 0 | M35: -60 | N35: 0 | O35: =IF(H35+I35<0,SUM(J35:N35),SUM(H35:N35)) -> 4487.98 | P35: -1764.42 | Q35: 0 | R35: -500 | S35: 0 | T35: 0 | U35: 0 | V35: 0 | W35: =SUM(O35:V35) -> 2223.56 | X35: =IF(W35>=0,W35,0) -> 2223.56 | Y35: =IF(W35<=0,W35,0) -> 0 | Z35: 0 | AA35: =+Y35+Z35 -> 0 | AB35: =+O35-X35+Z35+AA35 -> 2264.42 | AD35: CTA PROP TRABAJO EN PLAT 1 DÍA 2,500 SEM RESTANTE 2,700.. FIANZA 6/11
A36: 1 | B36: EDUARDO LICONA GODINEZ | C36: KIA RIO|2020|ROJO|MFP751C | D36: OHLM036759090 | E36: =VLOOKUP(C36,'[2]CTRL AUTOS'!$E$2:$L$58,8,FALSE) -> ASHC | F36: =VLOOKUP(C36,'[2]CTRL AUTOS'!$E$2:$K$58,7,FALSE) -> ASHC | G36: UBER | H36: 5671.6 | I36: -4668.93 | J36: -18.88 | K36: 11.27 | L36: -64.21 | M36: -65 | N36: 0 | O36: =IF(H36+I36<0,SUM(J36:N36),SUM(H36:N36)) -> 865.85 | P36: -2500 | Q36: 6 | R36: -500 | S36: 0 | T36: 0 | U36: 0 | V36: 0 | W36: =SUM(O36:V36) -> -2128.15 | X36: =IF(W36>=0,W36,0) -> 0 | Y36: =IF(W36<=0,W36,0) -> -2128.15 | Z36: 2128 | AA36: =+Y36+Z36 -> -0.15 | AB36: =+O36-X36+Z36+AA36 -> 2993.7 | AD36: FIANZA 4/9 - PAGA 2,182 7 ENE
A37: 1 | B37: FERNANDO GARRIDO GARNICA | C37: AVEO|2018|ROJO|R51BKD | D37: OHLM032762106 | E37: =VLOOKUP(C37,'[2]CTRL AUTOS'!$E$2:$L$58,8,FALSE) -> U64 | F37: =VLOOKUP(C37,'[2]CTRL AUTOS'!$E$2:$K$58,7,FALSE) -> BYER | G37: UBER | H37: 5154.64 | I37: -2256.03 | J37: -17.28 | K37: 0 | L37: 0 | M37: -65 | N37: 0 | O37: =IF(H37+I37<0,SUM(J37:N37),SUM(H37:N37)) -> 2816.33 | P37: -2500 | Q37: 0 | R37: -500 | S37: 0 | T37: 0 | U37: 0 | V37: 0 | W37: =SUM(O37:V37) -> -183.67 | X37: =IF(W37>=0,W37,0) -> 0 | Y37: =IF(W37<=0,W37,0) -> -183.67 | Z37: 0 | AA37: =+Y37+Z37 -> -183.67 | AB37: =+O37-X37+Z37+AA37 -> 2632.66 | AD37: FIANZA 4/11
A38: 1 | B38: GABRIEL JIMENEZ BAUTISTA | C38: BYD|2026|VERDE|78F032 | D38: OHLM038628194 | E38: =VLOOKUP(C38,'[2]CTRL AUTOS'!$E$2:$L$58,8,FALSE) -> ASHC | F38: BYER | G38: UBER | H38: 2648.45 | I38: 0 | J38: -26.08 | K38: 0 | L38: 0 | M38: 0 | N38: 0 | O38: =IF(H38+I38<0,SUM(J38:N38),SUM(H38:N38)) -> 2622.37 | P38: -2622 | Q38: 0 | R38: 0 | S38: 0 | T38: 0 | U38: 0 | V38: 0 | W38: =SUM(O38:V38) -> 0.37 | X38: =IF(W38>=0,W38,0) -> 0.37 | Y38: =IF(W38<=0,W38,0) -> 0 | Z38: 0 | AA38: =+Y38+Z38 -> 0 | AB38: =+O38-X38+Z38+AA38 -> 2622 | AD38: OPERACION
A39: 1 | B39: IVAN MOGUEL PULIDO | C39: KIA RIO|2023|ROJO|H99BLC | D39: OHLM035993526 | E39: =VLOOKUP(C39,'[2]CTRL AUTOS'!$E$2:$L$58,8,FALSE) -> U64 | F39: =VLOOKUP(C39,'[2]CTRL AUTOS'!$E$2:$K$58,7,FALSE) -> BYER | G39: UBER | H39: 6575.11 | I39: -4131.59 | J39: -14.88 | K39: 0 | L39: -65.54 | M39: -65 | N39: 0 | O39: =IF(H39+I39<0,SUM(J39:N39),SUM(H39:N39)) -> 2298.1 | P39: -1250 | Q39: 0 | R39: 0 | S39: 0 | T39: 0 | U39: 0 | V39: 0 | W39: =SUM(O39:V39) -> 1048.1 | X39: =IF(W39>=0,W39,0) -> 1048.1 | Y39: =IF(W39<=0,W39,0) -> 0 | Z39: 0 | AA39: =+Y39+Z39 -> 0 | AB39: =+O39-X39+Z39+AA39 -> 1250 | AD39: REDUCCION DE CTA 1/2
A40: 1 | B40: RUBI ROBLES SALMERON | C40: BEAT|2020|GRIS|NFN014B | D40: OHLM032762148 | E40: =VLOOKUP(C40,'[2]CTRL AUTOS'!$E$2:$L$58,8,FALSE) -> U64 | F40: =VLOOKUP(C40,'[2]CTRL AUTOS'!$E$2:$K$58,7,FALSE) -> BYER | G40: UBER | H40: 4207.92 | I40: -1148.34 | J40: -18.88 | K40: 0 | L40: 0 | M40: -65 | N40: 0 | O40: =IF(H40+I40<0,SUM(J40:N40),SUM(H40:N40)) -> 2975.7 | P40: -2500 | Q40: -679 | R40: 0 | S40: 0 | T40: -500 | U40: 0 | V40: 0 | W40: =SUM(O40:V40) -> -703.3 | X40: =IF(W40>=0,W40,0) -> 0 | Y40: =IF(W40<=0,W40,0) -> -703.3 | Z40: =503+200 -> 703 | AA40: =+Y40+Z40 -> -0.3 | AB40: =+O40-X40+Z40+AA40 -> 3678.4 | AD40: HOJALATERIA 7/18,PROMESA DE PAGO DIA MARTES NO CONTESTA. PAGA 503 10 ENE Y 200 11 ENE
A41: 1 | B41: VICTOR HUGO RUIZ CASTILLO | C41: VERSA|2021|BLANCO|MEE228C | D41: OHLM036759082 | E41: =VLOOKUP(C41,'[2]CTRL AUTOS'!$E$2:$L$58,8,FALSE) -> ASHC | F41: BYER | G41: UBER | H41: 1302.83 | I41: -269.92 | J41: -4.48 | K41: 0 | L41: -18.81 | M41: -65 | N41: 0 | O41: =IF(H41+I41<0,SUM(J41:N41),SUM(H41:N41)) -> 944.62 | P41: -2500 | Q41: -87 | R41: -500 | S41: 0 | T41: 0 | U41: 0 | V41: 0 | W41: =SUM(O41:V41) -> -2142.38 | X41: =IF(W41>=0,W41,0) -> 0 | Y41: =IF(W41<=0,W41,0) -> -2142.38 | Z41: 2000 | AA41: =+Y41+Z41 -> -142.38 | AB41: =+O41-X41+Z41+AA41 -> 2802.24 | AD41: FIANZA 4/10, PROM PAGO DIA MARTES, PAGA 2,000 7 ENE
A42: 1 | B42: TOLENTINO JOSETH PEREZ GONZALEZ | C42: MARCH|2019|TURQ|MAY737C | D42: OHLM0367590666 | E42: =VLOOKUP(C42,'[2]CTRL AUTOS'!$E$2:$L$58,8,FALSE) -> BYER | F42: =VLOOKUP(C42,'[2]CTRL AUTOS'!$E$2:$K$58,7,FALSE) -> BYER | G42: UBER | H42: 1641.99 | I42: 0 | J42: -17.6 | K42: 0 | L42: -16.39 | M42: -60 | N42: 0 | O42: =IF(H42+I42<0,SUM(J42:N42),SUM(H42:N42)) -> 1548 | P42: -2500 | Q42: -2800 | R42: 0 | S42: 0 | T42: 0 | U42: 0 | V42: 0 | W42: =SUM(O42:V42) -> -3752 | X42: =IF(W42>=0,W42,0) -> 0 | Y42: =IF(W42<=0,W42,0) -> -3752 | Z42: 0 | AA42: =+Y42+Z42 -> -3752 | AB42: =+O42-X42+Z42+AA42 -> -2204 | AD42: NO CONTESTA
A43: 1 | B43: ADOLFO LOPEZ MARTINEZ | C43: VERSA|2020|ROJO|NLP172B | D43: OHLM032370108 | E43: =VLOOKUP(C43,'[2]CTRL AUTOS'!$E$2:$L$58,8,FALSE) -> ASHC | F43: =VLOOKUP(C43,'[2]CTRL AUTOS'!$E$2:$K$58,7,FALSE) -> ASHC | G43: UBER | H43: 0 | I43: 0 | J43: 0 | K43: 0 | L43: 0 | M43: 0 | N43: 0 | O43: =IF(H43+I43<0,SUM(J43:N43),SUM(H43:N43)) -> 0 | P43: -2500 | Q43: 0 | R43: 0 | S43: 0 | T43: 0 | U43: 0 | V43: 0 | W43: =SUM(O43:V43) -> -2500 | X43: =IF(W43>=0,W43,0) -> 0 | Y43: =IF(W43<=0,W43,0) -> -2500 | Z43: 2500 | AA43: =+Y43+Z43 -> 0 | AB43: =+O43-X43+Z43+AA43 -> 2500 | AD43: PAGO 7 ENE 2,500
A44: 1 | B44: NICASIO EMOS CONTRERAS | C44: AVEO|2025|PERSUASION|MZN057C | D44: OHLM038626735 | E44: =VLOOKUP(C44,'[2]CTRL AUTOS'!$E$2:$L$58,8,FALSE) -> ASHC | F44: =VLOOKUP(C44,'[2]CTRL AUTOS'!$E$2:$K$58,7,FALSE) -> ASHC | G44: UBER | H44: 0 | I44: 0 | J44: 0 | K44: 0 | L44: 0 | M44: 0 | N44: 0 | O44: =IF(H44+I44<0,SUM(J44:N44),SUM(H44:N44)) -> 0 | P44: -2000 | Q44: 0 | R44: 0 | S44: 0 | T44: 0 | U44: 0 | V44: 0 | W44: =SUM(O44:V44) -> -2000 | X44: =IF(W44>=0,W44,0) -> 0 | Y44: =IF(W44<=0,W44,0) -> -2000 | Z44: 2000 | AA44: =+Y44+Z44 -> 0 | AB44: =+O44-X44+Z44+AA44 -> 2000 | AD44: PAGO 5 ENE 2,000
A45: 1 | B45: OSCAR CONTRERAS ZUÑIGA | C45: AVEO|2022|VINO|P62BHW | D45: OHLM037480340 | E45: =VLOOKUP(C45,'[2]CTRL AUTOS'!$E$2:$L$58,8,FALSE) -> ASHC | F45: BYER | G45: UBER | H45: 10687.44 | I45: -6128.28 | J45: -65.92 | K45: 0 | L45: 0 | M45: -65 | N45: 0 | O45: =IF(H45+I45<0,SUM(J45:N45),SUM(H45:N45)) -> 4428.24 | P45: -2229 | Q45: 0 | R45: -429 | S45: 0 | T45: 0 | U45: 0 | V45: 0 | W45: =SUM(O45:V45) -> 1770.24 | X45: =IF(W45>=0,W45,0) -> 1770.24 | Y45: =IF(W45<=0,W45,0) -> 0 | Z45: 0 | AA45: =+Y45+Z45 -> 0 | AB45: =+O45-X45+Z45+AA45 -> 2658 | AD45: CTA PROP 5.5 DÍAS, FIANZA 1/8
A46: 1 | B46: DIEGO ISAID PULIDO | C46: AVEO|2023|VINO|R22BMR | D46: OHML037480316 | E46: =VLOOKUP(C46,'[2]CTRL AUTOS'!$E$2:$L$58,8,FALSE) -> ASHC | F46: =VLOOKUP(C46,'[2]CTRL AUTOS'!$E$2:$K$58,7,FALSE) -> ASHC | G46: UBER | H46: 3558.12 | I46: -1633.62 | J46: 0 | K46: 0 | L46: 0 | M46: -60 | N46: 0 | O46: =IF(H46+I46<0,SUM(J46:N46),SUM(H46:N46)) -> 1864.5 | P46: -2042.85 | Q46: 0 | R46: -393 | S46: 0 | T46: 0 | U46: 0 | V46: 0 | W46: =SUM(O46:V46) -> -571.35 | X46: =IF(W46>=0,W46,0) -> 0 | Y46: =IF(W46<=0,W46,0) -> -571.35 | Z46: 571 | AA46: =+Y46+Z46 -> -0.35 | AB46: =+O46-X46+Z46+AA46 -> 2435.15 | AD46: CTA PROP 5 DÍAS, FIANZA 1/10 PAGA 571 6 ENE
A47: 1 | B47: XAVIER ALAN LARA JIMENEZ | C47: AVEO|2022|AZUL|NZY685B | D47: OHLM032370116 | E47: =VLOOKUP(C47,'[2]CTRL AUTOS'!$E$2:$L$58,8,FALSE) -> ASHC | F47: =VLOOKUP(C47,'[2]CTRL AUTOS'!$E$2:$K$58,7,FALSE) -> ASHC | G47: UBER | H47: 2744.62 | I47: -1421.22 | J47: -20.48 | K47: 0 | L47: 0 | M47: -60 | N47: 0 | O47: =IF(H47+I47<0,SUM(J47:N47),SUM(H47:N47)) -> 1242.92 | P47: =-2500+357 -> -2143 | Q47: 0 | R47: -500 | S47: 0 | T47: 0 | U47: 0 | V47: 0 | W47: =SUM(O47:V47) -> -1400.08 | X47: =IF(W47>=0,W47,0) -> 0 | Y47: =IF(W47<=0,W47,0) -> -1400.08 | Z47: 1400 | AA47: =+Y47+Z47 -> -0.08 | AB47: =+O47-X47+Z47+AA47 -> 2642.84 | AD47: FIANZA 7/11 - PAGA 1,400 6 ENE
A48: 1 | B48: CRISTIAN HERNANDEZ MUNGUIA | C48: AVEO|2022|VINO|P62BHW | D48: OHLM037480340 | E48: =VLOOKUP(C48,'[2]CTRL AUTOS'!$E$2:$L$58,8,FALSE) -> ASHC | F48: BYER | G48: UBER | H48: 896.74 | I48: 0 | J48: -9.44 | K48: 19.58 | L48: 0 | M48: 0 | N48: 0 | O48: =IF(H48+I48<0,SUM(J48:N48),SUM(H48:N48)) -> 906.88 | P48: -907 | Q48: 0 | R48: 0 | S48: 0 | T48: 0 | U48: 0 | V48: 0 | W48: =SUM(O48:V48) -> -0.12 | X48: =IF(W48>=0,W48,0) -> 0 | Y48: =IF(W48<=0,W48,0) -> -0.12 | Z48: 0 | AA48: =+Y48+Z48 -> -0.12 | AB48: =+O48-X48+Z48+AA48 -> 906.76 | AD48: CTA PROP TRABAJO EN FLOTILLA
A49: 1 | B49: JESUS AURELIO NUNGARAY CASTILLO | C49: MARCH|2021|ROJO|NZU5163 | D49: OHLM03237015 | E49: =VLOOKUP(C49,'[2]CTRL AUTOS'!$E$2:$L$58,8,FALSE) -> ASHC | F49: =VLOOKUP(C49,'[2]CTRL AUTOS'!$E$2:$K$58,7,FALSE) -> ASHC | G49: DIDI | H49: 0 | I49: 0 | J49: 0 | K49: 0 | L49: 0 | M49: 0 | N49: 0 | O49: =IF(H49+I49<0,SUM(J49:N49),SUM(H49:N49)) -> 0 | P49: -2500 | Q49: 0 | R49: 0 | S49: 0 | T49: 0 | U49: 0 | V49: 0 | W49: =SUM(O49:V49) -> -2500 | X49: =IF(W49>=0,W49,0) -> 0 | Y49: =IF(W49<=0,W49,0) -> -2500 | Z49: 2500 | AA49: =+Y49+Z49 -> 0 | AB49: =+O49-X49+Z49+AA49 -> 2500 | AD49: GENERA EN DIDI COMO SOCIO
A50: 2 | B50: RAUL FRANCISCO VAZQUEZ CORTE | C50: V DRIVE|2023|GRIS|MXW453C | D50: OHLM038626776 | E50: =VLOOKUP(C50,'[2]CTRL AUTOS'!$E$2:$L$58,8,FALSE) -> ASHC | F50: =VLOOKUP(C50,'[2]CTRL AUTOS'!$E$2:$K$58,7,FALSE) -> ASHC | G50: DIDI | H50: 0 | I50: 0 | J50: 0 | K50: 0 | L50: 0 | M50: 0 | N50: 0 | O50: =IF(H50+I50<0,SUM(J50:N50),SUM(H50:N50)) -> 0 | P50: -2500 | Q50: =-326*1.12 -> -365.12 | R50: 0 | S50: 0 | T50: 0 | U50: 0 | V50: 0 | W50: =SUM(O50:V50) -> -2865.12 | X50: =IF(W50>=0,W50,0) -> 0 | Y50: =IF(W50<=0,W50,0) -> -2865.12 | Z50: 0 | AA50: =+Y50+Z50 -> -2865.12 | AB50: =+O50-X50+Z50+AA50 -> -2865.12 | AD50: PAGA EL DOMINGO
A51: 2 | B51: RAUL FRANCISCO VAZQUEZ CORTE | C51: VENTO|2017|GRIS|MMA672C | D51: OHLM023720279 | E51: =VLOOKUP(C51,'[2]CTRL AUTOS'!$E$2:$L$58,8,FALSE) -> ASHC | F51: =VLOOKUP(C51,'[2]CTRL AUTOS'!$E$2:$K$58,7,FALSE) -> ASHC | G51: DIDI | H51: 0 | I51: 0 | J51: 0 | K51: 0 | L51: 0 | M51: 0 | N51: 0 | O51: =IF(H51+I51<0,SUM(J51:N51),SUM(H51:N51)) -> 0 | P51: 0 | Q51: 0 | R51: 0 | S51: 0 | T51: -500 | U51: 0 | V51: 0 | W51: =SUM(O51:V51) -> -500 | X51: =IF(W51>=0,W51,0) -> 0 | Y51: =IF(W51<=0,W51,0) -> -500 | Z51: 0 | AA51: =+Y51+Z51 -> -500 | AB51: =+O51-X51+Z51+AA51 -> -500 | AD51: PAGA EL DOMINGO
A52: 2 | B52: FRANCISCO ISLAS CHAVEZ | C52: AVEO|2024|GRIS|LRL009C | D52: OHLM032762171 | E52: =VLOOKUP(C52,'[2]CTRL AUTOS'!$E$2:$L$58,8,FALSE) -> ASHC | F52: =VLOOKUP(C52,'[2]CTRL AUTOS'!$E$2:$K$58,7,FALSE) -> ASHC | G52: DIDI | H52: 4397 | I52: -4448 | J52: -444 | K52: 0 | L52: 0 | M52: -65 | N52: 0 | O52: =IF(H52+I52<0,SUM(J52:N52),SUM(H52:N52)) -> -509 | P52: -2600 | Q52: =-2002*1.12 -> -2242.24 | R52: 0 | S52: 0 | T52: 0 | U52: 0 | V52: 0 | W52: =SUM(O52:V52) -> -5351.24 | X52: =IF(W52>=0,W52,0) -> 0 | Y52: =IF(W52<=0,W52,0) -> -5351.24 | Z52: =600+700+1000+1300 -> 3600 | AA52: =+Y52+Z52 -> -1751.24 | AB52: =+O52-X52+Z52+AA52 -> 1339.76 | AD52: P12ENE 600 P14ENE 700 P16ENE 1000 P18ENE 1300
A53: 2 | B53: ADALBERTO BELLO NAVARRO | C53: AVEO|2025|PERSUASION|MXM510C | D53: OHLM038285821 | E53: =VLOOKUP(C53,'[2]CTRL AUTOS'!$E$2:$L$58,8,FALSE) -> ASHC | F53: =VLOOKUP(C53,'[2]CTRL AUTOS'!$E$2:$K$58,7,FALSE) -> ASHC | G53: UBER | H53: 4908 | I53: -3232 | J53: 0 | K53: 0 | L53: 0 | M53: -40 | N53: 0 | O53: =IF(H53+I53<0,SUM(J53:N53),SUM(H53:N53)) -> 1636 | P53: -2700 | Q53: 0 | R53: 0 | S53: 0 | T53: 0 | U53: 0 | V53: 0 | W53: =SUM(O53:V53) -> -1064 | X53: =IF(W53>=0,W53,0) -> 0 | Y53: =IF(W53<=0,W53,0) -> -1064 | Z53: 1000 | AA53: =+Y53+Z53 -> -64 | AB53: =+O53-X53+Z53+AA53 -> 2572 | AD53: PAGO 15 ENE 1000
A54: 2 | B54: ADRIAN CRUZ CUADROS | C54: AVEO|2025|PERSUASION|MXM503C | D54: OHLM038285813 | E54: =VLOOKUP(C54,'[2]CTRL AUTOS'!$E$2:$L$58,8,FALSE) -> ASHC | F54: =VLOOKUP(C54,'[2]CTRL AUTOS'!$E$2:$K$58,7,FALSE) -> ASHC | G54: UBER | H54: 5768 | I54: 0 | J54: -36 | K54: 31 | L54: 0 | M54: -85 | N54: -120 | O54: =IF(H54+I54<0,SUM(J54:N54),SUM(H54:N54)) -> 5558 | P54: -2700 | Q54: 0 | R54: 0 | S54: 0 | T54: 0 | U54: 0 | V54: 0 | W54: =SUM(O54:V54) -> 2858 | X54: =IF(W54>=0,W54,0) -> 2858 | Y54: =IF(W54<=0,W54,0) -> 0 | Z54: 0 | AA54: =+Y54+Z54 -> 0 | AB54: =+O54-X54+Z54+AA54 -> 2700
A55: 2 | B55: KEVIN ALEXIS MERLOS CORTES | C55: VENTO|2020|GRIS|R66BER | D55: OHLM02372032 | E55: =VLOOKUP(C55,'[2]CTRL AUTOS'!$E$2:$L$58,8,FALSE) -> ASHC | F55: =VLOOKUP(C55,'[2]CTRL AUTOS'!$E$2:$K$58,7,FALSE) -> ASHC | G55: UBER | H55: 4060 | I55: -2036 | J55: -54 | K55: 0 | L55: 0 | M55: -45 | N55: 0 | O55: =IF(H55+I55<0,SUM(J55:N55),SUM(H55:N55)) -> 1925 | P55: =-357.14*3 -> -1071.42 | Q55: 0 | R55: =-214 -> -214 | S55: 0 | T55: 0 | U55: 0 | V55: 0 | W55: =SUM(O55:V55) -> 639.58 | X55: =IF(W55>=0,W55,0) -> 639.58 | Y55: =IF(W55<=0,W55,0) -> 0 | Z55: 0 | AA55: =+Y55+Z55 -> 0 | AB55: =+O55-X55+Z55+AA55 -> 1285.42 | AC55: 2000 | AD55: SE DIO 2,000 DE FIANZA EN EFECTIVO
A56: 2 | B56: OSCAR IVAN MIÑON RAMIREZ | C56: MARCH|2020|TURQ|N15BKD | D56: OHLM03140907 | E56: =VLOOKUP(C56,'[2]CTRL AUTOS'!$E$2:$L$58,8,FALSE) -> ASHC | F56: =VLOOKUP(C56,'[2]CTRL AUTOS'!$E$2:$K$58,7,FALSE) -> ASHC | G56: UBER | H56: 6925 | I56: -3099 | J56: -139 | K56: 0 | L56: 0 | M56: -45 | N56: 0 | O56: =IF(H56+I56<0,SUM(J56:N56),SUM(H56:N56)) -> 3642 | P56: =(-2500/7)*5 -> -1785.7143 | Q56: 0 | R56: -357 | S56: 0 | T56: 0 | U56: 0 | V56: 0 | W56: =SUM(O56:V56) -> 1499.2857 | X56: =IF(W56>=0,W56,0) -> 1499.2857 | Y56: =IF(W56<=0,W56,0) -> 0 | Z56: 0 | AA56: =+Y56+Z56 -> 0 | AB56: =+O56-X56+Z56+AA56 -> 2142.7143 | AD56: INICIA MIER 7 26_CTA Y FIANZ PROP 5 DÍAS
A57: 2 | B57: DANIEL CASTAÑEDA LOPEZ | C57: AVEO|2020|AZUL|D28BET | D57: OHLM032370140 | E57: =VLOOKUP(C57,'[2]CTRL AUTOS'!$E$2:$L$58,8,FALSE) -> ASHC | F57: =VLOOKUP(C57,'[2]CTRL AUTOS'!$E$2:$K$58,7,FALSE) -> ASHC | G57: UBER | H57: 4467 | I57: -2397 | J57: 0 | K57: 0 | L57: 0 | M57: -55 | N57: 0 | O57: =IF(H57+I57<0,SUM(J57:N57),SUM(H57:N57)) -> 2015 | P57: =(-2500/7)*5.5 -> -1964.2857 | Q57: 0 | R57: =(-500/7)*5.5 -> -392.85714 | S57: 0 | T57: 0 | U57: 0 | V57: 0 | W57: =SUM(O57:V57) -> -342.14286 | X57: =IF(W57>=0,W57,0) -> 0 | Y57: =IF(W57<=0,W57,0) -> -342.14286 | Z57: 342 | AA57: =+Y57+Z57 -> -0.14285714 | AB57: =+O57-X57+Z57+AA57 -> 2356.8571 | AD57: INICIA MAR 6 26_CTA Y FIANZ PROP 5.5 DÍAS DEJA EN GARANTÍA 2 CARTERAS ORIG TOMY Y MKOR PAGO 16 ENE
A58: 2 | B58: JOEL RAUL PEREA PEÑA | C58: AVEO|2019|BLANCO|NBS225A | D58: OHLM038285797 | E58: =VLOOKUP(C58,'[2]CTRL AUTOS'!$E$2:$L$58,8,FALSE) -> ASHC | F58: =VLOOKUP(C58,'[2]CTRL AUTOS'!$E$2:$K$58,7,FALSE) -> ASHC | G58: UBER | H58: 1853 | I58: -1145 | J58: 0 | K58: 0 | M58: -45 | N58: 0 | O58: =IF(H58+I58<0,SUM(J58:N58),SUM(H58:N58)) -> 663 | P58: =(-2500/7)*3.5 -> -1250 | Q58: 0 | R58: =((-500/7)*3.5) -> -250 | S58: 0 | T58: 0 | U58: 0 | V58: 0 | W58: =SUM(O58:V58) -> -837 | X58: =IF(W58>=0,W58,0) -> 0 | Y58: =IF(W58<=0,W58,0) -> -837 | Z58: 0 | AA58: =+Y58+Z58 -> -837 | AB58: =+O58-X58+Z58+AA58 -> -174 | AC58: 1000 | AD58: INICIA JUE 8 26 ENTREGA 1000 FIANZA EN EFE MAÑANA PAGA UNA PARTE
A59: 2 | B59: JAVIER MEDINA JAIMES | C59: AVEO|2021|GRIS|D51BHV | D59: OHLM037480324 | E59: =VLOOKUP(C59,'[2]CTRL AUTOS'!$E$2:$L$58,8,FALSE) -> ASHC | F59: =VLOOKUP(C59,'[2]CTRL AUTOS'!$E$2:$K$58,7,FALSE) -> ASHC | G59: UBER | H59: 7562 | I59: -4538 | J59: 0 | K59: 0 | L59: 0 | M59: -55 | O59: =IF(H59+I59<0,SUM(J59:N59),SUM(H59:N59)) -> 2969 | P59: =(-2500/7)*6.5 -> -2321.4286 | Q59: 0 | R59: =(-500/7)*6.5 -> -464.28571 | S59: 0 | T59: 0 | U59: 0 | V59: 0 | W59: =SUM(O59:V59) -> 183.28571 | X59: =IF(W59>=0,W59,0) -> 183.28571 | Y59: =IF(W59<=0,W59,0) -> 0 | Z59: 0 | AA59: =+Y59+Z59 -> 0 | AB59: =+O59-X59+Z59+AA59 -> 2785.7143 | AD59: INICIA 5 ENE 26 DEJA EN GARANTÍA LAPTOP
A60: 2 | B60: ALBERTO ARRIAGA MEJIA | C60: AVEOH|2026|ROJO|NEZ101C | D60: OHLM03864557 | E60: =VLOOKUP(C60,'[2]CTRL AUTOS'!$E$2:$L$58,8,FALSE) -> ASHC | F60: =VLOOKUP(C60,'[2]CTRL AUTOS'!$E$2:$K$58,7,FALSE) -> ASHC | G60: UBER | H60: 2482 | I60: -836 | J60: 0 | K60: 0 | L60: 0 | M60: -83 | N60: -71 | O60: =IF(H60+I60<0,SUM(J60:N60),SUM(H60:N60)) -> 1492 | P60: -2700 | Q60: 0 | R60: 0 | S60: 0 | T60: 0 | U60: 0 | V60: 0 | W60: =SUM(O60:V60) -> -1208 | X60: =IF(W60>=0,W60,0) -> 0 | Y60: =IF(W60<=0,W60,0) -> -1208 | AA60: =+Y60+Z60 -> -1208 | AB60: =+O60-X60+Z60+AA60 -> 284 | AD60: FIANZA 8/11 SE BAJA DEL AUTO 15 ENE CON ADEUDO Y NOS QUEDAMOS CON LA FIANZA
A61: 2 | B61: ANGEL ALCANTARA CRUZ | C61: AVEO|2025|PERSUASION|MZN091C | D61: OHLM038626768 | E61: =VLOOKUP(C61,'[2]CTRL AUTOS'!$E$2:$L$58,8,FALSE) -> ASHC | F61: =VLOOKUP(C61,'[2]CTRL AUTOS'!$E$2:$K$58,7,FALSE) -> ASHC | G61: UBER | H61: 2939 | I61: -866 | J61: 0 | K61: 0 | L61: 0 | M61: -45 | N61: 0 | O61: =IF(H61+I61<0,SUM(J61:N61),SUM(H61:N61)) -> 2028 | P61: -2700 | Q61: =-163 -> -163 | R61: 0 | S61: 0 | T61: 0 | U61: 0 | V61: 0 | W61: =SUM(O61:V61) -> -835 | X61: =IF(W61>=0,W61,0) -> 0 | Y61: =IF(W61<=0,W61,0) -> -835 | Z61: 835 | AA61: =+Y61+Z61 -> 0 | AB61: =+O61-X61+Z61+AA61 -> 2863 | AD61: PAGO 14 ENE 835
A62: 2 | B62: ARMANDO MARTINEZ VELAZQUEZ | C62: HYUNDAI|2022|PLATA|D40BKD | D62: OHLM023658024 | E62: =VLOOKUP(C62,'[2]CTRL AUTOS'!$E$2:$L$58,8,FALSE) -> ASHC | F62: =VLOOKUP(C62,'[2]CTRL AUTOS'!$E$2:$K$58,7,FALSE) -> ASHC | G62: UBER | H62: 3152 | I62: -100 | J62: -15 | K62: 0 | L62: -30 | M62: -45 | N62: 0 | O62: =IF(H62+I62<0,SUM(J62:N62),SUM(H62:N62)) -> 2962 | P62: =(-2500/7)*5 -> -1785.7143 | Q62: -120 | R62: 0 | S62: 0 | T62: 0 | U62: 0 | V62: 0 | W62: =SUM(O62:V62) -> 1056.2857 | X62: =IF(W62>=0,W62,0) -> 1056.2857 | Y62: =IF(W62<=0,W62,0) -> 0 | Z62: 0 | AA62: =+Y62+Z62 -> 0 | AB62: =+O62-X62+Z62+AA62 -> 1905.7143 | AD62: PIDIO Q EL DESC FUERA HASTA LA SEM 3
A63: 2 | B63: ARMANDO MARTINEZ VELAZQUEZ | C63: AVEO|2026|GRIS|NEZ115C | D63: OHLM038638839 | E63: IVETT | F63: IVETT | G63: UBER | H63: 998.71 | I63: 0 | J63: -24 | K63: 0 | L63: 0 | M63: 0 | N63: 0 | O63: =IF(H63+I63<0,SUM(J63:N63),SUM(H63:N63)) -> 974.71 | P63: =(-2500/7)*2 -> -714.28571 | Q63: 0 | R63: 0 | S63: 0 | T63: 0 | U63: 0 | V63: 0 | W63: =SUM(O63:V63) -> 260.42429 | X63: =IF(W63>=0,W63,0) -> 260.42429 | Y63: =IF(W63<=0,W63,0) -> 0 | Z63: 0 | AA63: =+Y63+Z63 -> 0 | AB63: =+O63-X63+Z63+AA63 -> 714.28571
A64: 2 | B64: CAMILO IESUA MEJIA DIAZ | C64: KIA RIO|2020|GRIS|NCK475B | D64: OHLM032370124 | E64: =VLOOKUP(C64,'[2]CTRL AUTOS'!$E$2:$L$58,8,FALSE) -> ASHC | F64: =VLOOKUP(C64,'[2]CTRL AUTOS'!$E$2:$K$58,7,FALSE) -> ASHC | G64: UBER | H64: 2681 | I64: 0 | J64: 0 | K64: 0 | L64: 0 | M64: -55 | N64: 0 | O64: =IF(H64+I64<0,SUM(J64:N64),SUM(H64:N64)) -> 2626 | P64: -2500 | Q64: 0 | R64: -500 | S64: 0 | T64: 0 | U64: 0 | V64: 0 | W64: =SUM(O64:V64) -> -374 | X64: =IF(W64>=0,W64,0) -> 0 | Y64: =IF(W64<=0,W64,0) -> -374 | Z64: 374 | AA64: =+Y64+Z64 -> 0 | AB64: =+O64-X64+Z64+AA64 -> 3000 | AD64: FIANZA 6/10 PAGO 15 ENE EN EFECTIVO A ASHC
A65: 2 | B65: DAVID ARTURO GONZALEZ TELLEZ | C65: AVEO|2025|PERSUASION|MXM502C | D65: OHLM038285805 | E65: =VLOOKUP(C65,'[2]CTRL AUTOS'!$E$2:$L$58,8,FALSE) -> ASHC | F65: =VLOOKUP(C65,'[2]CTRL AUTOS'!$E$2:$K$58,7,FALSE) -> ASHC | G65: UBER | H65: 2331 | I65: -1666 | J65: 0 | K65: 0 | L65: 0 | M65: -62 | N65: -25 | O65: =IF(H65+I65<0,SUM(J65:N65),SUM(H65:N65)) -> 578 | P65: =-2700/7*4 -> -1542.8571 | Q65: =-3465*1.12 -> -3880.8 | R65: 0 | S65: 0 | T65: 0 | U65: 0 | V65: 0 | W65: =SUM(O65:V65) -> -4845.6571 | X65: =IF(W65>=0,W65,0) -> 0 | Y65: =IF(W65<=0,W65,0) -> -4845.6571 | Z65: =1400+500+1300+500 -> 3700 | AA65: =+Y65+Z65 -> -1145.6571 | AB65: =+O65-X65+Z65+AA65 -> 3132.3429 | AD65: P14ENE 1000|P14ENE 1400|P18ENE 1300
A66: 2 | B66: DAVID ARTURO GONZALEZ TELLEZ | C66: KIA RIO|2020|GRIS|NCK475B | D66: OHLM032370124 | E66: =VLOOKUP(C66,'[2]CTRL AUTOS'!$E$2:$L$58,8,FALSE) -> ASHC | F66: =VLOOKUP(C66,'[2]CTRL AUTOS'!$E$2:$K$58,7,FALSE) -> ASHC | G66: UBER | H66: 0 | I66: 0 | J66: 0 | K66: 0 | L66: 0 | M66: 0 | N66: 0 | O66: =IF(H66+I66<0,SUM(J66:N66),SUM(H66:N66)) -> 0 | P66: 0 | Q66: 0 | R66: 0 | S66: 0 | T66: -500 | U66: 0 | V66: 0 | W66: =SUM(O66:V66) -> -500 | X66: =IF(W66>=0,W66,0) -> 0 | Y66: =IF(W66<=0,W66,0) -> -500 | Z66: 500 | AA66: =+Y66+Z66 -> 0 | AB66: =+O66-X66+Z66+AA66 -> 500 | AD66: HOJALATERIA 12/26 P14ENE 1000 P18N 500
A67: 2 | B67: FERNANDO FUENTES OTERO | C67: AVEOH|2024|BLANCO|MWV156C | D67: OHLM038626743 | E67: =VLOOKUP(C67,'[2]CTRL AUTOS'!$E$2:$L$58,8,FALSE) -> ASHC | F67: =VLOOKUP(C67,'[2]CTRL AUTOS'!$E$2:$K$58,7,FALSE) -> ASHC | G67: UBER | H67: 127 | I67: 0 | J67: -3 | K67: 0 | L67: 0 | M67: -45 | N67: 0 | O67: =IF(H67+I67<0,SUM(J67:N67),SUM(H67:N67)) -> 79 | P67: -2500 | Q67: 164 | R67: 0 | S67: 0 | T67: 0 | U67: 0 | V67: 0 | W67: =SUM(O67:V67) -> -2257 | X67: =IF(W67>=0,W67,0) -> 0 | Y67: =IF(W67<=0,W67,0) -> -2257 | Z67: 0 | AA67: =+Y67+Z67 -> -2257 | AB67: =+O67-X67+Z67+AA67 -> -2178 | AD67: HOY PAGA
A68: 2 | B68: FERNANDO FUENTES OTERO | C68: KIA RIO|2020|ROJO|MFP751C | D68: OHLM036759090 | E68: =VLOOKUP(C68,'[2]CTRL AUTOS'!$E$2:$L$58,8,FALSE) -> ASHC | F68: =VLOOKUP(C68,'[2]CTRL AUTOS'!$E$2:$K$58,7,FALSE) -> ASHC | G68: UBER | H68: 0 | I68: 0 | J68: 0 | K68: 0 | L68: 0 | M68: 0 | N68: 0 | O68: =IF(H68+I68<0,SUM(J68:N68),SUM(H68:N68)) -> 0 | P68: 0 | Q68: 0 | R68: 0 | S68: 0 | T68: -500 | U68: 0 | V68: 0 | W68: =SUM(O68:V68) -> -500 | X68: =IF(W68>=0,W68,0) -> 0 | Y68: =IF(W68<=0,W68,0) -> -500 | Z68: 0 | AA68: =+Y68+Z68 -> -500 | AB68: =+O68-X68+Z68+AA68 -> -500 | AD68: HOJALAT 1/6 SE EMPIEZA A DESCONTAR DEBIDO A QUE NO FUE ARREGLADO A LA FECHA ACORDADA CON ROSA QUE ES 15DIC25| PENDIENTE COMPRA DE ANTENA Y DESCUENTO A CONDUCTOR
A69: 2 | B69: FRANCISCO GOMEZ URQUIZA SILVA | C69: VERSA|2023|PLATA|NCT814A | D69: OHLM031491780 | E69: =VLOOKUP(C69,'[2]CTRL AUTOS'!$E$2:$L$58,8,FALSE) -> ASHC | F69: =VLOOKUP(C69,'[2]CTRL AUTOS'!$E$2:$K$58,7,FALSE) -> ASHC | G69: UBER | H69: 4301 | I69: -1115 | J69: 0 | K69: 0 | L69: 0 | M69: -55 | N69: 0 | O69: =IF(H69+I69<0,SUM(J69:N69),SUM(H69:N69)) -> 3131 | P69: -1964 | Q69: 0 | R69: -500 | S69: 0 | T69: 0 | U69: 0 | V69: 0 | W69: =SUM(O69:V69) -> 667 | X69: =IF(W69>=0,W69,0) -> 667 | Y69: =IF(W69<=0,W69,0) -> 0 | Z69: 0 | AA69: =+Y69+Z69 -> 0 | AB69: =+O69-X69+Z69+AA69 -> 2464 | AD69: SE DESC 1.5 POR INGRESAR MECANC FIANZA 6/10
A70: 2 | B70: GERMAN LUSARRETA ROMERO | C70: AVEOH|2026|ROJO|NEZ108C | D70: SIN TAG | E70: =VLOOKUP(C70,'[2]CTRL AUTOS'!$E$2:$L$58,8,FALSE) -> ASHC | F70: =VLOOKUP(C70,'[2]CTRL AUTOS'!$E$2:$K$58,7,FALSE) -> ASHC | G70: UBER | H70: 5360 | I70: -2245 | J70: 0 | K70: 0 | L70: 0 | M70: -55 | N70: 0 | O70: =IF(H70+I70<0,SUM(J70:N70),SUM(H70:N70)) -> 3060 | P70: -2700 | Q70: 0 | R70: -500 | S70: 0 | T70: 0 | U70: 0 | V70: 0 | W70: =SUM(O70:V70) -> -140 | X70: =IF(W70>=0,W70,0) -> 0 | Y70: =IF(W70<=0,W70,0) -> -140 | Z70: 140 | AA70: =+Y70+Z70 -> 0 | AB70: =+O70-X70+Z70+AA70 -> 3200 | AD70: FIANZA 7/11 - PAGO 14 ENE 140
A71: 2 | B71: JESUS ROSALES GARCIA | C71: AVEOH|2026|ACERO|NEJ996C | D71: SIN TAG | E71: =VLOOKUP(C71,'[2]CTRL AUTOS'!$E$2:$L$58,8,FALSE) -> ASHC | F71: =VLOOKUP(C71,'[2]CTRL AUTOS'!$E$2:$K$58,7,FALSE) -> ASHC | G71: UBER | H71: 11323 | I71: -6879 | J71: -130 | K71: 0 | L71: 0 | M71: -55 | N71: 0 | O71: =IF(H71+I71<0,SUM(J71:N71),SUM(H71:N71)) -> 4259 | P71: -2700 | Q71: 0 | R71: -500 | S71: 0 | T71: 0 | U71: 0 | V71: 0 | W71: =SUM(O71:V71) -> 1059 | X71: =IF(W71>=0,W71,0) -> 1059 | Y71: =IF(W71<=0,W71,0) -> 0 | Z71: 0 | AA71: =+Y71+Z71 -> 0 | AB71: =+O71-X71+Z71+AA71 -> 3200 | AD71: FIANZA 7/10
A72: 2 | B72: JONATHAN BERNAL RODRIGUEZ | C72: AVEO|2018|GRIS|X59AWG | D72: OHLM031409063 | E72: =VLOOKUP(C72,'[2]CTRL AUTOS'!$E$2:$L$58,8,FALSE) -> ASHC | F72: =VLOOKUP(C72,'[2]CTRL AUTOS'!$E$2:$K$58,7,FALSE) -> ASHC | G72: UBER | H72: 1318 | I72: 0 | J72: 0 | K72: 0 | L72: -15 | M72: -140 | N72: -378 | O72: =IF(H72+I72<0,SUM(J72:N72),SUM(H72:N72)) -> 785 | P72: -2500 | Q72: =-488*1.12 -> -546.56 | R72: -500 | S72: 0 | T72: -700 | U72: 0 | V72: 0 | W72: =SUM(O72:V72) -> -3461.56 | X72: =IF(W72>=0,W72,0) -> 0 | Y72: =IF(W72<=0,W72,0) -> -3461.56 | Z72: 0 | AA72: =+Y72+Z72 -> -3461.56 | AB72: =+O72-X72+Z72+AA72 -> -2676.56 | AD72: FIANZA 4/11| HOJALATERIA 3 DE 11 ACUERDO CON ASHC
A73: 2 | B73: JOSE GUILLERMO HERNANDEZ RAMIREZ | C73: AVEO|2023|GRIS|MLC126A | D73: OHLM037480332 | E73: =VLOOKUP(C73,'[2]CTRL AUTOS'!$E$2:$L$58,8,FALSE) -> ASHC | F73: =VLOOKUP(C73,'[2]CTRL AUTOS'!$E$2:$K$58,7,FALSE) -> ASHC | G73: UBER | H73: 7847 | I73: -3913 | J73: -58 | K73: 0 | L73: 0 | M73: -55 | N73: 0 | O73: =IF(H73+I73<0,SUM(J73:N73),SUM(H73:N73)) -> 3821 | P73: -1250 | Q73: 34 | R73: 0 | S73: 0 | T73: 0 | U73: 0 | V73: 0 | W73: =SUM(O73:V73) -> 2605 | X73: =IF(W73>=0,W73,0) -> 2605 | Y73: =IF(W73<=0,W73,0) -> 0 | Z73: 0 | AA73: =+Y73+Z73 -> 0 | AB73: =+O73-X73+Z73+AA73 -> 1216 | AD73: REDUCCION DE CTA 2/2
A74: 2 | B74: JOSE JUAN HERNANDEZ MEJIA | C74: VENTO|2020|GRIS|A19BDY | D74: OHLM038626750 | E74: =VLOOKUP(C74,'[2]CTRL AUTOS'!$E$2:$L$58,8,FALSE) -> ASHC | F74: =VLOOKUP(C74,'[2]CTRL AUTOS'!$E$2:$K$58,7,FALSE) -> ASHC | G74: UBER | H74: 2216 | I74: -1483 | J74: 0 | K74: 0 | L74: 0 | M74: -55 | N74: 0 | O74: =IF(H74+I74<0,SUM(J74:N74),SUM(H74:N74)) -> 678 | P74: -2500 | Q74: 0 | R74: 0 | S74: 0 | T74: 0 | U74: 0 | V74: 0 | W74: =SUM(O74:V74) -> -1822 | X74: =IF(W74>=0,W74,0) -> 0 | Y74: =IF(W74<=0,W74,0) -> -1822 | Z74: 0 | AA74: =+Y74+Z74 -> -1822 | AB74: =+O74-X74+Z74+AA74 -> -1144 | AD74: SE COMUNICARÁ MÁS TARDE
A75: 2 | B75: JUAN CARLOS ZEA CRUZ | C75: AVEO|2019|PLATA|NEL860A | D75: OHLM032370132 | E75: =VLOOKUP(C75,'[2]CTRL AUTOS'!$E$2:$L$58,8,FALSE) -> ASHC | F75: =VLOOKUP(C75,'[2]CTRL AUTOS'!$E$2:$K$58,7,FALSE) -> ASHC | G75: UBER | H75: 2576 | I75: -1176 | J75: 0 | K75: 0 | L75: 0 | M75: -55 | N75: 0 | O75: =IF(H75+I75<0,SUM(J75:N75),SUM(H75:N75)) -> 1345 | P75: -2500 | Q75: =-300*1.12 -> -336 | R75: -500 | S75: 0 | T75: 0 | U75: 0 | V75: 0 | W75: =SUM(O75:V75) -> -1991 | X75: =IF(W75>=0,W75,0) -> 0 | Y75: =IF(W75<=0,W75,0) -> -1991 | Z75: 0 | AA75: =+Y75+Z75 -> -1991 | AB75: =+O75-X75+Z75+AA75 -> -646 | AD75: FIANZA 4/11 SE TUVO CONTACTO Y HASTA EL DOM PAGA
A76: 2 | B76: MARCO ANTONIO FARIAS AVILES | C76: BEAT|2019|OCRE|MAY730C | D76: OHLM036759058 | E76: =VLOOKUP(C76,'[2]CTRL AUTOS'!$E$2:$L$58,8,FALSE) -> ASHC | F76: =VLOOKUP(C76,'[2]CTRL AUTOS'!$E$2:$K$58,7,FALSE) -> ASHC | G76: UBER | H76: 83 | I76: 0 | J76: 0 | K76: 0 | L76: 0 | M76: -65 | N76: 0 | O76: =IF(H76+I76<0,SUM(J76:N76),SUM(H76:N76)) -> 18 | P76: -2500 | Q76: =-72*1.12 -> -80.64 | R76: -500 | S76: 0 | T76: 0 | U76: 0 | V76: 0 | W76: =SUM(O76:V76) -> -3062.64 | X76: =IF(W76>=0,W76,0) -> 0 | Y76: =IF(W76<=0,W76,0) -> -3062.64 | Z76: =1450+1150 -> 2600 | AA76: =+Y76+Z76 -> -462.64 | AB76: =+O76-X76+Z76+AA76 -> 2155.36 | AD76: FIANZA 4/10 PAGA 13 ENE 1400 PAGO MIER 15 1150
A77: 2 | B77: RAYMUNDO CHAVEZ DELGADO | C77: AVEOH|2026|ACERO|NEJ971C | D77: SIN TAG | E77: =VLOOKUP(C77,'[2]CTRL AUTOS'!$E$2:$L$58,8,FALSE) -> ASHC | F77: =VLOOKUP(C77,'[2]CTRL AUTOS'!$E$2:$K$58,7,FALSE) -> ASHC | G77: UBER | H77: 5369 | I77: -1733 | J77: 0 | K77: 121 | L77: -70 | M77: -55 | N77: 0 | O77: =IF(H77+I77<0,SUM(J77:N77),SUM(H77:N77)) -> 3632 | P77: -2121 | Q77: =-746*1.12 -> -835.52 | R77: 0 | S77: 0 | T77: 0 | U77: -200 | V77: 0 | W77: =SUM(O77:V77) -> 475.48 | X77: =IF(W77>=0,W77,0) -> 475.48 | Y77: =IF(W77<=0,W77,0) -> 0 | Z77: 0 | AA77: =+Y77+Z77 -> 0 | AB77: =+O77-X77+Z77+AA77 -> 3156.52 | AD77: DESC 1 DÍA INACTIVO|REPARACIÓN ESTEREO|1/2 DEV SEM 1 746
A78: 2 | B78: RICARDO HERNANDEZ ARIAS | C78: VERSA|2022|GRIS|NES596C | D78: OHLM038285797 | E78: =VLOOKUP(C78,'[2]CTRL AUTOS'!$E$2:$L$58,8,FALSE) -> ASHC | F78: =VLOOKUP(C78,'[2]CTRL AUTOS'!$E$2:$K$58,7,FALSE) -> ASHC | G78: UBER | H78: 5975 | I78: -270 | J78: -24 | K78: 0 | L78: 0 | M78: -55 | N78: 0 | O78: =IF(H78+I78<0,SUM(J78:N78),SUM(H78:N78)) -> 5626 | P78: -2500 | Q78: 0 | R78: 0 | S78: 0 | T78: -700 | U78: 0 | V78: 0 | W78: =SUM(O78:V78) -> 2426 | X78: =IF(W78>=0,W78,0) -> 2426 | Y78: =IF(W78<=0,W78,0) -> 0 | Z78: 0 | AA78: =+Y78+Z78 -> 0 | AB78: =+O78-X78+Z78+AA78 -> 3200 | AD78: HOJALAT 12/23 ADEUDO AUT JGD
A79: 2 | B79: SAUL DOMINGUEZ VAZQUEZ | C79: VERSA|2020|BLANCO|A35BHD | D79: OHLM032370082 | E79: =VLOOKUP(C79,'[2]CTRL AUTOS'!$E$2:$L$58,8,FALSE) -> ASHC | F79: =VLOOKUP(C79,'[2]CTRL AUTOS'!$E$2:$K$58,7,FALSE) -> ASHC | G79: UBER | H79: 3225 | I79: -215 | J79: -8 | K79: 0 | L79: -28 | M79: -45 | N79: 0 | O79: =IF(H79+I79<0,SUM(J79:N79),SUM(H79:N79)) -> 2929 | P79: -2500 | Q79: 0 | R79: 0 | S79: 0 | T79: 0 | U79: 0 | V79: 0 | W79: =SUM(O79:V79) -> 429 | X79: =IF(W79>=0,W79,0) -> 429 | Y79: =IF(W79<=0,W79,0) -> 0 | Z79: 0 | AA79: =+Y79+Z79 -> 0 | AB79: =+O79-X79+Z79+AA79 -> 2500 | AD79: PENDIENTE ARREGLO DE CAJUELA SEM 3
A80: 2 | B80: SERGIO BALDERAS BAEZ | C80: AVEO|2022|AZUL|NZY685B | D80: OHLM032370116 | E80: =VLOOKUP(C80,'[2]CTRL AUTOS'!$E$2:$L$58,8,FALSE) -> ASHC | F80: =VLOOKUP(C80,'[2]CTRL AUTOS'!$E$2:$K$58,7,FALSE) -> ASHC | G80: UBER | H80: 3384 | I80: -1555 | J80: 0 | K80: 0 | L80: 0 | M80: -65 | N80: 0 | O80: =IF(H80+I80<0,SUM(J80:N80),SUM(H80:N80)) -> 1764 | P80: -2500 | Q80: 0 | R80: -500 | S80: 0 | T80: 0 | U80: 0 | V80: 0 | W80: =SUM(O80:V80) -> -1236 | X80: =IF(W80>=0,W80,0) -> 0 | Y80: =IF(W80<=0,W80,0) -> -1236 | Z80: 0 | AA80: =+Y80+Z80 -> -1236 | AB80: =+O80-X80+Z80+AA80 -> 528 | AD80: FIANZA 8/10 PAGA 236 CON INTERÉS
A81: 2 | B81: CRISTIAN HERNANDEZ MUNGUIA | C81: AVEOH|2026|ACERO|NEJ990C | D81: OHLM038645594 | E81: =VLOOKUP(C81,'[2]CTRL AUTOS'!$E$2:$L$58,8,FALSE) -> ASHC | F81: =VLOOKUP(C81,'[2]CTRL AUTOS'!$E$2:$K$58,7,FALSE) -> ASHC | G81: UBER | H81: 4400 | I81: -1177 | J81: -48 | K81: -120 | L81: 0 | M81: -175 | N81: -442 | O81: =IF(H81+I81<0,SUM(J81:N81),SUM(H81:N81)) -> 2438 | P81: -2700 | Q81: 0 | R81: -500 | S81: 0 | T81: 0 | U81: 0 | V81: 0 | W81: =SUM(O81:V81) -> -762 | X81: =IF(W81>=0,W81,0) -> 0 | Y81: =IF(W81<=0,W81,0) -> -762 | Z81: 762 | AA81: =+Y81+Z81 -> 0 | AB81: =+O81-X81+Z81+AA81 -> 3200 | AD81: FIANZA 7/11 PAGO 14 ENE 762
A82: 2 | B82: EDUARDO LICONA GODINEZ | C82: KIA RIO|2020|ROJO|MFP751C | D82: OHLM036759090 | E82: =VLOOKUP(C82,'[2]CTRL AUTOS'!$E$2:$L$58,8,FALSE) -> ASHC | F82: =VLOOKUP(C82,'[2]CTRL AUTOS'!$E$2:$K$58,7,FALSE) -> ASHC | G82: UBER | H82: 6079 | I82: -3904 | J82: -32 | K82: 0 | L82: -63 | M82: -55 | N82: 0 | O82: =IF(H82+I82<0,SUM(J82:N82),SUM(H82:N82)) -> 2025 | P82: -2321 | Q82: 0 | R82: -500 | S82: 0 | T82: 0 | U82: 0 | V82: 0 | W82: =SUM(O82:V82) -> -796 | X82: =IF(W82>=0,W82,0) -> 0 | Y82: =IF(W82<=0,W82,0) -> -796 | Z82: 796 | AA82: =+Y82+Z82 -> 0 | AB82: =+O82-X82+Z82+AA82 -> 2821 | AD82: FIANZA 5/9
A83: 2 | B83: RUBI ROBLES SALMERON | C83: VERSA|2021|BLANCO|MEE228C | D83: OHLM036759082 | E83: =VLOOKUP(C83,'[2]CTRL AUTOS'!$E$2:$L$58,8,FALSE) -> ASHC | F83: =VLOOKUP(C83,'[2]CTRL AUTOS'!$E$2:$K$58,7,FALSE) -> ASHC | G83: UBER | H83: 1733 | I83: -1446 | J83: 42 | K83: 0 | L83: 0 | M83: -45 | N83: 0 | O83: =IF(H83+I83<0,SUM(J83:N83),SUM(H83:N83)) -> 284 | P83: =(-2500/7)*4 -> -1428.5714 | Q83: 0 | R83: 0 | S83: 0 | T83: -500 | U83: 0 | V83: 0 | W83: =SUM(O83:V83) -> -1644.5714 | X83: =IF(W83>=0,W83,0) -> 0 | Y83: =IF(W83<=0,W83,0) -> -1644.5714 | Z83: 0 | AA83: =+Y83+Z83 -> -1644.5714 | AB83: =+O83-X83+Z83+AA83 -> -1360.5714 | AD83: CTA PROP 4 DÍAS HOLT 8/9 RUBÍ CON ADEUDO + INTERÉS
A84: 2 | B84: DIEGO ISAID PULIDO | C84: AVEO|2023|VINO|R22BMR | D84: OHML037480316 | E84: =VLOOKUP(C84,'[2]CTRL AUTOS'!$E$2:$L$58,8,FALSE) -> ASHC | F84: =VLOOKUP(C84,'[2]CTRL AUTOS'!$E$2:$K$58,7,FALSE) -> ASHC | G84: UBER | H84: 4271 | I84: -2461 | J84: 0 | K84: 0 | L84: 0 | M84: -55 | N84: 0 | O84: =IF(H84+I84<0,SUM(J84:N84),SUM(H84:N84)) -> 1755 | P84: -2500 | Q84: 0 | R84: -500 | S84: 0 | T84: 0 | U84: 0 | V84: 0 | W84: =SUM(O84:V84) -> -1245 | X84: =IF(W84>=0,W84,0) -> 0 | Y84: =IF(W84<=0,W84,0) -> -1245 | Z84: 1150 | AA84: =+Y84+Z84 -> -95 | AB84: =+O84-X84+Z84+AA84 -> 2810 | AD84: FIANZA 2/10 PAGO 14 ENE 1150
A85: 2 | B85: XAVIER ALAN LARA JIMENEZ | C85: AVEO|2022|AZUL|MUF515A | D85: OHLM032370116 | E85: =VLOOKUP(C85,'[2]CTRL AUTOS'!$E$2:$L$58,8,FALSE) -> ASHC | F85: =VLOOKUP(C85,'[2]CTRL AUTOS'!$E$2:$K$58,7,FALSE) -> ASHC | G85: UBER | H85: 2584 | I85: -379 | J85: 0 | K85: 0 | L85: 0 | M85: -45 | N85: 0 | O85: =IF(H85+I85<0,SUM(J85:N85),SUM(H85:N85)) -> 2160 | P85: -2500 | Q85: 0 | R85: -500 | S85: 0 | T85: 0 | U85: 0 | V85: 0 | W85: =SUM(O85:V85) -> -840 | X85: =IF(W85>=0,W85,0) -> 0 | Y85: =IF(W85<=0,W85,0) -> -840 | Z85: 840 | AA85: =+Y85+Z85 -> 0 | AB85: =+O85-X85+Z85+AA85 -> 3000 | AD85: FIANZA 8/11 TRANSF
A86: 2 | B86: ADOLFO LOPEZ MARTINEZ | C86: VERSA|2020|ROJO|NLP172B | D86: OHLM032370108 | E86: =VLOOKUP(C86,'[2]CTRL AUTOS'!$E$2:$L$58,8,FALSE) -> ASHC | F86: =VLOOKUP(C86,'[2]CTRL AUTOS'!$E$2:$K$58,7,FALSE) -> ASHC | G86: UBER | H86: 0 | I86: 0 | J86: 0 | K86: 0 | L86: 0 | M86: 0 | N86: 0 | O86: =IF(H86+I86<0,SUM(J86:N86),SUM(H86:N86)) -> 0 | P86: -2500 | Q86: 0 | R86: 0 | S86: 0 | T86: 0 | U86: 0 | V86: 0 | W86: =SUM(O86:V86) -> -2500 | X86: =IF(W86>=0,W86,0) -> 0 | Y86: =IF(W86<=0,W86,0) -> -2500 | Z86: 2500 | AA86: =+Y86+Z86 -> 0 | AB86: =+O86-X86+Z86+AA86 -> 2500 | AD86: PAGA 2,500 13 ENE
A87: 2 | B87: NICASIO EMOS CONTRERAS | C87: AVEO|2025|PERSUASION|MZN057C | D87: OHLM038626735 | E87: =VLOOKUP(C87,'[2]CTRL AUTOS'!$E$2:$L$58,8,FALSE) -> ASHC | F87: =VLOOKUP(C87,'[2]CTRL AUTOS'!$E$2:$K$58,7,FALSE) -> ASHC | G87: UBER | H87: 0 | I87: 0 | J87: 0 | K87: 0 | L87: 0 | M87: 0 | N87: 0 | O87: =IF(H87+I87<0,SUM(J87:N87),SUM(H87:N87)) -> 0 | P87: -2000 | Q87: 0 | R87: 0 | S87: 0 | T87: 0 | U87: 0 | V87: 0 | W87: =SUM(O87:V87) -> -2000 | X87: =IF(W87>=0,W87,0) -> 0 | Y87: =IF(W87<=0,W87,0) -> -2000 | Z87: 2000 | AA87: =+Y87+Z87 -> 0 | AB87: =+O87-X87+Z87+AA87 -> 2000 | AD87: PAGO 14 ENE 2000
A88: 2 | B88: JOSE LUIS HERNANDEZ MEDINA | C88: AVEO|2018|GRIS|X59AWG | D88: OHLM031409063 | E88: =VLOOKUP(C88,'[2]CTRL AUTOS'!$E$2:$L$58,8,FALSE) -> ASHC | F88: =VLOOKUP(C88,'[2]CTRL AUTOS'!$E$2:$K$58,7,FALSE) -> ASHC | G88: UBER | H88: 0 | I88: 0 | J88: 0 | K88: 0 | L88: 0 | M88: 0 | N88: 0 | O88: =IF(H88+I88<0,SUM(J88:N88),SUM(H88:N88)) -> 0 | P88: 0 | Q88: 0 | R88: 0 | S88: 0 | T88: -700 | U88: 0 | V88: 0 | W88: =SUM(O88:V88) -> -700 | X88: =IF(W88>=0,W88,0) -> 0 | Y88: =IF(W88<=0,W88,0) -> -700 | Z88: 700 | AA88: =+Y88+Z88 -> 0 | AB88: =+O88-X88+Z88+AA88 -> 700 | AD88: HOJALATERIA 13 DE 15
A89: 2 | B89: JOSE AGUILAR SOTO | C89: AVEO|2020|AZUL|D28BET | D89: OHLM032370140 | E89: =VLOOKUP(C89,'[2]CTRL AUTOS'!$E$2:$L$58,8,FALSE) -> ASHC | F89: =VLOOKUP(C89,'[2]CTRL AUTOS'!$E$2:$K$58,7,FALSE) -> ASHC | G89: UBER | H89: 0 | I89: 0 | J89: 0 | K89: 0 | L89: 0 | M89: 0 | N89: 0 | O89: =IF(H89+I89<0,SUM(J89:N89),SUM(H89:N89)) -> 0 | P89: 0 | Q89: 0 | R89: 500 | S89: 0 | T89: 0 | U89: 0 | V89: 0 | W89: =SUM(O89:V89) -> 500 | X89: =IF(W89>=0,W89,0) -> 500 | Y89: =IF(W89<=0,W89,0) -> 0 | Z89: 0 | AA89: =+Y89+Z89 -> 0 | AB89: =+O89-X89+Z89+AA89 -> -500 | AD89: DEV FIANZA 8/10 PAGO 14 ENE
A90: 2 | B90: FIDEL ALEJANDRO SANCHEZ VERGARA | C90: VERSA|2023|PLATA|NCT814A | D90: OHLM031491780 | E90: =VLOOKUP(C90,'[2]CTRL AUTOS'!$E$2:$L$58,8,FALSE) -> ASHC | F90: =VLOOKUP(C90,'[2]CTRL AUTOS'!$E$2:$K$58,7,FALSE) -> ASHC | G90: UBER | H90: 0 | I90: 0 | J90: 0 | K90: 0 | L90: 0 | M90: 0 | N90: 0 | O90: =IF(H90+I90<0,SUM(J90:N90),SUM(H90:N90)) -> 0 | P90: 0 | Q90: 0 | R90: 500 | S90: 0 | T90: 0 | U90: 0 | V90: 0 | W90: =SUM(O90:V90) -> 500 | X90: =IF(W90>=0,W90,0) -> 500 | Y90: =IF(W90<=0,W90,0) -> 0 | Z90: 0 | AA90: =+Y90+Z90 -> 0 | AB90: =+O90-X90+Z90+AA90 -> -500 | AD90: DEV DE FIANZA 4/7
A91: 2 | B91: RUBI ROBLES SALMERON | C91: BEAT|2020|GRIS|NFN014B | D91: OHLM032762148 | E91: =VLOOKUP(C91,'[2]CTRL AUTOS'!$E$2:$L$58,8,FALSE) -> U64 | F91: =VLOOKUP(C91,'[2]CTRL AUTOS'!$E$2:$K$58,7,FALSE) -> BYER | G91: UBER | H91: 1239.72 | I91: -477.02 | J91: 0 | K91: 0 | L91: 0 | M91: -13 | N91: 0 | O91: =IF(H91+I91<0,SUM(J91:N91),SUM(H91:N91)) -> 749.7 | P91: =(-2500/7)*3 -> -1071.4286 | Q91: 0 | R91: 0 | S91: 0 | T91: 0 | U91: 0 | V91: 0 | W91: =SUM(O91:V91) -> -321.72857 | X91: =IF(W91>=0,W91,0) -> 0 | Y91: =IF(W91<=0,W91,0) -> -321.72857 | Z91: 0 | AA91: =+Y91+Z91 -> -321.72857 | AB91: =+O91-X91+Z91+AA91 -> 427.97143 | AD91: CTA PROP 3 DÍAS SE PASA A ASHC
A92: 2 | B92: ALFONSO GONZALEZ MORALES | C92: SWIFT|2017|ROJO|X89ALV | D92: OHLM032370090 | E92: =VLOOKUP(C92,'[2]CTRL AUTOS'!$E$2:$L$58,8,FALSE) -> BYER | F92: =VLOOKUP(C92,'[2]CTRL AUTOS'!$E$2:$K$58,7,FALSE) -> BYER | G92: UBER | H92: 4267.65 | I92: -1721.5 | J92: 0 | K92: 0 | L92: 0 | M92: -65 | N92: 0 | O92: =IF(H92+I92<0,SUM(J92:N92),SUM(H92:N92)) -> 2481.15 | P92: -2500 | Q92: 0 | R92: 0 | S92: 0 | T92: -700 | U92: 0 | V92: 0 | W92: =SUM(O92:V92) -> -718.85 | X92: =IF(W92>=0,W92,0) -> 0 | Y92: =IF(W92<=0,W92,0) -> -718.85 | Z92: 0 | AA92: =+Y92+Z92 -> -718.85 | AB92: =+O92-X92+Z92+AA92 -> 1762.3 | AD92: ULTIMO PAGO HOJALATERIA EN VISTO
A93: 2 | B93: FERNANDO GARRIDO GARNICA | C93: AVEO|2018|ROJO|R51BKD | D93: OHLM032762106 | E93: =VLOOKUP(C93,'[2]CTRL AUTOS'!$E$2:$L$58,8,FALSE) -> U64 | F93: =VLOOKUP(C93,'[2]CTRL AUTOS'!$E$2:$K$58,7,FALSE) -> BYER | G93: UBER | H93: 3021.98 | I93: -1761.68 | J93: 0 | K93: 0 | L93: 0 | M93: -65 | N93: 0 | O93: =IF(H93+I93<0,SUM(J93:N93),SUM(H93:N93)) -> 1195.3 | P93: -2500 | Q93: =-184*1.12 -> -206.08 | R93: -500 | S93: 0 | T93: 0 | U93: 0 | V93: 0 | W93: =SUM(O93:V93) -> -2010.78 | X93: =IF(W93>=0,W93,0) -> 0 | Y93: =IF(W93<=0,W93,0) -> -2010.78 | Z93: 0 | AA93: =+Y93+Z93 -> -2010.78 | AB93: =+O93-X93+Z93+AA93 -> -815.48 | AD93: NO CONTESTA
A94: 2 | B94: GABRIEL JIMENEZ BAUTISTA | C94: BYD|2026|VERDE|78F032 | D94: OHLM038628194 | E94: =VLOOKUP(C94,'[2]CTRL AUTOS'!$E$2:$L$58,8,FALSE) -> ASHC | F94: BYER | G94: UBER | H94: 5181.27 | I94: 0 | J94: 0 | K94: 9.79 | L94: 0 | M94: 0 | N94: 0 | O94: =IF(H94+I94<0,SUM(J94:N94),SUM(H94:N94)) -> 5191.06 | P94: -5191 | Q94: 0 | R94: 0 | S94: 0 | T94: 0 | U94: 0 | V94: 0 | W94: =SUM(O94:V94) -> 0.06 | X94: =IF(W94>=0,W94,0) -> 0.06 | Y94: =IF(W94<=0,W94,0) -> 0 | Z94: 0 | AA94: =+Y94+Z94 -> 0 | AB94: =+O94-X94+Z94+AA94 -> 5191 | AD94: GOLPE KIA Y BYD PENDIENTE CON ASHC
A95: 2 | B95: IVAN MOGUEL PULIDO | C95: KIA RIO|2023|ROJO|H99BLC | D95: OHLM035993526 | E95: =VLOOKUP(C95,'[2]CTRL AUTOS'!$E$2:$L$58,8,FALSE) -> U64 | F95: =VLOOKUP(C95,'[2]CTRL AUTOS'!$E$2:$K$58,7,FALSE) -> BYER | G95: UBER | H95: 7676.14 | I95: -2792.78 | J95: -80 | K95: 19.58 | L95: -84.32 | M95: -65 | N95: 0 | O95: =IF(H95+I95<0,SUM(J95:N95),SUM(H95:N95)) -> 4673.62 | P95: -1250 | Q95: 0 | R95: 0 | S95: 0 | T95: 0 | U95: 0 | V95: 0 | W95: =SUM(O95:V95) -> 3423.62 | X95: =IF(W95>=0,W95,0) -> 3423.62 | Y95: =IF(W95<=0,W95,0) -> 0 | Z95: 0 | AA95: =+Y95+Z95 -> 0 | AB95: =+O95-X95+Z95+AA95 -> 1250 | AD95: REDUCCION DE CTA 2/2
A96: 2 | B96: VICTOR HUGO RUIZ CASTILLO | C96: VERSA|2021|BLANCO|MEE228C | D96: OHLM036759082 | E96: =VLOOKUP(C96,'[2]CTRL AUTOS'!$E$2:$L$58,8,FALSE) -> ASHC | F96: BYER | G96: UBER | H96: 131.11 | I96: 0 | J96: 0 | K96: 0 | L96: -1.48 | M96: -40 | N96: 0 | O96: =IF(H96+I96<0,SUM(J96:N96),SUM(H96:N96)) -> 89.63 | P96: =(-2500/7)*4 -> -1428.5714 | Q96: =-142*1.12 -> -159.04 | R96: -500 | S96: 0 | T96: 0 | U96: 0 | V96: 0 | W96: =SUM(O96:V96) -> -1997.9814 | X96: =IF(W96>=0,W96,0) -> 0 | Y96: =IF(W96<=0,W96,0) -> -1997.9814 | Z96: 694 | AA96: =+Y96+Z96 -> -1303.9814 | AB96: =+O96-X96+Z96+AA96 -> -520.35143 | AD96: GOLPE FASCIA PENDIENTE 1500 POR KIA, PEND Q CONFIRME SEM DE ARREGLO PAGA 16
A97: 2 | B97: TOLENTINO JOSETH PEREZ GONZALEZ | C97: MARCH|2019|TURQ|MAY737C | D97: OHLM0367590666 | E97: =VLOOKUP(C97,'[2]CTRL AUTOS'!$E$2:$L$58,8,FALSE) -> BYER | F97: =VLOOKUP(C97,'[2]CTRL AUTOS'!$E$2:$K$58,7,FALSE) -> BYER | G97: UBER | H97: 2542.21 | I97: -328.85 | J97: 0 | K97: 0 | L97: -26.74 | M97: -35 | N97: 0 | O97: =IF(H97+I97<0,SUM(J97:N97),SUM(H97:N97)) -> 2151.62 | P97: -2500 | Q97: =-3752*1.12 -> -4202.24 | R97: 0 | S97: 0 | T97: 0 | U97: 0 | V97: 0 | W97: =SUM(O97:V97) -> -4550.62 | X97: =IF(W97>=0,W97,0) -> 0 | Y97: =IF(W97<=0,W97,0) -> -4550.62 | Z97: 0 | AA97: =+Y97+Z97 -> -4550.62 | AB97: =+O97-X97+Z97+AA97 -> -2399 | AD97: PROMESA DE PAGO 19 ENE ACUERDO CON BYER
A98: 2 | B98: OSCAR CONTRERAS ZUÑIGA | C98: AVEO|2022|VINO|P62BHW | D98: OHLM037480340 | E98: =VLOOKUP(C98,'[2]CTRL AUTOS'!$E$2:$L$58,8,FALSE) -> ASHC | F98: BYER | G98: UBER | H98: 11557.6 | I98: -5195.35 | J98: -64 | K98: 0 | L98: 0 | M98: -72 | N98: 0 | O98: =IF(H98+I98<0,SUM(J98:N98),SUM(H98:N98)) -> 6226.25 | P98: -2500 | Q98: 0 | R98: -500 | S98: 0 | T98: 0 | U98: 0 | V98: 0 | W98: =SUM(O98:V98) -> 3226.25 | X98: =IF(W98>=0,W98,0) -> 3226.25 | Y98: =IF(W98<=0,W98,0) -> 0 | Z98: 0 | AA98: =+Y98+Z98 -> 0 | AB98: =+O98-X98+Z98+AA98 -> 3000
A99: 2 | B99: YOSHUA JARETH VALDEZ HERNANDEZ | C99: KIA RIO|2017|ROJO|MYE912A | D99: OHLM032762130 | E99: =VLOOKUP(C99,'[2]CTRL AUTOS'!$E$2:$L$58,8,FALSE) -> U64 | F99: =VLOOKUP(C99,'[2]CTRL AUTOS'!$E$2:$K$58,7,FALSE) -> BYER | G99: UBER | H99: 2249.15 | I99: -238.94 | J99: 0 | K99: 0 | L99: 0 | M99: -20 | N99: 0 | O99: =IF(H99+I99<0,SUM(J99:N99),SUM(H99:N99)) -> 1990.21 | P99: -2500 | Q99: 0 | R99: 0 | S99: 0 | T99: 0 | U99: 0 | V99: 0 | W99: =SUM(O99:V99) -> -509.79 | X99: =IF(W99>=0,W99,0) -> 0 | Y99: =IF(W99<=0,W99,0) -> -509.79 | Z99: 510 | AA99: =+Y99+Z99 -> 0.21 | AB99: =+O99-X99+Z99+AA99 -> 2500.42 | AD99: PENDIENTE CAMBIO DE COCHE VENTO O KIA PAGO 16 ENE 510
A100: 2 | B100: JUAN PABLO COLIN HERMENEGILDO | C100: VENTO|2017|GRIS|MMA672C | D100: OHLM023720279 | E100: =VLOOKUP(C100,'[2]CTRL AUTOS'!$E$2:$L$58,8,FALSE) -> ASHC | F100: BYER | G100: UBER | H100: 411.71 | I100: -106.37 | J100: 0 | K100: 0 | L100: 0 | M100: -19 | N100: 0 | O100: =IF(H100+I100<0,SUM(J100:N100),SUM(H100:N100)) -> 286.34 | P100: =(-2300/7)*1.5 -> -492.85714 | Q100: 0 | R100: 0 | S100: 0 | T100: 0 | U100: 0 | V100: 0 | W100: =SUM(O100:V100) -> -206.51714 | X100: =IF(W100>=0,W100,0) -> 0 | Y100: =IF(W100<=0,W100,0) -> -206.51714 | Z100: 207 | AA100: =+Y100+Z100 -> 0.48285714 | AB100: =+O100-X100+Z100+AA100 -> 493.82286 | AD100: INGRESA MIE 7 SE CONSIDERA 1.5 DÍAS PAGO 14 ENE 207
...

Sheet CONDUCTORES
B1: SEM | C1: CONDUCTOR | D1: AUTO | E1: ASHC
B2: 1 | C2: ALEJANDRO PAZ CAMACHO | D2: MARCH|2020|TURQ|N15BKD | E2: ASHC
B3: 1 | C3: RAUL FRANCISCO VAZQUEZ CORTE | D3: V DRIVE|2023|GRIS|MXW453C | E3: ASHC
B4: 1 | C4: FRANCISCO RODOLFO GOMEZ URQUIZA ESCALANTE | D4: KIA RIO|2020|AZUL|LUE960C | E4: U64
B5: 1 | C5: FRANCISCO ISLAS CHAVEZ | D5: AVEO|2024|GRIS|LRL009C | E5: ASHC
B6: 1 | C6: ADALBERTO BELLO NAVARRO | D6: AVEO|2025|PERSUASION|MXM510C | E6: ASHC
B7: 1 | C7: ADRIAN CRUZ CUADROS | D7: AVEO|2025|PERSUASION|MXM503C | E7: ASHC
B8: 1 | C8: ALBERTO ARRIAGA MEJIA | D8: AVEO|2020|AZUL|D28BET | E8: ASHC
B9: 1 | C9: ANGEL ALCANTARA CRUZ | D9: AVEO|2025|PERSUASION|MZN091C | E9: ASHC
B10: 1 | C10: ARMANDO MARTINEZ VELAZQUEZ | D10: HYUNDAI|2022|PLATA|D40BKD | E10: ASHC
B11: 1 | C11: CAMILO IESUA MEJIA DIAZ | D11: KIA RIO|2020|GRIS|NCK475B | E11: ASHC
B12: 1 | C12: DAVID ARTURO GONZALEZ TELLEZ | D12: AVEO|2025|PERSUASION|MXM502C | E12: U64
B13: 1 | C13: FERNANDO FUENTES OTERO | D13: AVEOH|2024|BLANCO|MWV156C | E13: ASHC
... B474: 8 | C474: FERNANDO OSORNIO VILLASANA | D474: AVEO|2019|PLATA|NEL860A | E474: ASHC
B475: 8 | C475: ULISES SANCHEZ HERNANDEZ | E475: ASHC
B476: 9 | C476: ALEJANDRO VELAZQUEZ VARGAS | D476: AVEO|2022|AZUL|NZY685B | E476: ASHC
B477: 9 | C477: JOSE LUIS PEDRAZA AVILA | D477: AVEO|2019|PLATA|NEL860A | E477: JGD
B478: 9 | C478: ALAN AURELIO ORTEGA ORDOÑEZ | D478: BEAT|2019|OCRE|MAY730C | E478: ASHC
B479: 9 | C479: EMILIANO SOLANO SALAZAR | D479: AVEO|2019|BLANCO|NBS225A | E479: ASHC
B480: 9 | C480: EMILIANO SOLANO SALAZAR | D480: AVEOH|2026|ROJO|NEZ101C | E480: ASHC
B481: 9 | C481: RAUL NABOR MORIN MEJIA | D481: AVEO|2018|GRIS|X59AWG | E481: BYER
B482: 9 | C482: JOSE PABLO AGUILAR HERNANDEZ | D482: AVEO|2025|PERSUASION|MXM502C | E482: JGD
B483: 9 | C483: IVAN GENARO BOCANEGRA MARTINEZ | D483: AVEOH|2026|ROJO|NEZ101C | E483: ASHC
B484: 9 | C484: JOSE JUAN HERNANDEZ MEJIA | D484: AVEO|2025|PERSUASION|MXM502C | E484: ASHC
B485: 9 | C485: JORGE ALEJANDRO HERNANDEZ VALLEJO | D485: VERSA|2020|BLANCO|A35BHD | E485: ASHC
B486: 9 | C486: JUAN CARLOS CASTRO CASTILLO | D486: VERSA|2021|BLANCO|MEE228C | E486: ASHC
B487: 9 | C487: JORGE LUIS MEJIA LEOBARDO | D487: AVEO|2018|ROJO|R51BKD | E487: ASHC
... B541: 9 | C541: ABRAHAM RODRIGUEZ HERNANDEZ | D541: VENTO|2019|BLANCO|LUE965C | E541: U64
B542: 9 | C542: ULISES SANCHEZ HERNANDEZ | E542: U64
B543: 9 | C543: PEDRO ARELLANO PEREZ | D543: AVEO|2022|AZUL|MUF515A | E543: ASHC
B544: 9 | C544: LUIS AXEL RODRIGUEZ RANGEL | D544: AVEO|2019|BLANCO|NBS225A | E544: ASHC
B545: 9 | C545: FREDY PANTALEON VILLALOBOS | D545: AVEO|2019|BLANCO|NBS225A | E545: ASHC
B546: 9 | C546: CESAR AXEL SANTIAGO GARCIA | D546: VERSA|2020|BLANCO|A35BHD | E546: ASHC
B547: 9 | C547: EMMANUEL LARA HERNANDEZ | D547: BMW|2025|NEGRA|40K216 | E547: ASHC
B548: 9 | C548: ANTONIO GUZMAN BARRON | E548: JGD
B549: 10 | C549: VERONICA POBLANO LOPEZ | D549: MARCH|2019|TURQ|MAY737C | E549: JGD
B550: 10 | C550: ABRAHAM RODRIGUEZ HERNANDEZ | D550: VERSA|2022|GRIS|NES596C | E550: ASHC
B551: 10 | C551: ROBERTO HERNANDEZ GRANADOS | D551: MARCH|2019|TURQ|MAY737C | E551: ASHC
B552: 10 | C552: ALEJANDRO VELAZQUEZ VARGAS | D552: AVEO|2022|AZUL|NZY685B | E552: BYER
B553: 10 | C553: JOSE LUIS PEDRAZA AVILA | D553: AVEO|2019|PLATA|NEL860A | E553: ASHC
B554: 10 | C554: ALAN AURELIO ORTEGA ORDOÑEZ | D554: BEAT|2019|OCRE|MAY730C | E554: ASHC
B555: 10 | C555: EMILIANO SOLANO SALAZAR | D555: AVEOH|2026|ROJO|NEZ101C | E555: ASHC
B556: 10 | C556: RAUL NABOR MORIN MEJIA | D556: AVEO|2018|GRIS|X59AWG | E556: U64
B557: 10 | C557: JOSE PABLO AGUILAR HERNANDEZ | D557: AVEO|2025|PERSUASION|MXM502C | E557: ASHC
B558: 10 | C558: JORGE ALEJANDRO HERNANDEZ VALLEJO | D558: VERSA|2020|BLANCO|A35BHD | E558: ASHC
B559: 10 | C559: JUAN CARLOS CASTRO CASTILLO | D559: VERSA|2021|BLANCO|MEE228C | E559: ASHC
B560: 10 | C560: JORGE LUIS MEJIA LEOBARDO | D560: AVEO|2018|ROJO|R51BKD | E560: ASHC
... B621: 11 | C621: JOSE LUIS PEDRAZA AVILA | D621: AVEO|2019|PLATA|NEL860A | E621: JGD
B622: 11 | C622: ALAN AURELIO ORTEGA ORDOÑEZ | D622: #N/A | E622: ASHC
B623: 11 | C623: EMILIANO SOLANO SALAZAR | D623: AVEOH|2026|ROJO|NEZ101C | E623: ASHC
B624: 11 | C624: RAUL NABOR MORIN MEJIA | D624: AVEO|2018|GRIS|X59AWG | E624: BYER
B625: 11 | C625: JOSE PABLO AGUILAR HERNANDEZ | D625: AVEO|2025|PERSUASION|MXM502C | E625: ASHC
B626: 11 | C626: JORGE ALEJANDRO HERNANDEZ VALLEJO | D626: VERSA|2020|BLANCO|A35BHD | E626: U64
B627: 11 | C627: JUAN CARLOS CASTRO CASTILLO | D627: VERSA|2021|BLANCO|MEE228C | E627: ASHC
B628: 11 | C628: JORGE LUIS MEJIA LEOBARDO | D628: AVEO|2018|ROJO|R51BKD | E628: ASHC
B629: 11 | C629: VICTOR HUGO RUIZ CASTILLO | D629: AVEO|2019|PLATA|NEL860A | E629: ASHC
B630: 11 | C630: ALBERTO ARRIAGA MEJIA | D630: AVEOH|2026|BLANCO|NJG467C | E630: U64
B631: 11 | C631: ADOLFO ANGEL ESTRADA RODRIGUEZ | D631: AVEO|2024|GRIS|LRL009C | E631: ASHC
B632: 11 | C632: ADOLFO LOPEZ MARTINEZ | D632: VERSA|2020|ROJO|NLP172B | E632: ASHC
B633: 11 | C633: ADRIAN CRUZ CUADROS | D633: AVEO|2025|PERSUASION|MXM503C | E633: ASHC
B634: 11 | C634: ALEJANDRA URBAN VALENCIA | D634: VENTO|2020|GRIS|A19BDY | E634: ASHC
... B682: 11 | C682: VERONICA POBLANO LOPEZ | D682: MARCH|2019|TURQ|MAY737C | E682: ASHC
E683: ASHC
E684: U64
E685: ASHC
E686: JGD
E687: ASHC
E688: ASHC
E689: ASHC
E690: ASHC
E691: U64
E692: U64
E693: ASHC
E694: JGD
... E1353: ASHC

Sheet BASE DATOS
A1: AÑO | B1: SEM | C1: CONDUCTOR | D1: AUTO | E1: SOCIO | F1: PLATAFORMA | G1: APP | H1: GANANCIAS TOTALES | I1: META | J1: FIANZA | K1: COMENTARIO
A2: 2025 | B2: 1 | C2: ADOLFO LOPEZ MARTINEZ | D2: AVEO|2021|OCRE|NEB156A | E2: ASHC | F2: IVETH | G2: UBER | H2: 2143.1396 | I2: 2500
A3: 2025 | B3: 1 | C3: ARACELI CASTILLO GUERRERO | D3: AVEO|2018|GRIS|X59AWG | E3: ASHC | F3: ASHC | G3: UBER | H3: 2142.85 | I3: 2500
A4: 2025 | B4: 1 | C4: CESAR PIÑA BARONA | D4: HYUNDAI|2022|PLATA|D40BKD | E4: ASHC | F4: IVETH | G4: UBER | H4: 2210.15 | I4: 2500
A5: 2025 | B5: 1 | C5: CLAUDIA LEAÑOS | D5: KIA RIO|2017|ROJO|MYE912A | E5: U64 | F5: ASHC | G5: UBER | H5: 2653.1484 | I5: 2500
A6: 2025 | B6: 1 | C6: IVAN MOGUEL PULIDO | D6: VERSA|2023|PLATA|NCT814A | E6: ASHC | F6: ASHC | G6: UBER | H6: 1214.28 | I6: 2500
A7: 2025 | B7: 1 | C7: JESUS AURELIO NUNGARAY CASTILLO | D7: VENTO|2020|GRIS|R66BER | E7: ASHC | F7: ASHC | G7: UBER | H7: 2827.0928 | I7: 2500
A8: 2025 | B8: 1 | C8: JORGE VAZQUEZ HERNANDEZ | D8: AVEO|2018|GRIS|X59AWG | E8: ASHC | F8: ASHC | G8: UBER | H8: 2142.85 | I8: 2500
A9: 2025 | B9: 1 | C9: JOSE GUADALUPE GARCIA MORALES | D9: MARCH|2020|TURQ|N15BKD | E9: ASHC | F9: ASHC | G9: UBER | H9: 2643.796 | I9: 2500
A10: 2025 | B10: 1 | C10: JOSE JUAN HERNANDEZ MEJIA | D10: VERSA|2017|ACERO|X24APU | E10: ASHC | F10: ASHC | G10: UBER | H10: 3018.6268 | I10: 2500
A11: 2025 | B11: 1 | C11: OSCAR BLANCAS NORIEGA | D11: VENTO|2017|GRIS|NZV7888 | E11: ASHC | F11: ASHC | G11: UBER | H11: 3534.468 | I11: 2500
A12: 2025 | B12: 1 | C12: ULISES ITIEL CASTILLO AVILA | D12: KIA RIO|2020|GRIS|NCK475B | E12: ASHC | F12: IVETH | G12: UBER | H12: 2142.85 | I12: 2500
A13: 2025 | B13: 2 | C13: ABRAHAM ESCOBEDO ESCALANTE | D13: BEAT|2020|GRIS|NFN014B | E13: U64 | F13: ASHC | G13: UBER | H13: -210.852 | I13: 2500
... A30: 2025 | B30: 3 | C30: ADOLFO LOPEZ MARTINEZ | D30: AVEO|2021|OCRE|NEB156A | E30: ASHC | F30: ASHC | G30: UBER | H30: 1071.62 | I30: 2500
A31: 2025 | B31: 3 | C31: ADOLFO LOPEZ MARTINEZ | D31: AVEO|2021|OCRE|NEB156A | E31: ASHC | F31: IVETH | G31: UBER | H31: 1429.2988
A32: 2025 | B32: 3 | C32: ARACELI CASTILLO GUERRERO | D32: AVEO|2018|GRIS|X59AWG | E32: ASHC | F32: ASHC | G32: UBER | H32: 2499.19 | I32: 2500
A33: 2025 | B33: 3 | C33: CESAR PIÑA BARONA | D33: HYUNDAI|2022|PLATA|D40BKD | E33: ASHC | F33: ASHC | G33: UBER | H33: 2371 | I33: 2500
A34: 2025 | B34: 3 | C34: CESAR PIÑA BARONA | D34: HYUNDAI|2022|PLATA|D40BKD | E34: ASHC | F34: IVETH | G34: UBER | H34: 1429
A35: 2025 | B35: 3 | C35: CLAUDIA LEAÑOS | D35: KIA RIO|2017|ROJO|MYE912A | E35: U64 | F35: ASHC | G35: UBER | H35: 0 | I35: 2500
A36: 2025 | B36: 3 | C36: DIEGO SANCHEZ | D36: VENTO|2020|GRIS|R66BER | E36: ASHC | F36: ASHC | G36: UBER | H36: 3019.8424 | I36: 2500
A37: 2025 | B37: 3 | C37: EDGAR GEOVANY URIBE | D37: AVEO|2019|PLATA|NEL860A | E37: ASHC | F37: ASHC | G37: UBER | H37: 3000 | I37: 2500
A38: 2025 | B38: 3 | C38: FERNANDO ESQUIVEL SOSA | D38: VENTO|2018|AMARILLO|PED1652 | E38: ASHC | F38: ASHC | G38: UBER | H38: 2468 | I38: 2500
A39: 2025 | B39: 3 | C39: IRAM HERNANDEZ | D39: AVEO|2022|AZUL|MUF515A | E39: ASHC | F39: ASHC | G39: UBER | H39: 2800 | I39: 2500
A40: 2025 | B40: 3 | C40: IVAN MOGUEL PULIDO | D40: VERSA|2023|PLATA|NCT814A | E40: ASHC | F40: ASHC | G40: UBER | H40: 4500 | I40: 2500
A41: 2025 | B41: 3 | C41: JORGE VAZQUEZ HERNANDEZ | D41: AVEO|2018|GRIS|X59AWG | E41: ASHC | F41: ASHC | G41: UBER | H41: 357.15 | I41: 2500
A42: 2025 | B42: 3 | C42: JOSE GUADALUPE GARCIA MORALES | D42: MARCH|2020|TURQ|N15BKD | E42: ASHC | F42: ASHC | G42: UBER | H42: 3654.5425 | I42: 2500
A43: 2025 | B43: 3 | C43: JOSE GUILLERMO HERNANDEZ RAMIREZ | D43: AVEO|2018|ROJO|R51BKD | E43: U64 | F43: ASHC | G43: UBER | H43: 3000 | I43: 2500
A44: 2025 | B44: 3 | C44: JOSE JUAN HERNANDEZ MEJIA | D44: VERSA|2017|ACERO|X24APU | E44: ASHC | F44: ASHC | G44: UBER | H44: 3558.2585 | I44: 2500
A45: 2025 | B45: 3 | C45: JUAN CARLOS MUÑOZ | D45: AVEO|2019|BLANCO|NBS225A | E45: ASHC | F45: IVETH | G45: UBER | H45: 1320.4816 | I45: 2500
A46: 2025 | B46: 3 | C46: OSCAR BLANCAS NORIEGA | D46: VENTO|2017|GRIS|NZV7888 | E46: ASHC | F46: ASHC | G46: UBER | H46: 2799.8493 | I46: 2500
A47: 2025 | B47: 3 | C47: ULISES ITIEL CASTILLO AVILA | D47: KIA RIO|2020|GRIS|NCK475B | E47: ASHC | F47: ASHC | G47: UBER | H47: 1071 | I47: 2500
A48: 2025 | B48: 3 | C48: ULISES ITIEL CASTILLO AVILA | D48: KIA RIO|2020|GRIS|NCK475B | E48: ASHC | F48: IVETH | G48: UBER | H48: 1429
A49: 2025 | B49: 4 | C49: ADOLFO LOPEZ MARTINEZ | D49: AVEO|2021|OCRE|NEB156A | E49: ASHC | F49: IVETH | G49: UBER | H49: 2500 | I49: 2500
A50: 2025 | B50: 4 | C50: ARACELI CASTILLO GUERRERO | D50: AVEO|2018|GRIS|X59AWG | E50: ASHC | F50: ASHC | G50: UBER | H50: -400 | I50: 2500
A51: 2025 | B51: 4 | C51: CESAR PIÑA BARONA | D51: HYUNDAI|2022|PLATA|D40BKD | E51: ASHC | F51: IVETH | G51: UBER | H51: -2500 | I51: 2500
A52: 2025 | B52: 4 | C52: DIEGO SANCHEZ | D52: VENTO|2020|GRIS|R66BER | E52: ASHC | F52: ASHC | G52: UBER | H52: 3000.1 | I52: 2500
A53: 2025 | B53: 4 | C53: EDGAR GEOVANY URIBE | D53: AVEO|2019|PLATA|NEL860A | E53: ASHC | F53: ASHC | G53: UBER | H53: 3000 | I53: 2500
A54: 2025 | B54: 4 | C54: FERNANDO ESQUIVEL SOSA | D54: VENTO|2018|AMARILLO|PED1652 | E54: ASHC | F54: ASHC | G54: UBER | H54: 3000 | I54: 2500
A55: 2025 | B55: 4 | C55: IRAM HERNANDEZ | D55: AVEO|2022|AZUL|MUF515A | E55: ASHC | F55: ASHC | G55: UBER | H55: 3000 | I55: 2500
A56: 2025 | B56: 4 | C56: IVAN MOGUEL PULIDO | D56: VERSA|2023|PLATA|NCT814A | E56: ASHC | F56: ASHC | G56: UBER | H56: 3000 | I56: 2500
A57: 2025 | B57: 4 | C57: JOSE GUADALUPE GARCIA MORALES | D57: MARCH|2020|TURQ|N15BKD | E57: ASHC | F57: ASHC | G57: UBER | H57: 1660.6 | I57: 2500
A58: 2025 | B58: 4 | C58: JOSE GUILLERMO HERNANDEZ RAMIREZ | D58: AVEO|2018|ROJO|R51BKD | E58: U64 | F58: ASHC | G58: UBER | H58: 2500 | I58: 2500
A59: 2025 | B59: 4 | C59: JOSE JUAN HERNANDEZ MEJIA | D59: VERSA|2017|ACERO|X24APU | E59: ASHC | F59: ASHC | G59: UBER | H59: 2883.1 | I59: 2500
A60: 2025 | B60: 4 | C60: JUAN CARLOS MUÑOZ | D60: AVEO|2019|BLANCO|NBS225A | E60: ASHC | F60: IVETH | G60: UBER | H60: 2500 | I60: 2500
... A123: 2025 | B123: 8 | C123: ULISES ITIEL CASTILLO AVILA | D123: KIA RIO|2020|GRIS|NCK475B | E123: ASHC | F123: IVETH | G123: UBER | H123: 357.14286 | I123: 2500
A124: 2025 | B124: 8 | C124: ULISES ITIEL CASTILLO AVILA | D124: KIA RIO|2020|GRIS|NCK475B | E124: ASHC | F124: IVETH | G124: UBER | H124: 0
A125: 2025 | B125: 9 | C125: ADOLFO LOPEZ MARTINEZ | D125: AVEO|2021|OCRE|NEB156A | E125: ASHC | F125: IVETH | G125: UBER | H125: 3000 | I125: 2500
A126: 2025 | B126: 9 | C126: CESAR PIÑA BARONA | D126: HYUNDAI|2022|PLATA|D40BKD | E126: ASHC | F126: IVETH | G126: UBER | H126: 2500.7
A127: 2025 | B127: 9 | C127: DAVID ARTURO GONZALEZ TELLEZ | D127: BEAT|2020|GRIS|NFN014B | E127: U64 | F127: ASHC | G127: UBER | H127: 2901 | I127: 2500
A128: 2025 | B128: 9 | C128: EDGAR GEOVANY URIBE | D128: AVEO|2019|PLATA|NEL860A | E128: ASHC | F128: ASHC | G128: UBER | H128: -500 | I128: 2500
A129: 2025 | B129: 9 | C129: FERNANDO ESQUIVEL SOSA | D129: AVEO|2019|BLANCO|NBS225A | E129: ASHC | F129: ASHC | G129: UBER | H129: -640.08899 | I129: 2500
A130: 2025 | B130: 9 | C130: IRAM HERNANDEZ | D130: AVEO|2022|AZUL|NZY685B | E130: ASHC | F130: ASHC | G130: UBER | H130: 2800 | I130: 2500
A131: 2025 | B131: 9 | C131: IVAN MOGUEL PULIDO | D131: VERSA|2023|PLATA|NCT814A | E131: ASHC | F131: ASHC | G131: UBER | H131: 3500 | I131: 2500
A132: 2025 | B132: 9 | C132: JESUS AURELIO NUNGARAY CASTILLO | D132: VENTO|2020|GRIS|R66BER | E132: ASHC | F132: ASHC | G132: UBER | H132: 5276.95 | I132: 2500
A133: 2025 | B133: 9 | C133: JOSE ALFREDO MUÑOZ | D133: KIA RIO|2017|ROJO|MYE912A | E133: U64 | F133: ASHC | G133: UBER | H133: 2850 | I133: 2500
A134: 2025 | B134: 9 | C134: JOSE GUADALUPE GARCIA MORALES | D134: MARCH|2020|TURQ|N15BKD | E134: ASHC | F134: ASHC | G134: UBER | H134: 2500 | I134: 2500
A135: 2025 | B135: 9 | C135: JOSE GUILLERMO HERNANDEZ RAMIREZ | D135: AVEO|2018|GRIS|X59AWG | E135: ASHC | F135: ASHC | G135: UBER | H135: 2542 | I135: 2500
A136: 2025 | B136: 9 | C136: JOSE JUAN HERNANDEZ MEJIA | D136: VERSA|2017|ACERO|X24APU | E136: ASHC | F136: ASHC | G136: UBER | H136: 2500 | I136: 2500
A137: 2025 | B137: 9 | C137: JULIO CESAR LOPEZ | D137: AVEO|2019|PLATA|NEL860A | E137: ASHC | F137: ASHC | G137: UBER | H137: 2794.1449 | I137: 2500
A138: 2025 | B138: 9 | C138: NESTOR NOE HERNANDEZ | D138: SWIFT|2017|ROJO|X89ALV | E138: BYER | F138: ASHC | G138: UBER | H138: -99.008571 | I138: 2500
... A237: 2025 | B237: 15 | C237: JESUS AURELIO NUNGARAY CASTILLO | D237: AVEO|2022|AZUL|NZY685B | E237: ASHC | F237: ASHC | G237: UBER | H237: 450 | I237: 2500
A238: 2025 | B238: 15 | C238: JESUS AURELIO NUNGARAY CASTILLO | D238: AVEO|2022|AZUL|NZY685B | E238: ASHC | F238: ASHC | G238: UBER | H238: 2
A239: 2025 | B239: 15 | C239: JOSE ALFREDO MUÑOZ | D239: KIA RIO|2017|ROJO|MYE912A | E239: U64 | F239: ASHC | G239: UBER | H239: 2350 | I239: 2500
A240: 2025 | B240: 15 | C240: JOSE GUADALUPE GARCIA MORALES | D240: MARCH|2020|TURQ|N15BKD | E240: ASHC | F240: ASHC | G240: UBER | H240: -314 | I240: 2500
A241: 2025 | B241: 15 | C241: JOSE GUILLERMO HERNANDEZ RAMIREZ | D241: AVEO|2018|GRIS|X59AWG | E241: ASHC | F241: ASHC | G241: UBER | H241: 2118 | I241: 2500
A242: 2025 | B242: 15 | C242: JOSE JUAN HERNANDEZ MEJIA | D242: VERSA|2017|ACERO|X24APU | E242: ASHC | F242: ASHC | G242: UBER | H242: 2500 | I242: 2500
A243: 2025 | B243: 15 | C243: MANUEL GARCIA MARTINEZ | D243: SWIFT|2017|ROJO|X89ALV | E243: BYER | F243: ASHC | G243: UBER | H243: 3000 | I243: 2500
A244: 2025 | B244: 15 | C244: OSCAR BLANCAS NORIEGA | D244: VENTO|2017|GRIS|NZV7888 | E244: ASHC | F244: ASHC | G244: UBER | H244: 2300 | I244: 2500
A245: 2025 | B245: 15 | C245: RAUL FRANCISCO VAZQUEZ CORTE | D245: AVEO|2019|BLANCO|NBS225A | E245: ASHC | F245: ASHC | G245: UBER | H245: 3000 | I245: 2500
A246: 2025 | B246: 15 | C246: YARETH ABRAHAM MORALES | D246: AVEO|2018|ROJO|R51BKD | E246: U64 | F246: ASHC | G246: UBER | H246: 2700 | I246: 2500
A247: 2025 | B247: 16 | C247: ADOLFO LOPEZ MARTINEZ | D247: AVEO|2021|OCRE|NEB156A | E247: ASHC | F247: ASHC | G247: UBER | H247: 2500 | I247: 2500
A248: 2025 | B248: 16 | C248: CESAR PIÑA BARONA | D248: HYUNDAI|2022|PLATA|D40BKD | E248: ASHC | F248: ASHC | G248: UBER | H248: 2449 | I248: 2500
A249: 2025 | B249: 16 | C249: DAVID ARTURO GONZALEZ TELLEZ | D249: KIA RIO|2020|GRIS|NCK475B | E249: ASHC | F249: ASHC | G249: UBER | H249: 2991 | I249: 2500
A250: 2025 | B250: 16 | C250: EDGAR DAMIAN MARTINEZ | D250: AVEO|2019|PLATA|NEL860A | E250: ASHC | F250: ASHC | G250: UBER | H250: 3300 | I250: 2500
... A315: 2025 | B315: 19 | C315: MARIA DEL CARMEN ALVARADO ALEJO | D315: AVEO|2018|ROJO|R51BKD | E315: U64 | F315: ASHC | G315: UBER | H315: 251 | I315: 2500
A316: 2025 | B316: 19 | C316: MARIA DEL CARMEN ALVARADO ALEJO | D316: AVEO|2018|ROJO|R51BKD | E316: U64 | F316: BYER | G316: UBER | H316: 1252
A317: 2025 | B317: 19 | C317: OSCAR BLANCAS NORIEGA | D317: VENTO|2017|GRIS|NZV7888 | E317: ASHC | F317: ASHC | G317: UBER | H317: 2300 | I317: 2500
A318: 2025 | B318: 19 | C318: RAUL FRANCISCO VAZQUEZ CORTE | D318: AVEO|2019|BLANCO|NBS225A | E318: ASHC | F318: ASHC | G318: UBER | H318: 2500 | I318: 2500
A319: 2025 | B319: 19 | C319: YARETH ABRAHAM MORALES | D319: MARCH|2021|ROJO|NZU5163 | E319: ASHC | F319: ASHC | G319: UBER | H319: 1869.1429 | I319: 2500
A320: 2025 | B320: 20 | C320: ADOLFO LOPEZ MARTINEZ | D320: VERSA|2020|BLANCO|A35BHD | E320: ASHC | F320: ASHC | G320: UBER | H320: 3000 | I320: 2500
A321: 2025 | B321: 20 | C321: ALEJANDRO CABALLERO POMPA | D321: HYUNDAI|2022|PLATA|D40BKD | E321: ASHC | F321: ASHC | G321: UBER | H321: 698 | I321: 2500
A322: 2025 | B322: 20 | C322: ALFONSO GONZALEZ MORALES | D322: AVEO|2020|AZUL|D28BET | E322: ASHC | F322: ASHC | G322: UBER | H322: 3000 | I322: 2500
A323: 2025 | B323: 20 | C323: DAVID ARTURO GONZALEZ TELLEZ | D323: KIA RIO|2020|GRIS|NCK475B | E323: ASHC | F323: ASHC | G323: UBER | H323: -500 | I323: 2500
A324: 2025 | B324: 20 | C324: EDGAR DAMIAN MARTINEZ | D324: AVEO|2019|PLATA|NEL860A | E324: ASHC | F324: ASHC | G324: UBER | H324: 1207 | I324: 2500
A325: 2025 | B325: 20 | C325: EDGAR GEOVANY URIBE | D325: AVEO|2019|PLATA|NEL860A | E325: ASHC | F325: ASHC | G325: UBER | H325: -1697 | I325: 2500
A326: 2025 | B326: 20 | C326: FERNANDO FUENTES OTERO | D326: VENTO|2020|GRIS|R66BER | E326: ASHC | F326: ASHC | G326: UBER | H326: 3000 | I326: 2500
A327: 2025 | B327: 20 | C327: IRAM HERNANDEZ | D327: VERSA|2020|ROJO|NLP172B | E327: ASHC | F327: ASHC | G327: UBER | H327: 2500 | I327: 2500
A328: 2025 | B328: 20 | C328: IVAN MOGUEL PULIDO | D328: AVEO|2022|AZUL|NZY685B | E328: ASHC | F328: ASHC | G328: UBER | H328: 3300 | I328: 2500
... A337: 2025 | B337: 20 | C337: MARIA DEL CARMEN ALVARADO ALEJO | D337: AVEO|2018|ROJO|R51BKD | E337: U64 | F337: ASHC | G337: UBER | H337: 182 | I337: 2500
A338: 2025 | B338: 20 | C338: MARIA DEL CARMEN ALVARADO ALEJO | D338: AVEO|2018|ROJO|R51BKD | E338: U64 | F338: BYER | G338: UBER | H338: 2281
A339: 2025 | B339: 20 | C339: OSCAR BLANCAS NORIEGA | D339: VENTO|2017|GRIS|NZV7888 | E339: ASHC | F339: ASHC | G339: UBER | H339: 2300 | I339: 2500
A340: 2025 | B340: 20 | C340: RAUL FRANCISCO VAZQUEZ CORTE | D340: AVEO|2019|BLANCO|NBS225A | E340: ASHC | F340: ASHC | G340: UBER | H340: 3100 | I340: 2500
A341: 2025 | B341: 20 | C341: YARETH ABRAHAM MORALES | D341: MARCH|2021|ROJO|NZU5163 | E341: ASHC | F341: ASHC | G341: UBER | H341: 286 | I341: 2500
A342: 2025 | B342: 21 | C342: ADOLFO LOPEZ MARTINEZ | D342: AVEO|2022|AZUL|NZY685B | E342: ASHC | F342: ASHC | G342: UBER | H342: 3000.2 | I342: 2500
A343: 2025 | B343: 21 | C343: ALEJANDRO CABALLERO POMPA | D343: HYUNDAI|2022|PLATA|D40BKD | E343: ASHC | F343: ASHC | G343: UBER | H343: 2364.52 | I343: 2500
A344: 2025 | B344: 21 | C344: ALFONSO GONZALEZ MORALES | D344: AVEO|2020|AZUL|D28BET | E344: ASHC | F344: ASHC | G344: UBER | H344: 3000 | I344: 2500
A345: 2025 | B345: 21 | C345: DAVID ARTURO GONZALEZ TELLEZ | D345: AVEO|2021|OCRE|NEB156A | E345: ASHC | F345: ASHC | G345: UBER | H345: 2463.92 | I345: 2500
A346: 2025 | B346: 21 | C346: EDGAR DAMIAN MARTINEZ | D346: KIA RIO|2017|ROJO|MYE912A | E346: U64 | F346: BYER | G346: UBER | H346: -113.68 | I346: 2500
A347: 2025 | B347: 21 | C347: EDGAR DAMIAN MARTINEZ | D347: KIA RIO|2017|ROJO|MYE912A | E347: U64 | F347: ASHC | G347: UBER | H347: -1677.6
A348: 2025 | B348: 21 | C348: EDGAR GEOVANY URIBE | D348: AVEO|2019|PLATA|NEL860A | E348: ASHC | F348: ASHC | G348: UBER | H348: -1697 | I348: 2500
...

Sheet TABLAS BARRAS 
B1: CONDUCTOR | C1: (Varios elementos)
B3: AÑO | C3: SEM | D3: Suma de GANANCIAS TOTALES | E3: Suma de FIANZA | F3: Cuenta de META
B4: 2025 | C4: 2 | D4: -210.852 | F4: 1
C5: 3 | D5: -1733.5504 | F5: 1
B6: Total 2025 | D6: -1944.4024 | F6: 2
B7: 2026 | C7: 3 | D7: 857.14286 | E7: 1000 | F7: 1
C8: 4 | D8: 2999.52 | F8: 1
C9: 5 | D9: 2963.8571 | F9: 1
C10: 6 | D10: 3199.78 | F10: 1
C11: 7 | D11: 3200.46 | F11: 1
C12: 8 | D12: 3199.76 | F12: 1
C13: 9 | D13: 2864.1429 | F13: 1
C14: 10 | D14: 3424.4 | F14: 1
C15: 11 | D15: 3014.1439 | F15: 1
C16: 12 | D16: 3399.66 | F16: 1
B17: Total 2026 | D17: 29122.867 | E17: 1000 | F17: 10
B18: Total general | D18: 27178.464 | E18: 1000 | F18: 12

Sheet CTRL AUTOS
A1: SEM | B1: CONDUCTOR | C1: AUTO
A2: 7 | B2: LUIS EDGARDO AYALA ALVAREZ | C2: VENTO|2020|GRIS|R66BER
A3: 7 | B3: SIN ASIGNAR | C3: AVEO|2022|AZUL|MUF515A
A4: 7 | B4: SIN ASIGNAR | C4: AVEO|2018|ROJO|R51BKD
A5: 7 | B5: VICTOR HUGO RUIZ CASTILLO | C5: AVEO|2019|PLATA|NEL860A
A6: 7 | B6: LUIS AXEL RODRIGUEZ RANGEL | C6: AVEO|2019|BLANCO|NBS225A
A7: 7 | B7: OSCAR IVAN MIÑON RAMIREZ | C7: MARCH|2020|TURQ|N15BKD
A8: 7 | B8: EDUARDO RIVERA LAVIN | C8: KIA RIO|2017|ROJO|MYE912A
A9: 7 | B9: SIN ASIGNAR | C9: AVEO|2018|GRIS|X59AWG
A10: 7 | B10: DAVID ROMERO JAIME | C10: BEAT|2020|GRIS|NFN014B
A11: 7 | B11: RODOLFO VILLEDA MACIAS | C11: VENTO|2017|GRIS|MMA672C
A12: 7 | B12: SAUL DOMINGUEZ VAZQUEZ | C12: VERSA|2023|PLATA|NCT814A
A13: 7 | B13: ARMANDO MARTINEZ VELAZQUEZ | C13: HYUNDAI|2022|PLATA|D40BKD
... A232: 3 | B232: OSCAR IVAN MIÑON RAMIREZ | C232: MARCH|2020|TURQ|N15BKD
A233: 3 | C233: KIA RIO|2017|ROJO|MYE912A
A234: 3 | B234: JONATHAN BERNAL RODRIGUEZ | C234: AVEO|2018|GRIS|X59AWG
A235: 3 | B235: DAVID ROMERO JAIME | C235: BEAT|2020|GRIS|NFN014B
A236: 3 | B236: YOSHUA JARETH VALDEZ HERNANDEZ | C236: VENTO|2017|GRIS|MMA672C
A237: 3 | B237: FRANCISCO GOMEZ URQUIZA SILVA | C237: VERSA|2023|PLATA|NCT814A
A238: 3 | B238: ARMANDO MARTINEZ VELAZQUEZ | C238: HYUNDAI|2022|PLATA|D40BKD
A239: 3 | B239: CAMILO IESUA MEJIA DIAZ | C239: KIA RIO|2020|GRIS|NCK475B
A240: 3 | B240: SERGIO BALDERAS BAEZ | C240: AVEO|2022|AZUL|NZY685B
A241: 3 | B241: SIN ASIGNAR | C241: VENTO|2018|AMARILLO|PED1652
A242: 3 | B242: EDUARDO LICONA GODINEZ | C242: KIA RIO|2020|ROJO|MFP751C
A243: 3 | B243: ADOLFO LOPEZ MARTINEZ | C243: VERSA|2020|ROJO|NLP172B
A244: 3 | B244: FRANCISCO ISLAS CHAVEZ | C244: AVEO|2024|GRIS|LRL009C
A245: 3 | B245: ALFONSO GONZALEZ | C245: SWIFT|2017|ROJO|X89ALV
... A274: 3 | B274: GERMAN LUSARRETA ROMERO | C274: AVEO|2026|ROJO|NEZ108C
A275: 3 | C275: AVEO H|2026|BLANCO
A276: 3 | C276: AVEO H|2026|BLANCO
A277: 3 | C277: AVEO H|2026|BLANCO
A278: 3 | C278: AVEO H|2026|BLANCO
A279: 3 | C279: AVEO H|2026|BLANCO
A280: 3 | C280: AVEO H|2026|BLANCO
A281: 2 | B281: KEVIN ALEXIS MERLOS CORTES | C281: VENTO|2020|GRIS|R66BER
A282: 2 | B282: XAVIER ALAN LARA JIMENEZ | C282: AVEO|2022|AZUL|MUF515A
A283: 2 | B283: FERNANDO GARRIDO GARNICA | C283: AVEO|2018|ROJO|R51BKD
A284: 2 | B284: JUAN CARLOS ZEA CRUZ | C284: AVEO|2019|PLATA|NEL860A
A285: 2 | B285: JOEL RAUL PEREA PEÑA | C285: AVEO|2019|BLANCO|NBS225A
A286: 2 | B286: OSCAR IVAN MIÑON RAMIREZ | C286: MARCH|2020|TURQ|N15BKD
A287: 2 | B287: YOSHUA JARETH VALDEZ HERNANDEZ | C287: KIA RIO|2017|ROJO|MYE912A
A288: 2 | B288: JONATHAN BERNAL RODRIGUEZ | C288: AVEO|2018|GRIS|X59AWG
A289: 2 | B289: RUBI ROBLES SALMERON | C289: BEAT|2020|GRIS|NFN014B
A290: 2 | B290: JUAN PABLO COLIN HERMENEGILDO | C290: VENTO|2017|GRIS|MMA672C
A291: 2 | B291: FRANCISCO GOMEZ URQUIZA SILVA | C291: VERSA|2023|PLATA|NCT814A
A292: 2 | B292: ARMANDO MARTINEZ VELAZQUEZ | C292: HYUNDAI|2022|PLATA|D40BKD
... A621: 11 | B621: SIN ASIGNAR | C621: BMW|2025|NEGRA|40K216

Sheet Hoja1
